Workbook

Sheet Disclaimer
B2: Disclaimer
B4: ="This Investor Presentation is provided for informational purposes only and does not constitute an offer to buy or a solicitation of an offer to invest, or to procure an investment in "&'Get Started'!D9&" (the “Company”)." -> This Investor Presentation is provided for informational purposes only and does not constitute an offer to buy or a solicitation of an offer to invest, or to procure an investment in 46387 (the “Company”).
B5: Investments in the Company, if offered, will only be offered to a selected number of accredited investors, and only on the basis of a private offering memorandum for the Company. There are significant risks that are not presented and disclosed in this Investor Presentation. These risks could have a significant negative impact on the performance of the Company.
B6: This Investor Presentation contains forward-looking statements regarding our business plans and prospects and financial conditions, all statements, other than statements of historical fact, in this Investor Presentation, and the attached exhibits, including, among other things, statements regarding our competitive strengths, business strategy, financial projections and plans and objectives of management are forward-looking statements. Although we believe that the expectations reflected in such forward-looking statements are reasonable, there can be no assurance that such expectations will prove to be correct. Forward-looking statements are inherently subject to risks and uncertainties, many of which cannot be predicted with accuracy and some of which might not even be anticipated. Future events and actual results, financial or otherwise, could differ materially from those set forth in, or contemplated by, the forward-looking statements in this Investor Presentation, and, as such, the forward-looking statements contained herein should not be relied upon when making your investment decision. We undertake no obligation to update or revise any forward-looking statements.
B7: The financial projections in this Investor Presentation present, to the best of management’s knowledge and belief, the Company’s expected financial position, results of operations, and cash flows for the forecast period. Accordingly, the financial projections reflect its judgment, as of the date of these financial projections, of the expected conditions and its expected course of action following the sale of securities by the Company. The assumptions disclosed herein are those that management believes are significant to the financial projections. There will usually be differences between the projected and actual results, because events and circumstances frequently do not occur as expected, and those differences may be material. Since the projections are based upon assumptions about circumstances and events that have not yet taken place regarding costs, income, expenses and federal tax matters, which are subject to variations and economic events as future operations actually occur, they do not necessarily reflect the results that will be achieved and should not be relied upon. In all cases, the targeted returns are not predictions or projections that the results in the pro forma financials will be achieved nor of the performance of any investment, and are expressly subject to all assumptions embedded in the pro forma financials and the risk factors disclosed herein. This investment has a high degree of risk, and there can be no assurances that all or any of the assumptions will be true or that an investment’s actual performance will bear any relation to these hypothetical illustrations.
B8: This information contained in this Investor Presentation includes proprietary information, is strictly confidential, and is not to be used or distributed to others without the express written consent of the Company.
B9: This document has been prepared solely for information purposes and is being furnished solely for use by prospective purchasers in considering their interest in obtaining additional information and making their own evaluation of the Company and does not contain all of the information that a prospective purchaser may desire. This information reflects various assumptions by the Company concerning anticipated results, which assumptions may or may not prove to be correct, and the Company has no obligation to update such information. The only information that will have any legal effect will be that specifically contained in definitive documentation. This Investor Presentation has been submitted confidentially to a limited number of investors so that they can consider their interest in obtaining additional information and making their own evaluation of the Company. No offers to purchase the securities of the Company will be accepted prior to (1) the receipt by recipient of a complete private offering memorandum and (2) determination by the Company that the recipient is an appropriate purchaser in light of standards contained in U.S. Securities laws after a full evaluation of recipient by the Company. The Company has not authorized its use for any other purpose. This Investor Presentation may not be copied or reproduced in whole or in part. By accepting a copy of this Investor Presentation, the recipient agrees that neither it nor any of its representatives, agents or employees shall use it for any other purpose or divulge to any party any confidential information about the Company.

Sheet Get Started
B2: Get Started | D2: NOT MAIN SUBMISSION DELIVERABLE Helps forecast impact of Team 3's reccomendations based on the limited info given by the client and comp based assumptions to measure the revenue and fiscal imapct on unit economics of the given changes
B3: Mauli illustration: supplied £87 AOV proxy; other inputs are reasonable assumptions.
B5: Setup and Timescale
B6: What is the name of your company? | D6: Mauli Rituals | F6: This is used in the Legal Disclaimer sheet, which is purely optional, but something many people choose to include in their projections when they provide them to potential investors
B7: What is your currency? | D7: £ | F7: Model works for any currency, as there are no currency-specific calculations in the model. This label is used in some presentation areas.
B8: What is the first date you want to forecast? | D8: ='Mauli sources'!C8 -> 46327 | F8: First month in the model; if this model is entirely a forecast of the future, input the first month you want to forecast from.
B9: What is the fiscal year end of the first year modeled? | D9: =DATE(YEAR(D8),12,31) -> 46387 | F9: Define the month that is the fiscal year end of the first year in the model. This allows you to set the fiscal years in the model, and thus the # of months in the first year forecasted in the model. The default setting uses a formula to return the year end (in December) from the first month in the forecast. Feel free to overwrite this to set a different fiscal year end, just overwrite the formula with a date.
B11: Historical Cohorts (Optional) | F11: Optional inputs, to use if you have historical cohort data you want to use to generate historical performance and baseline assumptions for future cohorts
B12: What is the first date in your historical data? | D12: =EOMONTH(D14,-24) -> 45596 | F12: The model is built to cover up to 48 months in the past, but (a) you do not have to go back that far, and (b) if you want to go back farther, the model can be edited to do that.
B13: What is the fiscal year end of the first year modeled? | D13: =DATE(YEAR(D12),12,31) -> 45657 | F13: used for the timescale formulas, same as the above
B14: What is the last date in your historical data? | D14: =EOMONTH(D8,-1) -> 46326 | F14: By structural default, this is assumed to be the month prior to the start of the forecast.
B16: Revenue and Marketing Assumptions
B17: ="Average Revenue per Order, new Customer" -> Average Revenue per Order, new Customer | C17: =D$7 -> £ | D17: ='Mauli sources'!C9 -> 87 | F17: Reported blended AOV £87 (challenge brief pp.3,9), unverified. New-customer AOV proxy only; period, VAT, refund and shipping basis unresolved.
B18: ="Average Revenue per Order, repeat Customer" -> Average Revenue per Order, repeat Customer | C18: =D$7 -> £ | D18: =D17 -> 87 | F18: Same £87 proxy for repeat AOV; no measured new/repeat split. Replaces the template 80% illustration, not a client finding.
B19: ="Baseline rate of change in "&B18 -> Baseline rate of change in Average Revenue per Order, repeat Customer | C19: % | D19: 0.1 | F19: this assumes the growth rate in the first month after growth starts, as defined above
B20: ="… where the rate "&IF(D20<0,"declines %",IF(D20>0,"increases %","stays the same"))&" per month" -> … where the rate declines % per month | C20: % | D20: -0.05 | F20: this changes the growth rate over time: you can assume a growth rate that increases over time, stays the same, or decreases (most common)
B22: Cost of Sales | C22: % | D22: 0.25 | F22: per order, as a % of revenues
B23: Additional Cost of Sales | C23: % | D23: 0.1 | F23: per order, as a % of revenues
B24: Additional Cost of Sales | C24: % | D24: 0 | F24: per order, as a % of revenues
B25: ="Baseline rate of change in "&B24 -> Baseline rate of change in Additional Cost of Sales | C25: % | D25: 0 | F25: this assumes the growth rate in the first month after growth starts, as defined above
B26: ="… where the rate "&IF(D26<0,"declines %",IF(D26>0,"increases %","stays the same"))&" per month" -> … where the rate stays the same per month | C26: % | D26: 0 | F26: this changes the growth rate over time: you can assume a growth rate that increases over time, stays the same, or decreases (most common)
B28: Shipping Revenue per order | C28: =D$7 -> £ | D28: 0 | F28: revenue earned from charging for shipping to end customer, per order
B29: Shipping Cost per order | C29: =D$7 -> £ | D29: 0 | F29: costs for shipping to end customer, per order
B31: Customer Acquisition Cost (CAC), new customer | C31: =D$7 -> £ | D31: 30 | F31: ="Customer acquisition cost, per new order" -> Customer acquisition cost, per new order
B32: Customer Acquisition Cost (CAC), repeat customer | C32: =D$7 -> £ | D32: 10 | F32: retention cost per subscriber, per renew cycle. Intention is to include cost to market to existing subscribers to increase retention
B33: ="Baseline rate of change in "&B32 -> Baseline rate of change in Customer Acquisition Cost (CAC), repeat customer | C33: % | D33: 0 | F33: this assumes the rate in the first month after starts, as defined above
B34: ="… where the rate "&IF(D34<0,"declines %",IF(D34>0,"increases %","stays the same"))&" per month" -> … where the rate stays the same per month | C34: % | D34: 0 | F34: this changes the rate over time: you can assume a rate that increases over time, stays the same, or decreases (most common)
B36: Growth and Churn Assumptions
B37: Date to start growth and revenues | D37: =D8 -> 46327 | F37: date to start growth of revenues, used on Forecast sheet in Growth section
B38: New Customers | C38: # | D38: 550 | F38: use the input to change the label, the number input refers to the # new in the first month, as defined above
B39: ="Baseline growth rate in "&B38 -> Baseline growth rate in New Customers | C39: % | D39: 0.9 | F39: this assumes the growth rate in the first month after growth starts, as defined above
B40: ="… where the growth rate "&IF(D40<0,"declines %",IF(D40>0,"increases %","stays the same"))&" per month" -> … where the growth rate declines % per month | C40: % | D40: -0.15 | F40: this changes the growth rate over time: you can assume a growth rate that increases over time, stays the same, or decreases (most common)
B41: Conversion Rate | C41: % | D41: 0.02 | F41: % of website sessions that convert to orders
B42: Customers, beginning of first month | C42: # | D42: 0 | F42: assume the # of new customers that have been acquired prior to the start of the forecast; this is useful if you have an existing base of customers making repeat orders and want to introduce that into the model's forecast of new and repeat orders
B43: Churn rate, per period | C43: % | D43: 0.5 | F43: % of customers that do not make a repeat order, on each repeat cycle
B44: Repeat Cycle | C44: # | D44: 3 | F44: If customers place repeat orders, the # of months to a repeat order. this sets the cadence of repeat orders, and combines with the churn assumption to forecast the # of repeat orders. Important to note is that if you assume a repeat rate, your repeat purchases is bounded by the web sessions and conversion rate. e.g., web sessions * conversion rate = orders. orders - repeat orders = new orders. so if you do not grow web sessions and you assume repeat purchases, it's possible to create a forecast that includes zero orders from new customers. if that happens, reduce your repeat rate, increase your churn, or increase your top-line web sessions growth
B47: After N total customers | C47: # | D47: 0 | F47: optional input to adjust the cohort performance based on total company size, not just per cohort performance
B48: Change cohort performance by | C48: # | D48: 1 | F48: optional adjustment that is applied based on the condition above. "1" means no change, 1.2 means it is 20% better, 0.8 is 20% worse, for example

Sheet Key Reports
B1: ILLUSTRATION ONLY: £87 reported AOV proxy; all other inputs remain assumptions.
B24: Profit and Loss | I24: Orders, per period
B25: by year | I25: Orders from new customers and repeat customers, by year

Sheet Forecast
B2: Forecast
B4: Date | C4: Unit | D4: Note | T4: =EOMONTH('Get Started'!D8,0) -> 46356 | U4: =EOMONTH(EDATE(T4,1),0) -> 46387 | V4: =EOMONTH(EDATE(U4,1),0) -> 46418 | W4: =EOMONTH(EDATE(V4,1),0) -> 46446 | X4: =EOMONTH(EDATE(W4,1),0) -> 46477 | Y4: =EOMONTH(EDATE(X4,1),0) -> 46507 | Z4: =EOMONTH(EDATE(Y4,1),0) -> 46538 | AA4: =EOMONTH(EDATE(Z4,1),0) -> 46568 | AB4: =EOMONTH(EDATE(AA4,1),0) -> 46599 | ... BO4: =EOMONTH(EDATE(BN4,1),0) -> 47787
B5: Timestep | C5: # | D5: where the first month in the period = 0 | T5: 0 | U5: =T5+1 -> 1 | V5: =U5+1 -> 2 | W5: =V5+1 -> 3 | X5: =W5+1 -> 4 | Y5: =X5+1 -> 5 | Z5: =Y5+1 -> 6 | AA5: =Z5+1 -> 7 | AB5: =AA5+1 -> 8 | ... BO5: =BN5+1 -> 47
B6: Month # in Model | C6: # | D6: ="the model structure runs for "&BO6&" months. Month 0 is a pre-structure month, meant to capture opening items that help calculate the first month" -> the model structure runs for 48 months. Month 0 is a pre-structure month, meant to capture opening items that help calculate the first month | T6: 1 | U6: =T6+1 -> 2 | V6: =U6+1 -> 3 | W6: =V6+1 -> 4 | X6: =W6+1 -> 5 | Y6: =X6+1 -> 6 | Z6: =Y6+1 -> 7 | AA6: =Z6+1 -> 8 | AB6: =AA6+1 -> 9 | ... BO6: =BN6+1 -> 48
B7: Fiscal Year | C7: # | D7: the fiscal year can vary from the calendar year, this is calculated based on the assumption for fiscal year end | T7: {=IF(EOMONTH(T4,0)<=EOMONTH('Get Started'!$D9,0),YEAR('Get Started'!$D9),IF(T6<=(MONTH('Get Started'!$D9)-MONTH('Get Started'!$D8)),YEAR('Get Started'!$D9),IF(T6<=12,YEAR('Get Started'!$D9)+1,IFERROR(INDEX(S7:$T7,0,MATCH(T5-12,S5:$T5,0)),0)+1)))} -> 2026 | U7: {=IF(EOMONTH(U4,0)<=EOMONTH('Get Started'!$D9,0),YEAR('Get Started'!$D9),IF(U6<=(MONTH('Get Started'!$D9)-MONTH('Get Started'!$D8)),YEAR('Get Started'!$D9),IF(U6<=12,YEAR('Get Started'!$D9)+1,IFERROR(INDEX(T7:$T7,0,MATCH(U5-12,T5:$T5,0)),0)+1)))} -> 2026 | V7: {=IF(EOMONTH(V4,0)<=EOMONTH('Get Started'!$D9,0),YEAR('Get Started'!$D9),IF(V6<=(MONTH('Get Started'!$D9)-MONTH('Get Started'!$D8)),YEAR('Get Started'!$D9),IF(V6<=12,YEAR('Get Started'!$D9)+1,IFERROR(INDEX($T7:U7,0,MATCH(V5-12,$T5:U5,0)),0)+1)))} -> 2027 | W7: {=IF(EOMONTH(W4,0)<=EOMONTH('Get Started'!$D9,0),YEAR('Get Started'!$D9),IF(W6<=(MONTH('Get Started'!$D9)-MONTH('Get Started'!$D8)),YEAR('Get Started'!$D9),IF(W6<=12,YEAR('Get Started'!$D9)+1,IFERROR(INDEX($T7:V7,0,MATCH(W5-12,$T5:V5,0)),0)+1)))} -> 2027 | X7: {=IF(EOMONTH(X4,0)<=EOMONTH('Get Started'!$D9,0),YEAR('Get Started'!$D9),IF(X6<=(MONTH('Get Started'!$D9)-MONTH('Get Started'!$D8)),YEAR('Get Started'!$D9),IF(X6<=12,YEAR('Get Started'!$D9)+1,IFERROR(INDEX($T7:W7,0,MATCH(X5-12,$T5:W5,0)),0)+1)))} -> 2027 | Y7: {=IF(EOMONTH(Y4,0)<=EOMONTH('Get Started'!$D9,0),YEAR('Get Started'!$D9),IF(Y6<=(MONTH('Get Started'!$D9)-MONTH('Get Started'!$D8)),YEAR('Get Started'!$D9),IF(Y6<=12,YEAR('Get Started'!$D9)+1,IFERROR(INDEX($T7:X7,0,MATCH(Y5-12,$T5:X5,0)),0)+1)))} -> 2027 | Z7: {=IF(EOMONTH(Z4,0)<=EOMONTH('Get Started'!$D9,0),YEAR('Get Started'!$D9),IF(Z6<=(MONTH('Get Started'!$D9)-MONTH('Get Started'!$D8)),YEAR('Get Started'!$D9),IF(Z6<=12,YEAR('Get Started'!$D9)+1,IFERROR(INDEX($T7:Y7,0,MATCH(Z5-12,$T5:Y5,0)),0)+1)))} -> 2027 | AA7: {=IF(EOMONTH(AA4,0)<=EOMONTH('Get Started'!$D9,0),YEAR('Get Started'!$D9),IF(AA6<=(MONTH('Get Started'!$D9)-MONTH('Get Started'!$D8)),YEAR('Get Started'!$D9),IF(AA6<=12,YEAR('Get Started'!$D9)+1,IFERROR(INDEX($T7:Z7,0,MATCH(AA5-12,$T5:Z5,0)),0)+1)))} -> 2027 | AB7: {=IF(EOMONTH(AB4,0)<=EOMONTH('Get Started'!$D9,0),YEAR('Get Started'!$D9),IF(AB6<=(MONTH('Get Started'!$D9)-MONTH('Get Started'!$D8)),YEAR('Get Started'!$D9),IF(AB6<=12,YEAR('Get Started'!$D9)+1,IFERROR(INDEX($T7:AA7,0,MATCH(AB5-12,$T5:AA5,0)),0)+1)))} -> 2027 | AC7: {=IF(EOMONTH(AC4,0)<=EOMONTH('Get Started'!$D9,0),YEAR('Get Started'!$D9),IF(AC6<=(MONTH('Get Started'!$D9)-MONTH('Get Started'!$D8)),YEAR('Get Started'!$D9),IF(AC6<=12,YEAR('Get Started'!$D9)+1,IFERROR(INDEX($T7:AB7,0,MATCH(AC5-12,$T5:AB5,0)),0)+1)))} -> 2027 | ... BO7: {=IF(EOMONTH(BO4,0)<=EOMONTH('Get Started'!$D9,0),YEAR('Get Started'!$D9),IF(BO6<=(MONTH('Get Started'!$D9)-MONTH('Get Started'!$D8)),YEAR('Get Started'!$D9),IF(BO6<=12,YEAR('Get Started'!$D9)+1,IFERROR(INDEX($T7:BN7,0,MATCH(BO5-12,$T5:BN5,0)),0)+1)))} -> 2030
B8: Quarter in Fiscal Year | C8: text | D8: the quarters of the year vary according by the fiscal year end | T8: =IF(OR(T11=3,T11=2,T11=1),"Q1",IF(OR(T11=6,T11=5,T11=4),"Q2",IF(OR(T11=9,T11=8,T11=7),"Q3","Q4"))) -> Q4 | U8: =IF(OR(U11=3,U11=2,U11=1),"Q1",IF(OR(U11=6,U11=5,U11=4),"Q2",IF(OR(U11=9,U11=8,U11=7),"Q3","Q4"))) -> Q4 | V8: =IF(OR(V11=3,V11=2,V11=1),"Q1",IF(OR(V11=6,V11=5,V11=4),"Q2",IF(OR(V11=9,V11=8,V11=7),"Q3","Q4"))) -> Q1 | W8: =IF(OR(W11=3,W11=2,W11=1),"Q1",IF(OR(W11=6,W11=5,W11=4),"Q2",IF(OR(W11=9,W11=8,W11=7),"Q3","Q4"))) -> Q1 | X8: =IF(OR(X11=3,X11=2,X11=1),"Q1",IF(OR(X11=6,X11=5,X11=4),"Q2",IF(OR(X11=9,X11=8,X11=7),"Q3","Q4"))) -> Q1 | Y8: =IF(OR(Y11=3,Y11=2,Y11=1),"Q1",IF(OR(Y11=6,Y11=5,Y11=4),"Q2",IF(OR(Y11=9,Y11=8,Y11=7),"Q3","Q4"))) -> Q2 | Z8: =IF(OR(Z11=3,Z11=2,Z11=1),"Q1",IF(OR(Z11=6,Z11=5,Z11=4),"Q2",IF(OR(Z11=9,Z11=8,Z11=7),"Q3","Q4"))) -> Q2 | AA8: =IF(OR(AA11=3,AA11=2,AA11=1),"Q1",IF(OR(AA11=6,AA11=5,AA11=4),"Q2",IF(OR(AA11=9,AA11=8,AA11=7),"Q3","Q4"))) -> Q2 | ... BO8: =IF(OR(BO11=3,BO11=2,BO11=1),"Q1",IF(OR(BO11=6,BO11=5,BO11=4),"Q2",IF(OR(BO11=9,BO11=8,BO11=7),"Q3","Q4"))) -> Q4
B9: Quarter / Year | C9: text | D9: quarters and year, reported in text form for some charts and graphs | T9: =T8&" "&T7 -> Q4 2026 | U9: =U8&" "&U7 -> Q4 2026 | V9: =V8&" "&V7 -> Q1 2027 | W9: =W8&" "&W7 -> Q1 2027 | X9: =X8&" "&X7 -> Q1 2027 | Y9: =Y8&" "&Y7 -> Q2 2027 | Z9: =Z8&" "&Z7 -> Q2 2027 | AA9: =AA8&" "&AA7 -> Q2 2027 | ... BO9: =BO8&" "&BO7 -> Q4 2030
B10: Month (Text) | C10: text | D10: the month of the calendar year, used for reporting and seasonality calculations | T10: =TEXT(T4,"mmmm") -> November | U10: =TEXT(U4,"mmmm") -> December | V10: =TEXT(V4,"mmmm") -> January | W10: =TEXT(W4,"mmmm") -> February | X10: =TEXT(X4,"mmmm") -> March | Y10: =TEXT(Y4,"mmmm") -> April | Z10: =TEXT(Z4,"mmmm") -> May | AA10: =TEXT(AA4,"mmmm") -> June | ... BO10: =TEXT(BO4,"mmmm") -> October
B11: Month # in Fiscal year | C11: # | D11: the month # in the fiscal year. This rolls over to 1 at the start of each fiscal year | T11: =IF(MOD(MONTH(T4)+12-MONTH('Get Started'!$D9),12)=0,12,MOD(MONTH(T4)+12-MONTH('Get Started'!$D9),12)) -> 11 | U11: =IF(MOD(MONTH(U4)+12-MONTH('Get Started'!$D9),12)=0,12,MOD(MONTH(U4)+12-MONTH('Get Started'!$D9),12)) -> 12 | V11: =IF(MOD(MONTH(V4)+12-MONTH('Get Started'!$D9),12)=0,12,MOD(MONTH(V4)+12-MONTH('Get Started'!$D9),12)) -> 1 | W11: =IF(MOD(MONTH(W4)+12-MONTH('Get Started'!$D9),12)=0,12,MOD(MONTH(W4)+12-MONTH('Get Started'!$D9),12)) -> 2 | X11: =IF(MOD(MONTH(X4)+12-MONTH('Get Started'!$D9),12)=0,12,MOD(MONTH(X4)+12-MONTH('Get Started'!$D9),12)) -> 3 | Y11: =IF(MOD(MONTH(Y4)+12-MONTH('Get Started'!$D9),12)=0,12,MOD(MONTH(Y4)+12-MONTH('Get Started'!$D9),12)) -> 4 | Z11: =IF(MOD(MONTH(Z4)+12-MONTH('Get Started'!$D9),12)=0,12,MOD(MONTH(Z4)+12-MONTH('Get Started'!$D9),12)) -> 5 | AA11: =IF(MOD(MONTH(AA4)+12-MONTH('Get Started'!$D9),12)=0,12,MOD(MONTH(AA4)+12-MONTH('Get Started'!$D9),12)) -> 6 | ... BO11: =IF(MOD(MONTH(BO4)+12-MONTH('Get Started'!$D9),12)=0,12,MOD(MONTH(BO4)+12-MONTH('Get Started'!$D9),12)) -> 10
B12: Year of Operations | C12: # | D12: the year of operations. Used for some reports based on time of operations, not calendar year | T12: 1 | U12: =T12 -> 1 | V12: =U12 -> 1 | W12: =V12 -> 1 | X12: =W12 -> 1 | Y12: =X12 -> 1 | Z12: =Y12 -> 1 | AA12: =Z12 -> 1 | AB12: =AA12 -> 1 | ... AE12: =AD12 -> 1 | AF12: =T12+1 -> 2 | AG12: =U12+1 -> 2 | AH12: =V12+1 -> 2 | AI12: =W12+1 -> 2 | AJ12: =X12+1 -> 2 | AK12: =Y12+1 -> 2 | AL12: =Z12+1 -> 2 | AM12: =AA12+1 -> 2 | ... BO12: =BC12+1 -> 4
B15: Revenue and Marketing Assumptions
B16: ='Get Started'!B17 -> Average Revenue per Order, new Customer | C16: ='Get Started'!D$7 -> £ | D16: ='Get Started'!F17 -> Reported blended AOV £87 (challenge brief pp.3,9), unverified. New-customer AOV proxy only; period, VAT, refund and shipping basis unresolved. | H16: average | I16: =IF(H16=Forecast!$H$195,T16,IF(H16=Forecast!$H$196,BO16,IF(H16=Forecast!$H$197,SUM(T16:BO16),IF(H16=Forecast!$H$198,AVERAGE(T16:BO16),0)))) -> 87 | T16: ='Get Started'!$D17 -> 87 | U16: ='Get Started'!$D17 -> 87 | V16: ='Get Started'!$D17 -> 87 | W16: ='Get Started'!$D17 -> 87 | X16: ='Get Started'!$D17 -> 87 | Y16: ='Get Started'!$D17 -> 87 | Z16: ='Get Started'!$D17 -> 87 | AA16: ='Get Started'!$D17 -> 87 | ... BO16: ='Get Started'!$D17 -> 87
B17: ='Get Started'!B18 -> Average Revenue per Order, repeat Customer | C17: ='Get Started'!D$7 -> £ | D17: ='Get Started'!F18 -> Same £87 proxy for repeat AOV; no measured new/repeat split. Replaces the template 80% illustration, not a client finding. | H17: average | I17: =IF(H17=Forecast!$H$195,T17,IF(H17=Forecast!$H$196,BO17,IF(H17=Forecast!$H$197,SUM(T17:BO17),IF(H17=Forecast!$H$198,AVERAGE(T17:BO17),0)))) -> 87 | T17: ='Get Started'!$D18 -> 87 | U17: ='Get Started'!$D18 -> 87 | V17: ='Get Started'!$D18 -> 87 | W17: ='Get Started'!$D18 -> 87 | X17: ='Get Started'!$D18 -> 87 | Y17: ='Get Started'!$D18 -> 87 | Z17: ='Get Started'!$D18 -> 87 | AA17: ='Get Started'!$D18 -> 87 | ... BO17: ='Get Started'!$D18 -> 87
B18: Starting rate of change, Average Revenue per Order | C18: % | D18: ='Get Started'!F19 -> this assumes the growth rate in the first month after growth starts, as defined above | H18: average | I18: =IF(H18=Forecast!$H$195,T18,IF(H18=Forecast!$H$196,BO18,IF(H18=Forecast!$H$197,SUM(T18:BO18),IF(H18=Forecast!$H$198,AVERAGE(T18:BO18),0)))) -> 0.1 | T18: ='Get Started'!$D19 -> 0.1 | U18: ='Get Started'!$D19 -> 0.1 | V18: ='Get Started'!$D19 -> 0.1 | W18: ='Get Started'!$D19 -> 0.1 | X18: ='Get Started'!$D19 -> 0.1 | Y18: ='Get Started'!$D19 -> 0.1 | Z18: ='Get Started'!$D19 -> 0.1 | AA18: ='Get Started'!$D19 -> 0.1 | ... BO18: ='Get Started'!$D19 -> 0.1
B19: Rate of change, Average Revenue per Order | C19: % | D19: ='Get Started'!F20 -> this changes the growth rate over time: you can assume a growth rate that increases over time, stays the same, or decreases (most common) | H19: average | I19: =IF(H19=Forecast!$H$195,T19,IF(H19=Forecast!$H$196,BO19,IF(H19=Forecast!$H$197,SUM(T19:BO19),IF(H19=Forecast!$H$198,AVERAGE(T19:BO19),0)))) -> -0.05 | T19: ='Get Started'!$D20 -> -0.05 | U19: ='Get Started'!$D20 -> -0.05 | V19: ='Get Started'!$D20 -> -0.05 | W19: ='Get Started'!$D20 -> -0.05 | X19: ='Get Started'!$D20 -> -0.05 | Y19: ='Get Started'!$D20 -> -0.05 | Z19: ='Get Started'!$D20 -> -0.05 | AA19: ='Get Started'!$D20 -> -0.05 | ... BO19: ='Get Started'!$D20 -> -0.05
B20: ='Get Started'!B22 -> Cost of Sales | C20: % | D20: ='Get Started'!F22 -> per order, as a % of revenues | H20: average | I20: =IF(H20=Forecast!$H$195,T20,IF(H20=Forecast!$H$196,BO20,IF(H20=Forecast!$H$197,SUM(T20:BO20),IF(H20=Forecast!$H$198,AVERAGE(T20:BO20),0)))) -> 0.25 | T20: ='Get Started'!$D22 -> 0.25 | U20: ='Get Started'!$D22 -> 0.25 | V20: ='Get Started'!$D22 -> 0.25 | W20: ='Get Started'!$D22 -> 0.25 | X20: ='Get Started'!$D22 -> 0.25 | Y20: ='Get Started'!$D22 -> 0.25 | Z20: ='Get Started'!$D22 -> 0.25 | AA20: ='Get Started'!$D22 -> 0.25 | ... BO20: ='Get Started'!$D22 -> 0.25
B21: ='Get Started'!B23 -> Additional Cost of Sales | C21: % | D21: ='Get Started'!F23 -> per order, as a % of revenues | H21: average | I21: =IF(H21=Forecast!$H$195,T21,IF(H21=Forecast!$H$196,BO21,IF(H21=Forecast!$H$197,SUM(T21:BO21),IF(H21=Forecast!$H$198,AVERAGE(T21:BO21),0)))) -> 0.1 | T21: ='Get Started'!$D23 -> 0.1 | U21: ='Get Started'!$D23 -> 0.1 | V21: ='Get Started'!$D23 -> 0.1 | W21: ='Get Started'!$D23 -> 0.1 | X21: ='Get Started'!$D23 -> 0.1 | Y21: ='Get Started'!$D23 -> 0.1 | Z21: ='Get Started'!$D23 -> 0.1 | AA21: ='Get Started'!$D23 -> 0.1 | ... BO21: ='Get Started'!$D23 -> 0.1
B22: ='Get Started'!B24 -> Additional Cost of Sales | C22: % | D22: ='Get Started'!F24 -> per order, as a % of revenues | H22: average | I22: =IF(H22=Forecast!$H$195,T22,IF(H22=Forecast!$H$196,BO22,IF(H22=Forecast!$H$197,SUM(T22:BO22),IF(H22=Forecast!$H$198,AVERAGE(T22:BO22),0)))) -> 0 | T22: ='Get Started'!$D24 -> 0 | U22: ='Get Started'!$D24 -> 0 | V22: ='Get Started'!$D24 -> 0 | W22: ='Get Started'!$D24 -> 0 | X22: ='Get Started'!$D24 -> 0 | Y22: ='Get Started'!$D24 -> 0 | Z22: ='Get Started'!$D24 -> 0 | AA22: ='Get Started'!$D24 -> 0 | ... BO22: ='Get Started'!$D24 -> 0
B23: Starting rate of change, Cost of Sales | C23: % | D23: ='Get Started'!F25 -> this assumes the growth rate in the first month after growth starts, as defined above | H23: average | I23: =IF(H23=Forecast!$H$195,T23,IF(H23=Forecast!$H$196,BO23,IF(H23=Forecast!$H$197,SUM(T23:BO23),IF(H23=Forecast!$H$198,AVERAGE(T23:BO23),0)))) -> 0 | T23: ='Get Started'!$D25 -> 0 | U23: ='Get Started'!$D25 -> 0 | V23: ='Get Started'!$D25 -> 0 | W23: ='Get Started'!$D25 -> 0 | X23: ='Get Started'!$D25 -> 0 | Y23: ='Get Started'!$D25 -> 0 | Z23: ='Get Started'!$D25 -> 0 | AA23: ='Get Started'!$D25 -> 0 | ... BO23: ='Get Started'!$D25 -> 0
B24: Rate of change, Cost of Sales | C24: % | D24: ='Get Started'!F26 -> this changes the growth rate over time: you can assume a growth rate that increases over time, stays the same, or decreases (most common) | H24: average | I24: =IF(H24=Forecast!$H$195,T24,IF(H24=Forecast!$H$196,BO24,IF(H24=Forecast!$H$197,SUM(T24:BO24),IF(H24=Forecast!$H$198,AVERAGE(T24:BO24),0)))) -> 0 | T24: ='Get Started'!$D26 -> 0 | U24: ='Get Started'!$D26 -> 0 | V24: ='Get Started'!$D26 -> 0 | W24: ='Get Started'!$D26 -> 0 | X24: ='Get Started'!$D26 -> 0 | Y24: ='Get Started'!$D26 -> 0 | Z24: ='Get Started'!$D26 -> 0 | AA24: ='Get Started'!$D26 -> 0 | ... BO24: ='Get Started'!$D26 -> 0
B25: ='Get Started'!B28 -> Shipping Revenue per order | C25: ='Get Started'!D$7 -> £ | D25: ='Get Started'!F28 -> revenue earned from charging for shipping to end customer, per order | H25: average | I25: =IF(H25=Forecast!$H$195,T25,IF(H25=Forecast!$H$196,BO25,IF(H25=Forecast!$H$197,SUM(T25:BO25),IF(H25=Forecast!$H$198,AVERAGE(T25:BO25),0)))) -> 0 | T25: ='Get Started'!$D28 -> 0 | U25: ='Get Started'!$D28 -> 0 | V25: ='Get Started'!$D28 -> 0 | W25: ='Get Started'!$D28 -> 0 | X25: ='Get Started'!$D28 -> 0 | Y25: ='Get Started'!$D28 -> 0 | Z25: ='Get Started'!$D28 -> 0 | AA25: ='Get Started'!$D28 -> 0 | ... BO25: ='Get Started'!$D28 -> 0
B26: ='Get Started'!B29 -> Shipping Cost per order | C26: ='Get Started'!D$7 -> £ | D26: ='Get Started'!F29 -> costs for shipping to end customer, per order | H26: average | I26: =IF(H26=Forecast!$H$195,T26,IF(H26=Forecast!$H$196,BO26,IF(H26=Forecast!$H$197,SUM(T26:BO26),IF(H26=Forecast!$H$198,AVERAGE(T26:BO26),0)))) -> 0 | T26: ='Get Started'!$D29 -> 0 | U26: ='Get Started'!$D29 -> 0 | V26: ='Get Started'!$D29 -> 0 | W26: ='Get Started'!$D29 -> 0 | X26: ='Get Started'!$D29 -> 0 | Y26: ='Get Started'!$D29 -> 0 | Z26: ='Get Started'!$D29 -> 0 | AA26: ='Get Started'!$D29 -> 0 | ... BO26: ='Get Started'!$D29 -> 0
B27: ='Get Started'!B31 -> Customer Acquisition Cost (CAC), new customer | C27: ='Get Started'!D$7 -> £ | D27: ='Get Started'!F31 -> Customer acquisition cost, per new order | H27: average | I27: =IF(H27=Forecast!$H$195,T27,IF(H27=Forecast!$H$196,BO27,IF(H27=Forecast!$H$197,SUM(T27:BO27),IF(H27=Forecast!$H$198,AVERAGE(T27:BO27),0)))) -> 30 | T27: ='Get Started'!$D31 -> 30 | U27: ='Get Started'!$D31 -> 30 | V27: ='Get Started'!$D31 -> 30 | W27: ='Get Started'!$D31 -> 30 | X27: ='Get Started'!$D31 -> 30 | Y27: ='Get Started'!$D31 -> 30 | Z27: ='Get Started'!$D31 -> 30 | AA27: ='Get Started'!$D31 -> 30 | ... BO27: ='Get Started'!$D31 -> 30
B28: ='Get Started'!B32 -> Customer Acquisition Cost (CAC), repeat customer | C28: ='Get Started'!D$7 -> £ | D28: ='Get Started'!F32 -> retention cost per subscriber, per renew cycle. Intention is to include cost to market to existing subscribers to increase retention | H28: average | I28: =IF(H28=Forecast!$H$195,T28,IF(H28=Forecast!$H$196,BO28,IF(H28=Forecast!$H$197,SUM(T28:BO28),IF(H28=Forecast!$H$198,AVERAGE(T28:BO28),0)))) -> 10 | T28: ='Get Started'!$D32 -> 10 | U28: ='Get Started'!$D32 -> 10 | V28: ='Get Started'!$D32 -> 10 | W28: ='Get Started'!$D32 -> 10 | X28: ='Get Started'!$D32 -> 10 | Y28: ='Get Started'!$D32 -> 10 | Z28: ='Get Started'!$D32 -> 10 | AA28: ='Get Started'!$D32 -> 10 | ... BO28: ='Get Started'!$D32 -> 10
B29: Starting rate of change, CAC | C29: % | D29: ='Get Started'!F33 -> this assumes the rate in the first month after starts, as defined above | H29: average | I29: =IF(H29=Forecast!$H$195,T29,IF(H29=Forecast!$H$196,BO29,IF(H29=Forecast!$H$197,SUM(T29:BO29),IF(H29=Forecast!$H$198,AVERAGE(T29:BO29),0)))) -> 0 | T29: ='Get Started'!$D33 -> 0 | U29: ='Get Started'!$D33 -> 0 | V29: ='Get Started'!$D33 -> 0 | W29: ='Get Started'!$D33 -> 0 | X29: ='Get Started'!$D33 -> 0 | Y29: ='Get Started'!$D33 -> 0 | Z29: ='Get Started'!$D33 -> 0 | AA29: ='Get Started'!$D33 -> 0 | ... BO29: ='Get Started'!$D33 -> 0
B30: Rate of change, CAC | C30: % | D30: ='Get Started'!F34 -> this changes the rate over time: you can assume a rate that increases over time, stays the same, or decreases (most common) | H30: average | I30: =IF(H30=Forecast!$H$195,T30,IF(H30=Forecast!$H$196,BO30,IF(H30=Forecast!$H$197,SUM(T30:BO30),IF(H30=Forecast!$H$198,AVERAGE(T30:BO30),0)))) -> 0 | T30: ='Get Started'!$D34 -> 0 | U30: ='Get Started'!$D34 -> 0 | V30: ='Get Started'!$D34 -> 0 | W30: ='Get Started'!$D34 -> 0 | X30: ='Get Started'!$D34 -> 0 | Y30: ='Get Started'!$D34 -> 0 | Z30: ='Get Started'!$D34 -> 0 | AA30: ='Get Started'!$D34 -> 0 | ... BO30: ='Get Started'!$D34 -> 0
B32: Growth and Churn Assumptions
B33: ='Get Started'!B37 -> Date to start growth and revenues | C33: # | D33: ='Get Started'!F37 -> date to start growth of revenues, used on Forecast sheet in Growth section | H33: initial | I33: =IF(H33=Forecast!$H$195,T33,IF(H33=Forecast!$H$196,BO33,IF(H33=Forecast!$H$197,SUM(T33:BO33),IF(H33=Forecast!$H$198,AVERAGE(T33:BO33),0)))) -> 46327 | T33: ='Get Started'!$D37 -> 46327 | U33: ='Get Started'!$D37 -> 46327 | V33: ='Get Started'!$D37 -> 46327 | W33: ='Get Started'!$D37 -> 46327 | X33: ='Get Started'!$D37 -> 46327 | Y33: ='Get Started'!$D37 -> 46327 | Z33: ='Get Started'!$D37 -> 46327 | AA33: ='Get Started'!$D37 -> 46327 | ... BO33: ='Get Started'!$D37 -> 46327
B34: ='Get Started'!B38 -> New Customers | C34: # | D34: ='Get Started'!F38 -> use the input to change the label, the number input refers to the # new in the first month, as defined above | H34: average | I34: =IF(H34=Forecast!$H$195,T34,IF(H34=Forecast!$H$196,BO34,IF(H34=Forecast!$H$197,SUM(T34:BO34),IF(H34=Forecast!$H$198,AVERAGE(T34:BO34),0)))) -> 550 | T34: ='Get Started'!$D38 -> 550 | U34: ='Get Started'!$D38 -> 550 | V34: ='Get Started'!$D38 -> 550 | W34: ='Get Started'!$D38 -> 550 | X34: ='Get Started'!$D38 -> 550 | Y34: ='Get Started'!$D38 -> 550 | Z34: ='Get Started'!$D38 -> 550 | AA34: ='Get Started'!$D38 -> 550 | ... BO34: ='Get Started'!$D38 -> 550
B35: Starting growth rate, new subscribers | C35: % | D35: ='Get Started'!F39 -> this assumes the growth rate in the first month after growth starts, as defined above | H35: average | I35: =IF(H35=Forecast!$H$195,T35,IF(H35=Forecast!$H$196,BO35,IF(H35=Forecast!$H$197,SUM(T35:BO35),IF(H35=Forecast!$H$198,AVERAGE(T35:BO35),0)))) -> 0.9 | T35: ='Get Started'!$D39 -> 0.9 | U35: ='Get Started'!$D39 -> 0.9 | V35: ='Get Started'!$D39 -> 0.9 | W35: ='Get Started'!$D39 -> 0.9 | X35: ='Get Started'!$D39 -> 0.9 | Y35: ='Get Started'!$D39 -> 0.9 | Z35: ='Get Started'!$D39 -> 0.9 | AA35: ='Get Started'!$D39 -> 0.9 | ... BO35: ='Get Started'!$D39 -> 0.9
B36: Change in Growth Rate in new subscribers | C36: % | D36: ='Get Started'!F40 -> this changes the growth rate over time: you can assume a growth rate that increases over time, stays the same, or decreases (most common) | H36: average | I36: =IF(H36=Forecast!$H$195,T36,IF(H36=Forecast!$H$196,BO36,IF(H36=Forecast!$H$197,SUM(T36:BO36),IF(H36=Forecast!$H$198,AVERAGE(T36:BO36),0)))) -> -0.15 | T36: ='Get Started'!$D40 -> -0.15 | U36: ='Get Started'!$D40 -> -0.15 | V36: ='Get Started'!$D40 -> -0.15 | W36: ='Get Started'!$D40 -> -0.15 | X36: ='Get Started'!$D40 -> -0.15 | Y36: ='Get Started'!$D40 -> -0.15 | Z36: ='Get Started'!$D40 -> -0.15 | AA36: ='Get Started'!$D40 -> -0.15 | ... BO36: ='Get Started'!$D40 -> -0.15
B37: ='Get Started'!B41 -> Conversion Rate | C37: # | D37: ='Get Started'!F41 -> % of website sessions that convert to orders | H37: average | I37: =IF(H37=Forecast!$H$195,T37,IF(H37=Forecast!$H$196,BO37,IF(H37=Forecast!$H$197,SUM(T37:BO37),IF(H37=Forecast!$H$198,AVERAGE(T37:BO37),0)))) -> 0.02 | T37: ='Get Started'!$D41 -> 0.02 | U37: ='Get Started'!$D41 -> 0.02 | V37: ='Get Started'!$D41 -> 0.02 | W37: ='Get Started'!$D41 -> 0.02 | X37: ='Get Started'!$D41 -> 0.02 | Y37: ='Get Started'!$D41 -> 0.02 | Z37: ='Get Started'!$D41 -> 0.02 | AA37: ='Get Started'!$D41 -> 0.02 | ... BO37: ='Get Started'!$D41 -> 0.02
B38: ='Get Started'!B42 -> Customers, beginning of first month | C38: # | D38: ='Get Started'!F42 -> assume the # of new customers that have been acquired prior to the start of the forecast; this is useful if you have an existing base of customers making repeat orders and want to introduce that into the model's forecast of new and repeat orders | H38: average | I38: =IF(H38=Forecast!$H$195,T38,IF(H38=Forecast!$H$196,BO38,IF(H38=Forecast!$H$197,SUM(T38:BO38),IF(H38=Forecast!$H$198,AVERAGE(T38:BO38),0)))) -> 0 | T38: ='Get Started'!$D42 -> 0 | U38: ='Get Started'!$D42 -> 0 | V38: ='Get Started'!$D42 -> 0 | W38: ='Get Started'!$D42 -> 0 | X38: ='Get Started'!$D42 -> 0 | Y38: ='Get Started'!$D42 -> 0 | Z38: ='Get Started'!$D42 -> 0 | AA38: ='Get Started'!$D42 -> 0 | ... BO38: ='Get Started'!$D42 -> 0
B39: ='Get Started'!B43 -> Churn rate, per period | C39: % | D39: ='Get Started'!F43 -> % of customers that do not make a repeat order, on each repeat cycle | H39: average | I39: =IF(H39=Forecast!$H$195,T39,IF(H39=Forecast!$H$196,BO39,IF(H39=Forecast!$H$197,SUM(T39:BO39),IF(H39=Forecast!$H$198,AVERAGE(T39:BO39),0)))) -> 0.5 | T39: ='Get Started'!$D43 -> 0.5 | U39: ='Get Started'!$D43 -> 0.5 | V39: ='Get Started'!$D43 -> 0.5 | W39: ='Get Started'!$D43 -> 0.5 | X39: ='Get Started'!$D43 -> 0.5 | Y39: ='Get Started'!$D43 -> 0.5 | Z39: ='Get Started'!$D43 -> 0.5 | AA39: ='Get Started'!$D43 -> 0.5 | ... BO39: ='Get Started'!$D43 -> 0.5
B40: ='Get Started'!B44 -> Repeat Cycle | C40: # | D40: =" "&LOWER('Get Started'!F44) -> if customers place repeat orders, the # of months to a repeat order. this sets the cadence of repeat orders, and combines with the churn assumption to forecast the # of repeat orders. important to note is that if you assume a repeat rate, your repeat purchases is bounded by the web sessions and conversion rate. e.g., web sessions * conversion rate = orders. orders - repeat orders = new orders. so if you do not grow web sessions and you assume repeat purchases, it's possible to create a forecast that includes zero orders from new customers. if that happens, reduce your repeat rate, increase your churn, or increase your top-line web sessions growth | H40: average | I40: =IF(H40=Forecast!$H$195,T40,IF(H40=Forecast!$H$196,BO40,IF(H40=Forecast!$H$197,SUM(T40:BO40),IF(H40=Forecast!$H$198,AVERAGE(T40:BO40),0)))) -> 3 | T40: ='Get Started'!$D44 -> 3 | U40: ='Get Started'!$D44 -> 3 | V40: ='Get Started'!$D44 -> 3 | W40: ='Get Started'!$D44 -> 3 | X40: ='Get Started'!$D44 -> 3 | Y40: ='Get Started'!$D44 -> 3 | Z40: ='Get Started'!$D44 -> 3 | AA40: ='Get Started'!$D44 -> 3 | ... BO40: ='Get Started'!$D44 -> 3
B41: Orders, per customer, as a # per 1 customer | C41: # | D41: calculated from the churn rate and repeat cycle inputs | H41: sum | I41: =IF(H41=Forecast!$H$195,T41,IF(H41=Forecast!$H$196,BO41,IF(H41=Forecast!$H$197,SUM(T41:BO41),IF(H41=Forecast!$H$198,AVERAGE(T41:BO41),0)))) -> 1.9999695 | T41: =IF(T6=1,1,IF(MOD(T5,T40)=0,(1-T39)*IF(T5<T40,0, OFFSET(T41,,-1*T40)),0)) -> 1 | U41: =IF(U6=1,1,IF(MOD(U5,U40)=0,(1-U39)*IF(U5<U40,0, OFFSET(U41,,-1*U40)),0)) -> 0 | V41: =IF(V6=1,1,IF(MOD(V5,V40)=0,(1-V39)*IF(V5<V40,0, OFFSET(V41,,-1*V40)),0)) -> 0 | W41: =IF(W6=1,1,IF(MOD(W5,W40)=0,(1-W39)*IF(W5<W40,0, OFFSET(W41,,-1*W40)),0)) -> 0.5 | X41: =IF(X6=1,1,IF(MOD(X5,X40)=0,(1-X39)*IF(X5<X40,0, OFFSET(X41,,-1*X40)),0)) -> 0 | Y41: =IF(Y6=1,1,IF(MOD(Y5,Y40)=0,(1-Y39)*IF(Y5<Y40,0, OFFSET(Y41,,-1*Y40)),0)) -> 0 | Z41: =IF(Z6=1,1,IF(MOD(Z5,Z40)=0,(1-Z39)*IF(Z5<Z40,0, OFFSET(Z41,,-1*Z40)),0)) -> 0.25 | AA41: =IF(AA6=1,1,IF(MOD(AA5,AA40)=0,(1-AA39)*IF(AA5<AA40,0, OFFSET(AA41,,-1*AA40)),0)) -> 0 | ... BO41: =IF(BO6=1,1,IF(MOD(BO5,BO40)=0,(1-BO39)*IF(BO5<BO40,0, OFFSET(BO41,,-1*BO40)),0)) -> 0
B42: Orders, per customer, as a # per 1 customer | C42: # | D42: historical average | H42: sum | I42: =IF(H42=Forecast!$H$195,T42,IF(H42=Forecast!$H$196,BO42,IF(H42=Forecast!$H$197,SUM(T42:BO42),IF(H42=Forecast!$H$198,AVERAGE(T42:BO42),0)))) -> 4.051061 | T42: =Historicals!T64 -> 1 | U42: =Historicals!U64 -> 0.64761384 | V42: =Historicals!V64 -> 0.586256 | W42: =Historicals!W64 -> 0.42200024 | X42: =Historicals!X64 -> 0.32424205 | Y42: =Historicals!Y64 -> 0.24920418 | Z42: =Historicals!Z64 -> 0.19158545 | AA42: =Historicals!AA64 -> 0.14732616 | ... BO42: =Historicals!BO64 -> 0
B43: Orders, per customer, as a # per 1 customer | C43: # | D43: manual input | H43: sum | I43: =IF(H43=Forecast!$H$195,T43,IF(H43=Forecast!$H$196,BO43,IF(H43=Forecast!$H$197,SUM(T43:BO43),IF(H43=Forecast!$H$198,AVERAGE(T43:BO43),0)))) -> 1.9999999 | T43: 1 | U43: 0 | V43: =T43*0.5 -> 0.5 | W43: =U43*0.5 -> 0 | X43: =V43*0.5 -> 0.25 | Y43: =W43*0.5 -> 0 | Z43: =X43*0.5 -> 0.125 | AA43: =Y43*0.5 -> 0 | AB43: =Z43*0.5 -> 0.0625 | AC43: =AA43*0.5 -> 0 | ... BO43: =BM43*0.5 -> 0
B44: Orders per 1 New Customer (the retention curve used in the model) | C44: # | D44: calculated from the churn rate and repeat cycle inputs | F44: 1 | G44: x | H44: sum | I44: =IF(H44=Forecast!$H$195,T44,IF(H44=Forecast!$H$196,BO44,IF(H44=Forecast!$H$197,SUM(T44:BO44),IF(H44=Forecast!$H$198,AVERAGE(T44:BO44),0)))) -> 1.9999695 | T44: =INDEX(T41:T43,MATCH($D44,$D41:$D43,0))*IF(T6=1,1,$F44) -> 1 | U44: =INDEX(U41:U43,MATCH($D44,$D41:$D43,0))*IF(U6=1,1,$F44) -> 0 | V44: =INDEX(V41:V43,MATCH($D44,$D41:$D43,0))*IF(V6=1,1,$F44) -> 0 | W44: =INDEX(W41:W43,MATCH($D44,$D41:$D43,0))*IF(W6=1,1,$F44) -> 0.5 | X44: =INDEX(X41:X43,MATCH($D44,$D41:$D43,0))*IF(X6=1,1,$F44) -> 0 | Y44: =INDEX(Y41:Y43,MATCH($D44,$D41:$D43,0))*IF(Y6=1,1,$F44) -> 0 | Z44: =INDEX(Z41:Z43,MATCH($D44,$D41:$D43,0))*IF(Z6=1,1,$F44) -> 0.25 | AA44: =INDEX(AA41:AA43,MATCH($D44,$D41:$D43,0))*IF(AA6=1,1,$F44) -> 0 | ... BO44: =INDEX(BO41:BO43,MATCH($D44,$D41:$D43,0))*IF(BO6=1,1,$F44) -> 0
B45: Orders per 1 Existing Customer | C45: # | D45: estimated from the new cohort used above. this is manual, please change the formula here to fit what you want to estimate from the customers that were booked as new customers prior to the start of the model | H45: sum | I45: =IF(H45=Forecast!$H$195,T45,IF(H45=Forecast!$H$196,BO45,IF(H45=Forecast!$H$197,SUM(T45:BO45),IF(H45=Forecast!$H$198,AVERAGE(T45:BO45),0)))) -> 0.97915173 | T45: =$I44/48*(48-T6)/48 -> 0.040797989 | U45: =$I44/48*(48-U6)/48 -> 0.039929946 | V45: =$I44/48*(48-V6)/48 -> 0.039061904 | W45: =$I44/48*(48-W6)/48 -> 0.038193862 | X45: =$I44/48*(48-X6)/48 -> 0.037325819 | Y45: =$I44/48*(48-Y6)/48 -> 0.036457777 | Z45: =$I44/48*(48-Z6)/48 -> 0.035589735 | AA45: =$I44/48*(48-AA6)/48 -> 0.034721692 | ... BO45: =$I44/48*(48-BO6)/48 -> 0
B46: Adjustment to Retention Curve | C46: # | D46: adjustment to apply to base retention curve for all cohorts at a certain month | H46: average | I46: =IF(H46=Forecast!$H$195,T46,IF(H46=Forecast!$H$196,BO46,IF(H46=Forecast!$H$197,SUM(T46:BO46),IF(H46=Forecast!$H$198,AVERAGE(T46:BO46),0)))) -> 1 | T46: =IF(T47>'Get Started'!$D47,'Get Started'!$D48,1) -> 1 | U46: =IF(U47>'Get Started'!$D47,'Get Started'!$D48,1) -> 1 | V46: =IF(V47>'Get Started'!$D47,'Get Started'!$D48,1) -> 1 | W46: =IF(W47>'Get Started'!$D47,'Get Started'!$D48,1) -> 1 | X46: =IF(X47>'Get Started'!$D47,'Get Started'!$D48,1) -> 1 | Y46: =IF(Y47>'Get Started'!$D47,'Get Started'!$D48,1) -> 1 | Z46: =IF(Z47>'Get Started'!$D47,'Get Started'!$D48,1) -> 1 | AA46: =IF(AA47>'Get Started'!$D47,'Get Started'!$D48,1) -> 1 | ... BO46: =IF(BO47>'Get Started'!$D47,'Get Started'!$D48,1) -> 1
B47: Cumulative New Customers | C47: # | S47: 0 | T47: =T34+S47 -> 550 | U47: =U34+T47 -> 1100 | V47: =V34+U47 -> 1650 | W47: =W34+V47 -> 2200 | X47: =X34+W47 -> 2750 | Y47: =Y34+X47 -> 3300 | Z47: =Z34+Y47 -> 3850 | AA47: =AA34+Z47 -> 4400 | ... BO47: =BO34+BN47 -> 26400
B48: Cumulative Orders | C48: # | S48: 0 | T48: =T54+S48 -> 7510.724 | U48: =U54+T48 -> 10142.415 | V48: =V54+U48 -> 13493.895 | W48: =W54+V48 -> 17045.257 | X48: =X54+W48 -> 22017.118 | Y48: =Y54+X48 -> 28808.849 | Z48: =Z54+Y48 -> 37437.064 | AA48: =AA54+Z48 -> 48752.618 | ... BO48: =BO54+BN48 -> 2578672
B50: Orders
B51: Website Traffic | D51: calculated from orders and conversion rate; what demand generation would have to be, given the assumed conversion rate | H51: sum | I51: =IF(H51=Forecast!$H$195,T51,IF(H51=Forecast!$H$196,BO51,IF(H51=Forecast!$H$197,SUM(T51:BO51),IF(H51=Forecast!$H$198,AVERAGE(T51:BO51),0)))) -> 1.289336e+08 | T51: =T54/T37 -> 375536.2 | U51: =U54/U37 -> 131584.56 | V51: =V54/V37 -> 167573.99 | W51: =W54/W37 -> 177568.09 | X51: =X54/X37 -> 248593.08 | Y51: =Y54/Y37 -> 339586.52 | Z51: =Z54/Z37 -> 431410.76 | AA51: =AA54/AA37 -> 565777.71 | ... BO51: =BO54/BO37 -> 4084164.9
B52: ='Get Started'!B38&", per period" -> New Customers, per period | C52: # | D52: during period | H52: sum | I52: =IF(H52=Forecast!$H$195,T52,IF(H52=Forecast!$H$196,BO52,IF(H52=Forecast!$H$197,SUM(T52:BO52),IF(H52=Forecast!$H$198,AVERAGE(T52:BO52),0)))) -> 1404054.1 | T52: =IF(EOMONTH(T33,0)=T4,T34,S52*(1+T53)) -> 550 | U52: =IF(EOMONTH(U33,0)=U4,U34,T52*(1+U53)) -> 970.75 | V52: =IF(EOMONTH(V33,0)=V4,V34,U52*(1+V53)) -> 1601.9802 | W52: =IF(EOMONTH(W33,0)=W4,W34,V52*(1+W53)) -> 2487.4147 | X52: =IF(EOMONTH(X33,0)=X4,X34,W52*(1+X53)) -> 3656.0161 | Y52: =IF(EOMONTH(Y33,0)=Y4,Y34,X52*(1+Y53)) -> 5115.9904 | Z52: =IF(EOMONTH(Z33,0)=Z4,Z34,Y52*(1+Z53)) -> 6852.5344 | AA52: =IF(EOMONTH(AA33,0)=AA4,AA34,Z52*(1+AA53)) -> 8829.6234 | ... BO52: =IF(EOMONTH(BO33,0)=BO4,BO34,BN52*(1+BO53)) -> 40991.004
B53: ="Growth Rate in New "&'Get Started'!B38 -> Growth Rate in New New Customers | C53: % | D53: growth rate in new customers per period | H53: average | I53: =IF(H53=Forecast!$H$195,T53,IF(H53=Forecast!$H$196,BO53,IF(H53=Forecast!$H$197,SUM(T53:BO53),IF(H53=Forecast!$H$198,AVERAGE(T53:BO53),0)))) -> 0.12494883 | T53: =IF(EOMONTH(T33,0)=T4,T35,S53*(1+T36)) -> 0.9 | U53: =IF(EOMONTH(U33,0)=U4,U35,T53*(1+U36)) -> 0.765 | V53: =IF(EOMONTH(V33,0)=V4,V35,U53*(1+V36)) -> 0.65025 | W53: =IF(EOMONTH(W33,0)=W4,W35,V53*(1+W36)) -> 0.5527125 | X53: =IF(EOMONTH(X33,0)=X4,X35,W53*(1+X36)) -> 0.46980562 | Y53: =IF(EOMONTH(Y33,0)=Y4,Y35,X53*(1+Y36)) -> 0.39933478 | Z53: =IF(EOMONTH(Z33,0)=Z4,Z35,Y53*(1+Z36)) -> 0.33943456 | AA53: =IF(EOMONTH(AA33,0)=AA4,AA35,Z53*(1+AA36)) -> 0.28851938 | ... BO53: =IF(EOMONTH(BO33,0)=BO4,BO35,BN53*(1+BO36)) -> 0.00043344302
B54: Orders | C54: # | D54: sum of the cohorts below | H54: sum | I54: =IF(H54=Forecast!$H$195,T54,IF(H54=Forecast!$H$196,BO54,IF(H54=Forecast!$H$197,SUM(T54:BO54),IF(H54=Forecast!$H$198,AVERAGE(T54:BO54),0)))) -> 2578672 | T54: =SUM(T55:T151) -> 7510.724 | U54: =SUM(U55:U151) -> 2631.6912 | V54: =SUM(V55:V151) -> 3351.4799 | W54: =SUM(W55:W151) -> 3551.3617 | X54: =SUM(X55:X151) -> 4971.8616 | Y54: =SUM(Y55:Y151) -> 6791.7304 | Z54: =SUM(Z55:Z151) -> 8628.2153 | AA54: =SUM(AA55:AA151) -> 11315.554 | ... BO54: =SUM(BO55:BO151) -> 81683.298
B55: Existing Customers | C55: # | D55: 0 | H55: sum | I55: =IF(H55=Forecast!$H$195,T55,IF(H55=Forecast!$H$196,BO55,IF(H55=Forecast!$H$197,SUM(T55:BO55),IF(H55=Forecast!$H$198,AVERAGE(T55:BO55),0)))) -> 0 | T55: =IF(T$6<$D55,0,INDEX($T$45:$BO$45,,T$6-1+1)*T38) -> 0 | U55: =IF(U$6<$D55,0,INDEX($T$45:$BO$45,,U$6-1+1)*U38) -> 0 | V55: =IF(V$6<$D55,0,INDEX($T$45:$BO$45,,V$6-1+1)*V38) -> 0 | W55: =IF(W$6<$D55,0,INDEX($T$45:$BO$45,,W$6-1+1)*W38) -> 0 | X55: =IF(X$6<$D55,0,INDEX($T$45:$BO$45,,X$6-1+1)*X38) -> 0 | Y55: =IF(Y$6<$D55,0,INDEX($T$45:$BO$45,,Y$6-1+1)*Y38) -> 0 | Z55: =IF(Z$6<$D55,0,INDEX($T$45:$BO$45,,Z$6-1+1)*Z38) -> 0 | AA55: =IF(AA$6<$D55,0,INDEX($T$45:$BO$45,,AA$6-1+1)*AA38) -> 0 | ... BO55: =IF(BO$6<$D55,0,INDEX($T$45:$BO$45,,BO$6-1+1)*BO38) -> 0
B56: =EDATE(B57,-1) -> 44893 | C56: # | D56: =D57-1 -> -47 | F56: 1 | G56: x | H56: sum | I56: =IF(H56=Forecast!$H$195,T56,IF(H56=Forecast!$H$196,BO56,IF(H56=Forecast!$H$197,SUM(T56:BO56),IF(H56=Forecast!$H$198,AVERAGE(T56:BO56),0)))) -> 0 | T56: {=IFERROR(IF(INDEX(Historicals!$T12:$BO12,,T$6+$D56*-1)<>"",INDEX(Historicals!$T12:$BO12,,T$6+$D56*-1),$F56*T$46*Historicals!$S12*INDEX($T$44:$BO$44,,T$6-$D56+1)),0)} -> 0 | U56: {=IFERROR(IF(INDEX(Historicals!$T12:$BO12,,U$6+$D56*-1)<>"",INDEX(Historicals!$T12:$BO12,,U$6+$D56*-1),$F56*U$46*Historicals!$S12*INDEX($T$44:$BO$44,,U$6-$D56+1)),0)} -> 0 | V56: {=IFERROR(IF(INDEX(Historicals!$T12:$BO12,,V$6+$D56*-1)<>"",INDEX(Historicals!$T12:$BO12,,V$6+$D56*-1),$F56*V$46*Historicals!$S12*INDEX($T$44:$BO$44,,V$6-$D56+1)),0)} -> 0 | W56: {=IFERROR(IF(INDEX(Historicals!$T12:$BO12,,W$6+$D56*-1)<>"",INDEX(Historicals!$T12:$BO12,,W$6+$D56*-1),$F56*W$46*Historicals!$S12*INDEX($T$44:$BO$44,,W$6-$D56+1)),0)} -> 0 | X56: {=IFERROR(IF(INDEX(Historicals!$T12:$BO12,,X$6+$D56*-1)<>"",INDEX(Historicals!$T12:$BO12,,X$6+$D56*-1),$F56*X$46*Historicals!$S12*INDEX($T$44:$BO$44,,X$6-$D56+1)),0)} -> 0 | Y56: {=IFERROR(IF(INDEX(Historicals!$T12:$BO12,,Y$6+$D56*-1)<>"",INDEX(Historicals!$T12:$BO12,,Y$6+$D56*-1),$F56*Y$46*Historicals!$S12*INDEX($T$44:$BO$44,,Y$6-$D56+1)),0)} -> 0 | Z56: {=IFERROR(IF(INDEX(Historicals!$T12:$BO12,,Z$6+$D56*-1)<>"",INDEX(Historicals!$T12:$BO12,,Z$6+$D56*-1),$F56*Z$46*Historicals!$S12*INDEX($T$44:$BO$44,,Z$6-$D56+1)),0)} -> 0 | AA56: {=IFERROR(IF(INDEX(Historicals!$T12:$BO12,,AA$6+$D56*-1)<>"",INDEX(Historicals!$T12:$BO12,,AA$6+$D56*-1),$F56*AA$46*Historicals!$S12*INDEX($T$44:$BO$44,,AA$6-$D56+1)),0)} -> 0 | ... BO56: {=IFERROR(IF(INDEX(Historicals!$T12:$BO12,,BO$6+$D56*-1)<>"",INDEX(Historicals!$T12:$BO12,,BO$6+$D56*-1),$F56*BO$46*Historicals!$S12*INDEX($T$44:$BO$44,,BO$6-$D56+1)),0)} -> 0
B57: =EDATE(B58,-1) -> 44923 | C57: # | D57: =D58-1 -> -46 | F57: 1 | G57: x | H57: sum | I57: =IF(H57=Forecast!$H$195,T57,IF(H57=Forecast!$H$196,BO57,IF(H57=Forecast!$H$197,SUM(T57:BO57),IF(H57=Forecast!$H$198,AVERAGE(T57:BO57),0)))) -> 0 | T57: {=IFERROR(IF(INDEX(Historicals!$T13:$BO13,,T$6+$D57*-1)<>"",INDEX(Historicals!$T13:$BO13,,T$6+$D57*-1),$F57*T$46*Historicals!$S13*INDEX($T$44:$BO$44,,T$6-$D57+1)),0)} -> 0 | U57: {=IFERROR(IF(INDEX(Historicals!$T13:$BO13,,U$6+$D57*-1)<>"",INDEX(Historicals!$T13:$BO13,,U$6+$D57*-1),$F57*U$46*Historicals!$S13*INDEX($T$44:$BO$44,,U$6-$D57+1)),0)} -> 0 | V57: {=IFERROR(IF(INDEX(Historicals!$T13:$BO13,,V$6+$D57*-1)<>"",INDEX(Historicals!$T13:$BO13,,V$6+$D57*-1),$F57*V$46*Historicals!$S13*INDEX($T$44:$BO$44,,V$6-$D57+1)),0)} -> 0 | W57: {=IFERROR(IF(INDEX(Historicals!$T13:$BO13,,W$6+$D57*-1)<>"",INDEX(Historicals!$T13:$BO13,,W$6+$D57*-1),$F57*W$46*Historicals!$S13*INDEX($T$44:$BO$44,,W$6-$D57+1)),0)} -> 0 | X57: {=IFERROR(IF(INDEX(Historicals!$T13:$BO13,,X$6+$D57*-1)<>"",INDEX(Historicals!$T13:$BO13,,X$6+$D57*-1),$F57*X$46*Historicals!$S13*INDEX($T$44:$BO$44,,X$6-$D57+1)),0)} -> 0 | Y57: {=IFERROR(IF(INDEX(Historicals!$T13:$BO13,,Y$6+$D57*-1)<>"",INDEX(Historicals!$T13:$BO13,,Y$6+$D57*-1),$F57*Y$46*Historicals!$S13*INDEX($T$44:$BO$44,,Y$6-$D57+1)),0)} -> 0 | Z57: {=IFERROR(IF(INDEX(Historicals!$T13:$BO13,,Z$6+$D57*-1)<>"",INDEX(Historicals!$T13:$BO13,,Z$6+$D57*-1),$F57*Z$46*Historicals!$S13*INDEX($T$44:$BO$44,,Z$6-$D57+1)),0)} -> 0 | AA57: {=IFERROR(IF(INDEX(Historicals!$T13:$BO13,,AA$6+$D57*-1)<>"",INDEX(Historicals!$T13:$BO13,,AA$6+$D57*-1),$F57*AA$46*Historicals!$S13*INDEX($T$44:$BO$44,,AA$6-$D57+1)),0)} -> 0 | ... BO57: {=IFERROR(IF(INDEX(Historicals!$T13:$BO13,,BO$6+$D57*-1)<>"",INDEX(Historicals!$T13:$BO13,,BO$6+$D57*-1),$F57*BO$46*Historicals!$S13*INDEX($T$44:$BO$44,,BO$6-$D57+1)),0)} -> 0
B58: =EDATE(B59,-1) -> 44954 | C58: # | D58: =D59-1 -> -45 | F58: 1 | G58: x | H58: sum | I58: =IF(H58=Forecast!$H$195,T58,IF(H58=Forecast!$H$196,BO58,IF(H58=Forecast!$H$197,SUM(T58:BO58),IF(H58=Forecast!$H$198,AVERAGE(T58:BO58),0)))) -> 0 | T58: {=IFERROR(IF(INDEX(Historicals!$T14:$BO14,,T$6+$D58*-1)<>"",INDEX(Historicals!$T14:$BO14,,T$6+$D58*-1),$F58*T$46*Historicals!$S14*INDEX($T$44:$BO$44,,T$6-$D58+1)),0)} -> 0 | U58: {=IFERROR(IF(INDEX(Historicals!$T14:$BO14,,U$6+$D58*-1)<>"",INDEX(Historicals!$T14:$BO14,,U$6+$D58*-1),$F58*U$46*Historicals!$S14*INDEX($T$44:$BO$44,,U$6-$D58+1)),0)} -> 0 | V58: {=IFERROR(IF(INDEX(Historicals!$T14:$BO14,,V$6+$D58*-1)<>"",INDEX(Historicals!$T14:$BO14,,V$6+$D58*-1),$F58*V$46*Historicals!$S14*INDEX($T$44:$BO$44,,V$6-$D58+1)),0)} -> 0 | W58: {=IFERROR(IF(INDEX(Historicals!$T14:$BO14,,W$6+$D58*-1)<>"",INDEX(Historicals!$T14:$BO14,,W$6+$D58*-1),$F58*W$46*Historicals!$S14*INDEX($T$44:$BO$44,,W$6-$D58+1)),0)} -> 0 | X58: {=IFERROR(IF(INDEX(Historicals!$T14:$BO14,,X$6+$D58*-1)<>"",INDEX(Historicals!$T14:$BO14,,X$6+$D58*-1),$F58*X$46*Historicals!$S14*INDEX($T$44:$BO$44,,X$6-$D58+1)),0)} -> 0 | Y58: {=IFERROR(IF(INDEX(Historicals!$T14:$BO14,,Y$6+$D58*-1)<>"",INDEX(Historicals!$T14:$BO14,,Y$6+$D58*-1),$F58*Y$46*Historicals!$S14*INDEX($T$44:$BO$44,,Y$6-$D58+1)),0)} -> 0 | Z58: {=IFERROR(IF(INDEX(Historicals!$T14:$BO14,,Z$6+$D58*-1)<>"",INDEX(Historicals!$T14:$BO14,,Z$6+$D58*-1),$F58*Z$46*Historicals!$S14*INDEX($T$44:$BO$44,,Z$6-$D58+1)),0)} -> 0 | AA58: {=IFERROR(IF(INDEX(Historicals!$T14:$BO14,,AA$6+$D58*-1)<>"",INDEX(Historicals!$T14:$BO14,,AA$6+$D58*-1),$F58*AA$46*Historicals!$S14*INDEX($T$44:$BO$44,,AA$6-$D58+1)),0)} -> 0 | ... BO58: {=IFERROR(IF(INDEX(Historicals!$T14:$BO14,,BO$6+$D58*-1)<>"",INDEX(Historicals!$T14:$BO14,,BO$6+$D58*-1),$F58*BO$46*Historicals!$S14*INDEX($T$44:$BO$44,,BO$6-$D58+1)),0)} -> 0
B59: =EDATE(B60,-1) -> 44985 | C59: # | D59: =D60-1 -> -44 | F59: 1 | G59: x | H59: sum | I59: =IF(H59=Forecast!$H$195,T59,IF(H59=Forecast!$H$196,BO59,IF(H59=Forecast!$H$197,SUM(T59:BO59),IF(H59=Forecast!$H$198,AVERAGE(T59:BO59),0)))) -> 0 | T59: {=IFERROR(IF(INDEX(Historicals!$T15:$BO15,,T$6+$D59*-1)<>"",INDEX(Historicals!$T15:$BO15,,T$6+$D59*-1),$F59*T$46*Historicals!$S15*INDEX($T$44:$BO$44,,T$6-$D59+1)),0)} -> 0 | U59: {=IFERROR(IF(INDEX(Historicals!$T15:$BO15,,U$6+$D59*-1)<>"",INDEX(Historicals!$T15:$BO15,,U$6+$D59*-1),$F59*U$46*Historicals!$S15*INDEX($T$44:$BO$44,,U$6-$D59+1)),0)} -> 0 | V59: {=IFERROR(IF(INDEX(Historicals!$T15:$BO15,,V$6+$D59*-1)<>"",INDEX(Historicals!$T15:$BO15,,V$6+$D59*-1),$F59*V$46*Historicals!$S15*INDEX($T$44:$BO$44,,V$6-$D59+1)),0)} -> 0 | W59: {=IFERROR(IF(INDEX(Historicals!$T15:$BO15,,W$6+$D59*-1)<>"",INDEX(Historicals!$T15:$BO15,,W$6+$D59*-1),$F59*W$46*Historicals!$S15*INDEX($T$44:$BO$44,,W$6-$D59+1)),0)} -> 0 | X59: {=IFERROR(IF(INDEX(Historicals!$T15:$BO15,,X$6+$D59*-1)<>"",INDEX(Historicals!$T15:$BO15,,X$6+$D59*-1),$F59*X$46*Historicals!$S15*INDEX($T$44:$BO$44,,X$6-$D59+1)),0)} -> 0 | Y59: {=IFERROR(IF(INDEX(Historicals!$T15:$BO15,,Y$6+$D59*-1)<>"",INDEX(Historicals!$T15:$BO15,,Y$6+$D59*-1),$F59*Y$46*Historicals!$S15*INDEX($T$44:$BO$44,,Y$6-$D59+1)),0)} -> 0 | Z59: {=IFERROR(IF(INDEX(Historicals!$T15:$BO15,,Z$6+$D59*-1)<>"",INDEX(Historicals!$T15:$BO15,,Z$6+$D59*-1),$F59*Z$46*Historicals!$S15*INDEX($T$44:$BO$44,,Z$6-$D59+1)),0)} -> 0 | AA59: {=IFERROR(IF(INDEX(Historicals!$T15:$BO15,,AA$6+$D59*-1)<>"",INDEX(Historicals!$T15:$BO15,,AA$6+$D59*-1),$F59*AA$46*Historicals!$S15*INDEX($T$44:$BO$44,,AA$6-$D59+1)),0)} -> 0 | ... BO59: {=IFERROR(IF(INDEX(Historicals!$T15:$BO15,,BO$6+$D59*-1)<>"",INDEX(Historicals!$T15:$BO15,,BO$6+$D59*-1),$F59*BO$46*Historicals!$S15*INDEX($T$44:$BO$44,,BO$6-$D59+1)),0)} -> 0
B60: =EDATE(B61,-1) -> 45013 | C60: # | D60: =D61-1 -> -43 | F60: 1 | G60: x | H60: sum | I60: =IF(H60=Forecast!$H$195,T60,IF(H60=Forecast!$H$196,BO60,IF(H60=Forecast!$H$197,SUM(T60:BO60),IF(H60=Forecast!$H$198,AVERAGE(T60:BO60),0)))) -> 0 | T60: {=IFERROR(IF(INDEX(Historicals!$T16:$BO16,,T$6+$D60*-1)<>"",INDEX(Historicals!$T16:$BO16,,T$6+$D60*-1),$F60*T$46*Historicals!$S16*INDEX($T$44:$BO$44,,T$6-$D60+1)),0)} -> 0 | U60: {=IFERROR(IF(INDEX(Historicals!$T16:$BO16,,U$6+$D60*-1)<>"",INDEX(Historicals!$T16:$BO16,,U$6+$D60*-1),$F60*U$46*Historicals!$S16*INDEX($T$44:$BO$44,,U$6-$D60+1)),0)} -> 0 | V60: {=IFERROR(IF(INDEX(Historicals!$T16:$BO16,,V$6+$D60*-1)<>"",INDEX(Historicals!$T16:$BO16,,V$6+$D60*-1),$F60*V$46*Historicals!$S16*INDEX($T$44:$BO$44,,V$6-$D60+1)),0)} -> 0 | W60: {=IFERROR(IF(INDEX(Historicals!$T16:$BO16,,W$6+$D60*-1)<>"",INDEX(Historicals!$T16:$BO16,,W$6+$D60*-1),$F60*W$46*Historicals!$S16*INDEX($T$44:$BO$44,,W$6-$D60+1)),0)} -> 0 | X60: {=IFERROR(IF(INDEX(Historicals!$T16:$BO16,,X$6+$D60*-1)<>"",INDEX(Historicals!$T16:$BO16,,X$6+$D60*-1),$F60*X$46*Historicals!$S16*INDEX($T$44:$BO$44,,X$6-$D60+1)),0)} -> 0 | Y60: {=IFERROR(IF(INDEX(Historicals!$T16:$BO16,,Y$6+$D60*-1)<>"",INDEX(Historicals!$T16:$BO16,,Y$6+$D60*-1),$F60*Y$46*Historicals!$S16*INDEX($T$44:$BO$44,,Y$6-$D60+1)),0)} -> 0 | Z60: {=IFERROR(IF(INDEX(Historicals!$T16:$BO16,,Z$6+$D60*-1)<>"",INDEX(Historicals!$T16:$BO16,,Z$6+$D60*-1),$F60*Z$46*Historicals!$S16*INDEX($T$44:$BO$44,,Z$6-$D60+1)),0)} -> 0 | AA60: {=IFERROR(IF(INDEX(Historicals!$T16:$BO16,,AA$6+$D60*-1)<>"",INDEX(Historicals!$T16:$BO16,,AA$6+$D60*-1),$F60*AA$46*Historicals!$S16*INDEX($T$44:$BO$44,,AA$6-$D60+1)),0)} -> 0 | ... BO60: {=IFERROR(IF(INDEX(Historicals!$T16:$BO16,,BO$6+$D60*-1)<>"",INDEX(Historicals!$T16:$BO16,,BO$6+$D60*-1),$F60*BO$46*Historicals!$S16*INDEX($T$44:$BO$44,,BO$6-$D60+1)),0)} -> 0
B61: =EDATE(B62,-1) -> 45044 | C61: # | D61: =D62-1 -> -42 | F61: 1 | G61: x | H61: sum | I61: =IF(H61=Forecast!$H$195,T61,IF(H61=Forecast!$H$196,BO61,IF(H61=Forecast!$H$197,SUM(T61:BO61),IF(H61=Forecast!$H$198,AVERAGE(T61:BO61),0)))) -> 0 | T61: {=IFERROR(IF(INDEX(Historicals!$T17:$BO17,,T$6+$D61*-1)<>"",INDEX(Historicals!$T17:$BO17,,T$6+$D61*-1),$F61*T$46*Historicals!$S17*INDEX($T$44:$BO$44,,T$6-$D61+1)),0)} -> 0 | U61: {=IFERROR(IF(INDEX(Historicals!$T17:$BO17,,U$6+$D61*-1)<>"",INDEX(Historicals!$T17:$BO17,,U$6+$D61*-1),$F61*U$46*Historicals!$S17*INDEX($T$44:$BO$44,,U$6-$D61+1)),0)} -> 0 | V61: {=IFERROR(IF(INDEX(Historicals!$T17:$BO17,,V$6+$D61*-1)<>"",INDEX(Historicals!$T17:$BO17,,V$6+$D61*-1),$F61*V$46*Historicals!$S17*INDEX($T$44:$BO$44,,V$6-$D61+1)),0)} -> 0 | W61: {=IFERROR(IF(INDEX(Historicals!$T17:$BO17,,W$6+$D61*-1)<>"",INDEX(Historicals!$T17:$BO17,,W$6+$D61*-1),$F61*W$46*Historicals!$S17*INDEX($T$44:$BO$44,,W$6-$D61+1)),0)} -> 0 | X61: {=IFERROR(IF(INDEX(Historicals!$T17:$BO17,,X$6+$D61*-1)<>"",INDEX(Historicals!$T17:$BO17,,X$6+$D61*-1),$F61*X$46*Historicals!$S17*INDEX($T$44:$BO$44,,X$6-$D61+1)),0)} -> 0 | Y61: {=IFERROR(IF(INDEX(Historicals!$T17:$BO17,,Y$6+$D61*-1)<>"",INDEX(Historicals!$T17:$BO17,,Y$6+$D61*-1),$F61*Y$46*Historicals!$S17*INDEX($T$44:$BO$44,,Y$6-$D61+1)),0)} -> 0 | Z61: {=IFERROR(IF(INDEX(Historicals!$T17:$BO17,,Z$6+$D61*-1)<>"",INDEX(Historicals!$T17:$BO17,,Z$6+$D61*-1),$F61*Z$46*Historicals!$S17*INDEX($T$44:$BO$44,,Z$6-$D61+1)),0)} -> 0 | AA61: {=IFERROR(IF(INDEX(Historicals!$T17:$BO17,,AA$6+$D61*-1)<>"",INDEX(Historicals!$T17:$BO17,,AA$6+$D61*-1),$F61*AA$46*Historicals!$S17*INDEX($T$44:$BO$44,,AA$6-$D61+1)),0)} -> 0 | ... BO61: {=IFERROR(IF(INDEX(Historicals!$T17:$BO17,,BO$6+$D61*-1)<>"",INDEX(Historicals!$T17:$BO17,,BO$6+$D61*-1),$F61*BO$46*Historicals!$S17*INDEX($T$44:$BO$44,,BO$6-$D61+1)),0)} -> 0
B62: =EDATE(B63,-1) -> 45074 | C62: # | D62: =D63-1 -> -41 | F62: 1 | G62: x | H62: sum | I62: =IF(H62=Forecast!$H$195,T62,IF(H62=Forecast!$H$196,BO62,IF(H62=Forecast!$H$197,SUM(T62:BO62),IF(H62=Forecast!$H$198,AVERAGE(T62:BO62),0)))) -> 0 | T62: {=IFERROR(IF(INDEX(Historicals!$T18:$BO18,,T$6+$D62*-1)<>"",INDEX(Historicals!$T18:$BO18,,T$6+$D62*-1),$F62*T$46*Historicals!$S18*INDEX($T$44:$BO$44,,T$6-$D62+1)),0)} -> 0 | U62: {=IFERROR(IF(INDEX(Historicals!$T18:$BO18,,U$6+$D62*-1)<>"",INDEX(Historicals!$T18:$BO18,,U$6+$D62*-1),$F62*U$46*Historicals!$S18*INDEX($T$44:$BO$44,,U$6-$D62+1)),0)} -> 0 | V62: {=IFERROR(IF(INDEX(Historicals!$T18:$BO18,,V$6+$D62*-1)<>"",INDEX(Historicals!$T18:$BO18,,V$6+$D62*-1),$F62*V$46*Historicals!$S18*INDEX($T$44:$BO$44,,V$6-$D62+1)),0)} -> 0 | W62: {=IFERROR(IF(INDEX(Historicals!$T18:$BO18,,W$6+$D62*-1)<>"",INDEX(Historicals!$T18:$BO18,,W$6+$D62*-1),$F62*W$46*Historicals!$S18*INDEX($T$44:$BO$44,,W$6-$D62+1)),0)} -> 0 | X62: {=IFERROR(IF(INDEX(Historicals!$T18:$BO18,,X$6+$D62*-1)<>"",INDEX(Historicals!$T18:$BO18,,X$6+$D62*-1),$F62*X$46*Historicals!$S18*INDEX($T$44:$BO$44,,X$6-$D62+1)),0)} -> 0 | Y62: {=IFERROR(IF(INDEX(Historicals!$T18:$BO18,,Y$6+$D62*-1)<>"",INDEX(Historicals!$T18:$BO18,,Y$6+$D62*-1),$F62*Y$46*Historicals!$S18*INDEX($T$44:$BO$44,,Y$6-$D62+1)),0)} -> 0 | Z62: {=IFERROR(IF(INDEX(Historicals!$T18:$BO18,,Z$6+$D62*-1)<>"",INDEX(Historicals!$T18:$BO18,,Z$6+$D62*-1),$F62*Z$46*Historicals!$S18*INDEX($T$44:$BO$44,,Z$6-$D62+1)),0)} -> 0 | AA62: {=IFERROR(IF(INDEX(Historicals!$T18:$BO18,,AA$6+$D62*-1)<>"",INDEX(Historicals!$T18:$BO18,,AA$6+$D62*-1),$F62*AA$46*Historicals!$S18*INDEX($T$44:$BO$44,,AA$6-$D62+1)),0)} -> 0 | ... BO62: {=IFERROR(IF(INDEX(Historicals!$T18:$BO18,,BO$6+$D62*-1)<>"",INDEX(Historicals!$T18:$BO18,,BO$6+$D62*-1),$F62*BO$46*Historicals!$S18*INDEX($T$44:$BO$44,,BO$6-$D62+1)),0)} -> 0
B63: =EDATE(B64,-1) -> 45105 | C63: # | D63: =D64-1 -> -40 | F63: 1 | G63: x | H63: sum | I63: =IF(H63=Forecast!$H$195,T63,IF(H63=Forecast!$H$196,BO63,IF(H63=Forecast!$H$197,SUM(T63:BO63),IF(H63=Forecast!$H$198,AVERAGE(T63:BO63),0)))) -> 0 | T63: {=IFERROR(IF(INDEX(Historicals!$T19:$BO19,,T$6+$D63*-1)<>"",INDEX(Historicals!$T19:$BO19,,T$6+$D63*-1),$F63*T$46*Historicals!$S19*INDEX($T$44:$BO$44,,T$6-$D63+1)),0)} -> 0 | U63: {=IFERROR(IF(INDEX(Historicals!$T19:$BO19,,U$6+$D63*-1)<>"",INDEX(Historicals!$T19:$BO19,,U$6+$D63*-1),$F63*U$46*Historicals!$S19*INDEX($T$44:$BO$44,,U$6-$D63+1)),0)} -> 0 | V63: {=IFERROR(IF(INDEX(Historicals!$T19:$BO19,,V$6+$D63*-1)<>"",INDEX(Historicals!$T19:$BO19,,V$6+$D63*-1),$F63*V$46*Historicals!$S19*INDEX($T$44:$BO$44,,V$6-$D63+1)),0)} -> 0 | W63: {=IFERROR(IF(INDEX(Historicals!$T19:$BO19,,W$6+$D63*-1)<>"",INDEX(Historicals!$T19:$BO19,,W$6+$D63*-1),$F63*W$46*Historicals!$S19*INDEX($T$44:$BO$44,,W$6-$D63+1)),0)} -> 0 | X63: {=IFERROR(IF(INDEX(Historicals!$T19:$BO19,,X$6+$D63*-1)<>"",INDEX(Historicals!$T19:$BO19,,X$6+$D63*-1),$F63*X$46*Historicals!$S19*INDEX($T$44:$BO$44,,X$6-$D63+1)),0)} -> 0 | Y63: {=IFERROR(IF(INDEX(Historicals!$T19:$BO19,,Y$6+$D63*-1)<>"",INDEX(Historicals!$T19:$BO19,,Y$6+$D63*-1),$F63*Y$46*Historicals!$S19*INDEX($T$44:$BO$44,,Y$6-$D63+1)),0)} -> 0 | Z63: {=IFERROR(IF(INDEX(Historicals!$T19:$BO19,,Z$6+$D63*-1)<>"",INDEX(Historicals!$T19:$BO19,,Z$6+$D63*-1),$F63*Z$46*Historicals!$S19*INDEX($T$44:$BO$44,,Z$6-$D63+1)),0)} -> 0 | AA63: {=IFERROR(IF(INDEX(Historicals!$T19:$BO19,,AA$6+$D63*-1)<>"",INDEX(Historicals!$T19:$BO19,,AA$6+$D63*-1),$F63*AA$46*Historicals!$S19*INDEX($T$44:$BO$44,,AA$6-$D63+1)),0)} -> 0 | ... BO63: {=IFERROR(IF(INDEX(Historicals!$T19:$BO19,,BO$6+$D63*-1)<>"",INDEX(Historicals!$T19:$BO19,,BO$6+$D63*-1),$F63*BO$46*Historicals!$S19*INDEX($T$44:$BO$44,,BO$6-$D63+1)),0)} -> 0
B64: =EDATE(B65,-1) -> 45135 | C64: # | D64: =D65-1 -> -39 | F64: 1 | G64: x | H64: sum | I64: =IF(H64=Forecast!$H$195,T64,IF(H64=Forecast!$H$196,BO64,IF(H64=Forecast!$H$197,SUM(T64:BO64),IF(H64=Forecast!$H$198,AVERAGE(T64:BO64),0)))) -> 0 | T64: {=IFERROR(IF(INDEX(Historicals!$T20:$BO20,,T$6+$D64*-1)<>"",INDEX(Historicals!$T20:$BO20,,T$6+$D64*-1),$F64*T$46*Historicals!$S20*INDEX($T$44:$BO$44,,T$6-$D64+1)),0)} -> 0 | U64: {=IFERROR(IF(INDEX(Historicals!$T20:$BO20,,U$6+$D64*-1)<>"",INDEX(Historicals!$T20:$BO20,,U$6+$D64*-1),$F64*U$46*Historicals!$S20*INDEX($T$44:$BO$44,,U$6-$D64+1)),0)} -> 0 | V64: {=IFERROR(IF(INDEX(Historicals!$T20:$BO20,,V$6+$D64*-1)<>"",INDEX(Historicals!$T20:$BO20,,V$6+$D64*-1),$F64*V$46*Historicals!$S20*INDEX($T$44:$BO$44,,V$6-$D64+1)),0)} -> 0 | W64: {=IFERROR(IF(INDEX(Historicals!$T20:$BO20,,W$6+$D64*-1)<>"",INDEX(Historicals!$T20:$BO20,,W$6+$D64*-1),$F64*W$46*Historicals!$S20*INDEX($T$44:$BO$44,,W$6-$D64+1)),0)} -> 0 | X64: {=IFERROR(IF(INDEX(Historicals!$T20:$BO20,,X$6+$D64*-1)<>"",INDEX(Historicals!$T20:$BO20,,X$6+$D64*-1),$F64*X$46*Historicals!$S20*INDEX($T$44:$BO$44,,X$6-$D64+1)),0)} -> 0 | Y64: {=IFERROR(IF(INDEX(Historicals!$T20:$BO20,,Y$6+$D64*-1)<>"",INDEX(Historicals!$T20:$BO20,,Y$6+$D64*-1),$F64*Y$46*Historicals!$S20*INDEX($T$44:$BO$44,,Y$6-$D64+1)),0)} -> 0 | Z64: {=IFERROR(IF(INDEX(Historicals!$T20:$BO20,,Z$6+$D64*-1)<>"",INDEX(Historicals!$T20:$BO20,,Z$6+$D64*-1),$F64*Z$46*Historicals!$S20*INDEX($T$44:$BO$44,,Z$6-$D64+1)),0)} -> 0 | AA64: {=IFERROR(IF(INDEX(Historicals!$T20:$BO20,,AA$6+$D64*-1)<>"",INDEX(Historicals!$T20:$BO20,,AA$6+$D64*-1),$F64*AA$46*Historicals!$S20*INDEX($T$44:$BO$44,,AA$6-$D64+1)),0)} -> 0 | ... BO64: {=IFERROR(IF(INDEX(Historicals!$T20:$BO20,,BO$6+$D64*-1)<>"",INDEX(Historicals!$T20:$BO20,,BO$6+$D64*-1),$F64*BO$46*Historicals!$S20*INDEX($T$44:$BO$44,,BO$6-$D64+1)),0)} -> 0
B65: =EDATE(B66,-1) -> 45166 | C65: # | D65: =D66-1 -> -38 | F65: 1 | G65: x | H65: sum | I65: =IF(H65=Forecast!$H$195,T65,IF(H65=Forecast!$H$196,BO65,IF(H65=Forecast!$H$197,SUM(T65:BO65),IF(H65=Forecast!$H$198,AVERAGE(T65:BO65),0)))) -> 0 | T65: {=IFERROR(IF(INDEX(Historicals!$T21:$BO21,,T$6+$D65*-1)<>"",INDEX(Historicals!$T21:$BO21,,T$6+$D65*-1),$F65*T$46*Historicals!$S21*INDEX($T$44:$BO$44,,T$6-$D65+1)),0)} -> 0 | U65: {=IFERROR(IF(INDEX(Historicals!$T21:$BO21,,U$6+$D65*-1)<>"",INDEX(Historicals!$T21:$BO21,,U$6+$D65*-1),$F65*U$46*Historicals!$S21*INDEX($T$44:$BO$44,,U$6-$D65+1)),0)} -> 0 | V65: {=IFERROR(IF(INDEX(Historicals!$T21:$BO21,,V$6+$D65*-1)<>"",INDEX(Historicals!$T21:$BO21,,V$6+$D65*-1),$F65*V$46*Historicals!$S21*INDEX($T$44:$BO$44,,V$6-$D65+1)),0)} -> 0 | W65: {=IFERROR(IF(INDEX(Historicals!$T21:$BO21,,W$6+$D65*-1)<>"",INDEX(Historicals!$T21:$BO21,,W$6+$D65*-1),$F65*W$46*Historicals!$S21*INDEX($T$44:$BO$44,,W$6-$D65+1)),0)} -> 0 | X65: {=IFERROR(IF(INDEX(Historicals!$T21:$BO21,,X$6+$D65*-1)<>"",INDEX(Historicals!$T21:$BO21,,X$6+$D65*-1),$F65*X$46*Historicals!$S21*INDEX($T$44:$BO$44,,X$6-$D65+1)),0)} -> 0 | Y65: {=IFERROR(IF(INDEX(Historicals!$T21:$BO21,,Y$6+$D65*-1)<>"",INDEX(Historicals!$T21:$BO21,,Y$6+$D65*-1),$F65*Y$46*Historicals!$S21*INDEX($T$44:$BO$44,,Y$6-$D65+1)),0)} -> 0 | Z65: {=IFERROR(IF(INDEX(Historicals!$T21:$BO21,,Z$6+$D65*-1)<>"",INDEX(Historicals!$T21:$BO21,,Z$6+$D65*-1),$F65*Z$46*Historicals!$S21*INDEX($T$44:$BO$44,,Z$6-$D65+1)),0)} -> 0 | AA65: {=IFERROR(IF(INDEX(Historicals!$T21:$BO21,,AA$6+$D65*-1)<>"",INDEX(Historicals!$T21:$BO21,,AA$6+$D65*-1),$F65*AA$46*Historicals!$S21*INDEX($T$44:$BO$44,,AA$6-$D65+1)),0)} -> 0 | ... BO65: {=IFERROR(IF(INDEX(Historicals!$T21:$BO21,,BO$6+$D65*-1)<>"",INDEX(Historicals!$T21:$BO21,,BO$6+$D65*-1),$F65*BO$46*Historicals!$S21*INDEX($T$44:$BO$44,,BO$6-$D65+1)),0)} -> 0
B66: =EDATE(B67,-1) -> 45197 | C66: # | D66: =D67-1 -> -37 | F66: 1 | G66: x | H66: sum | I66: =IF(H66=Forecast!$H$195,T66,IF(H66=Forecast!$H$196,BO66,IF(H66=Forecast!$H$197,SUM(T66:BO66),IF(H66=Forecast!$H$198,AVERAGE(T66:BO66),0)))) -> 0 | T66: {=IFERROR(IF(INDEX(Historicals!$T22:$BO22,,T$6+$D66*-1)<>"",INDEX(Historicals!$T22:$BO22,,T$6+$D66*-1),$F66*T$46*Historicals!$S22*INDEX($T$44:$BO$44,,T$6-$D66+1)),0)} -> 0 | U66: {=IFERROR(IF(INDEX(Historicals!$T22:$BO22,,U$6+$D66*-1)<>"",INDEX(Historicals!$T22:$BO22,,U$6+$D66*-1),$F66*U$46*Historicals!$S22*INDEX($T$44:$BO$44,,U$6-$D66+1)),0)} -> 0 | V66: {=IFERROR(IF(INDEX(Historicals!$T22:$BO22,,V$6+$D66*-1)<>"",INDEX(Historicals!$T22:$BO22,,V$6+$D66*-1),$F66*V$46*Historicals!$S22*INDEX($T$44:$BO$44,,V$6-$D66+1)),0)} -> 0 | W66: {=IFERROR(IF(INDEX(Historicals!$T22:$BO22,,W$6+$D66*-1)<>"",INDEX(Historicals!$T22:$BO22,,W$6+$D66*-1),$F66*W$46*Historicals!$S22*INDEX($T$44:$BO$44,,W$6-$D66+1)),0)} -> 0 | X66: {=IFERROR(IF(INDEX(Historicals!$T22:$BO22,,X$6+$D66*-1)<>"",INDEX(Historicals!$T22:$BO22,,X$6+$D66*-1),$F66*X$46*Historicals!$S22*INDEX($T$44:$BO$44,,X$6-$D66+1)),0)} -> 0 | Y66: {=IFERROR(IF(INDEX(Historicals!$T22:$BO22,,Y$6+$D66*-1)<>"",INDEX(Historicals!$T22:$BO22,,Y$6+$D66*-1),$F66*Y$46*Historicals!$S22*INDEX($T$44:$BO$44,,Y$6-$D66+1)),0)} -> 0 | Z66: {=IFERROR(IF(INDEX(Historicals!$T22:$BO22,,Z$6+$D66*-1)<>"",INDEX(Historicals!$T22:$BO22,,Z$6+$D66*-1),$F66*Z$46*Historicals!$S22*INDEX($T$44:$BO$44,,Z$6-$D66+1)),0)} -> 0 | AA66: {=IFERROR(IF(INDEX(Historicals!$T22:$BO22,,AA$6+$D66*-1)<>"",INDEX(Historicals!$T22:$BO22,,AA$6+$D66*-1),$F66*AA$46*Historicals!$S22*INDEX($T$44:$BO$44,,AA$6-$D66+1)),0)} -> 0 | ... BO66: {=IFERROR(IF(INDEX(Historicals!$T22:$BO22,,BO$6+$D66*-1)<>"",INDEX(Historicals!$T22:$BO22,,BO$6+$D66*-1),$F66*BO$46*Historicals!$S22*INDEX($T$44:$BO$44,,BO$6-$D66+1)),0)} -> 0
B67: =EDATE(B68,-1) -> 45227 | C67: # | D67: =D68-1 -> -36 | F67: 1 | G67: x | H67: sum | I67: =IF(H67=Forecast!$H$195,T67,IF(H67=Forecast!$H$196,BO67,IF(H67=Forecast!$H$197,SUM(T67:BO67),IF(H67=Forecast!$H$198,AVERAGE(T67:BO67),0)))) -> 0 | T67: {=IFERROR(IF(INDEX(Historicals!$T23:$BO23,,T$6+$D67*-1)<>"",INDEX(Historicals!$T23:$BO23,,T$6+$D67*-1),$F67*T$46*Historicals!$S23*INDEX($T$44:$BO$44,,T$6-$D67+1)),0)} -> 0 | U67: {=IFERROR(IF(INDEX(Historicals!$T23:$BO23,,U$6+$D67*-1)<>"",INDEX(Historicals!$T23:$BO23,,U$6+$D67*-1),$F67*U$46*Historicals!$S23*INDEX($T$44:$BO$44,,U$6-$D67+1)),0)} -> 0 | V67: {=IFERROR(IF(INDEX(Historicals!$T23:$BO23,,V$6+$D67*-1)<>"",INDEX(Historicals!$T23:$BO23,,V$6+$D67*-1),$F67*V$46*Historicals!$S23*INDEX($T$44:$BO$44,,V$6-$D67+1)),0)} -> 0 | W67: {=IFERROR(IF(INDEX(Historicals!$T23:$BO23,,W$6+$D67*-1)<>"",INDEX(Historicals!$T23:$BO23,,W$6+$D67*-1),$F67*W$46*Historicals!$S23*INDEX($T$44:$BO$44,,W$6-$D67+1)),0)} -> 0 | X67: {=IFERROR(IF(INDEX(Historicals!$T23:$BO23,,X$6+$D67*-1)<>"",INDEX(Historicals!$T23:$BO23,,X$6+$D67*-1),$F67*X$46*Historicals!$S23*INDEX($T$44:$BO$44,,X$6-$D67+1)),0)} -> 0 | Y67: {=IFERROR(IF(INDEX(Historicals!$T23:$BO23,,Y$6+$D67*-1)<>"",INDEX(Historicals!$T23:$BO23,,Y$6+$D67*-1),$F67*Y$46*Historicals!$S23*INDEX($T$44:$BO$44,,Y$6-$D67+1)),0)} -> 0 | Z67: {=IFERROR(IF(INDEX(Historicals!$T23:$BO23,,Z$6+$D67*-1)<>"",INDEX(Historicals!$T23:$BO23,,Z$6+$D67*-1),$F67*Z$46*Historicals!$S23*INDEX($T$44:$BO$44,,Z$6-$D67+1)),0)} -> 0 | AA67: {=IFERROR(IF(INDEX(Historicals!$T23:$BO23,,AA$6+$D67*-1)<>"",INDEX(Historicals!$T23:$BO23,,AA$6+$D67*-1),$F67*AA$46*Historicals!$S23*INDEX($T$44:$BO$44,,AA$6-$D67+1)),0)} -> 0 | ... BO67: {=IFERROR(IF(INDEX(Historicals!$T23:$BO23,,BO$6+$D67*-1)<>"",INDEX(Historicals!$T23:$BO23,,BO$6+$D67*-1),$F67*BO$46*Historicals!$S23*INDEX($T$44:$BO$44,,BO$6-$D67+1)),0)} -> 0
... B103: =EDATE(B104,-1) -> 46325 | C103: # | D103: =D104-1 -> 0 | F103: 1 | G103: x | H103: sum | I103: =IF(H103=Forecast!$H$195,T103,IF(H103=Forecast!$H$196,BO103,IF(H103=Forecast!$H$197,SUM(T103:BO103),IF(H103=Forecast!$H$198,AVERAGE(T103:BO103),0)))) -> 3999.0234 | T103: {=IFERROR(IF(INDEX(Historicals!$T59:$BO59,,T$6+$D103*-1)<>"",INDEX(Historicals!$T59:$BO59,,T$6+$D103*-1),$F103*T$46*Historicals!$S59*INDEX($T$44:$BO$44,,T$6-$D103+1)),0)} -> 2000 | U103: {=IFERROR(IF(INDEX(Historicals!$T59:$BO59,,U$6+$D103*-1)<>"",INDEX(Historicals!$T59:$BO59,,U$6+$D103*-1),$F103*U$46*Historicals!$S59*INDEX($T$44:$BO$44,,U$6-$D103+1)),0)} -> 0 | V103: {=IFERROR(IF(INDEX(Historicals!$T59:$BO59,,V$6+$D103*-1)<>"",INDEX(Historicals!$T59:$BO59,,V$6+$D103*-1),$F103*V$46*Historicals!$S59*INDEX($T$44:$BO$44,,V$6-$D103+1)),0)} -> 1000 | W103: {=IFERROR(IF(INDEX(Historicals!$T59:$BO59,,W$6+$D103*-1)<>"",INDEX(Historicals!$T59:$BO59,,W$6+$D103*-1),$F103*W$46*Historicals!$S59*INDEX($T$44:$BO$44,,W$6-$D103+1)),0)} -> 0 | X103: {=IFERROR(IF(INDEX(Historicals!$T59:$BO59,,X$6+$D103*-1)<>"",INDEX(Historicals!$T59:$BO59,,X$6+$D103*-1),$F103*X$46*Historicals!$S59*INDEX($T$44:$BO$44,,X$6-$D103+1)),0)} -> 0 | Y103: {=IFERROR(IF(INDEX(Historicals!$T59:$BO59,,Y$6+$D103*-1)<>"",INDEX(Historicals!$T59:$BO59,,Y$6+$D103*-1),$F103*Y$46*Historicals!$S59*INDEX($T$44:$BO$44,,Y$6-$D103+1)),0)} -> 500 | Z103: {=IFERROR(IF(INDEX(Historicals!$T59:$BO59,,Z$6+$D103*-1)<>"",INDEX(Historicals!$T59:$BO59,,Z$6+$D103*-1),$F103*Z$46*Historicals!$S59*INDEX($T$44:$BO$44,,Z$6-$D103+1)),0)} -> 0 | AA103: {=IFERROR(IF(INDEX(Historicals!$T59:$BO59,,AA$6+$D103*-1)<>"",INDEX(Historicals!$T59:$BO59,,AA$6+$D103*-1),$F103*AA$46*Historicals!$S59*INDEX($T$44:$BO$44,,AA$6-$D103+1)),0)} -> 0 | ... BO103: {=IFERROR(IF(INDEX(Historicals!$T59:$BO59,,BO$6+$D103*-1)<>"",INDEX(Historicals!$T59:$BO59,,BO$6+$D103*-1),$F103*BO$46*Historicals!$S59*INDEX($T$44:$BO$44,,BO$6-$D103+1)),0)} -> 0
B104: =INDEX(T$4:BO$4,,D104) -> 46356 | C104: # | D104: 1 | F104: 1 | G104: x | H104: sum | I104: =IF(H104=Forecast!$H$195,T104,IF(H104=Forecast!$H$196,BO104,IF(H104=Forecast!$H$197,SUM(T104:BO104),IF(H104=Forecast!$H$198,AVERAGE(T104:BO104),0)))) -> 1099.9832 | T104: =IF(T$6<$D104,0,INDEX($T$44:$BO$44,,T$6-$D104+1)*INDEX($T$52:$BO$52,,$D104)*IF(T$6=$D104,1,$F104)*T$46) -> 550 | U104: =IF(U$6<$D104,0,INDEX($T$44:$BO$44,,U$6-$D104+1)*INDEX($T$52:$BO$52,,$D104)*IF(U$6=$D104,1,$F104)*U$46) -> 0 | V104: =IF(V$6<$D104,0,INDEX($T$44:$BO$44,,V$6-$D104+1)*INDEX($T$52:$BO$52,,$D104)*IF(V$6=$D104,1,$F104)*V$46) -> 0 | W104: =IF(W$6<$D104,0,INDEX($T$44:$BO$44,,W$6-$D104+1)*INDEX($T$52:$BO$52,,$D104)*IF(W$6=$D104,1,$F104)*W$46) -> 275 | X104: =IF(X$6<$D104,0,INDEX($T$44:$BO$44,,X$6-$D104+1)*INDEX($T$52:$BO$52,,$D104)*IF(X$6=$D104,1,$F104)*X$46) -> 0 | Y104: =IF(Y$6<$D104,0,INDEX($T$44:$BO$44,,Y$6-$D104+1)*INDEX($T$52:$BO$52,,$D104)*IF(Y$6=$D104,1,$F104)*Y$46) -> 0 | Z104: =IF(Z$6<$D104,0,INDEX($T$44:$BO$44,,Z$6-$D104+1)*INDEX($T$52:$BO$52,,$D104)*IF(Z$6=$D104,1,$F104)*Z$46) -> 137.5 | AA104: =IF(AA$6<$D104,0,INDEX($T$44:$BO$44,,AA$6-$D104+1)*INDEX($T$52:$BO$52,,$D104)*IF(AA$6=$D104,1,$F104)*AA$46) -> 0 | ... BO104: =IF(BO$6<$D104,0,INDEX($T$44:$BO$44,,BO$6-$D104+1)*INDEX($T$52:$BO$52,,$D104)*IF(BO$6=$D104,1,$F104)*BO$46) -> 0
B105: =INDEX(T$4:BO$4,,D105) -> 46387 | C105: # | D105: =D104+1 -> 2 | F105: =F104 -> 1 | G105: x | H105: sum | I105: =IF(H105=Forecast!$H$195,T105,IF(H105=Forecast!$H$196,BO105,IF(H105=Forecast!$H$197,SUM(T105:BO105),IF(H105=Forecast!$H$198,AVERAGE(T105:BO105),0)))) -> 1941.4704 | T105: =IF(T$6<$D105,0,INDEX($T$44:$BO$44,,T$6-$D105+1)*INDEX($T$52:$BO$52,,$D105)*IF(T$6=$D105,1,$F105)*T$46) -> 0 | U105: =IF(U$6<$D105,0,INDEX($T$44:$BO$44,,U$6-$D105+1)*INDEX($T$52:$BO$52,,$D105)*IF(U$6=$D105,1,$F105)*U$46) -> 970.75 | V105: =IF(V$6<$D105,0,INDEX($T$44:$BO$44,,V$6-$D105+1)*INDEX($T$52:$BO$52,,$D105)*IF(V$6=$D105,1,$F105)*V$46) -> 0 | W105: =IF(W$6<$D105,0,INDEX($T$44:$BO$44,,W$6-$D105+1)*INDEX($T$52:$BO$52,,$D105)*IF(W$6=$D105,1,$F105)*W$46) -> 0 | X105: =IF(X$6<$D105,0,INDEX($T$44:$BO$44,,X$6-$D105+1)*INDEX($T$52:$BO$52,,$D105)*IF(X$6=$D105,1,$F105)*X$46) -> 485.375 | Y105: =IF(Y$6<$D105,0,INDEX($T$44:$BO$44,,Y$6-$D105+1)*INDEX($T$52:$BO$52,,$D105)*IF(Y$6=$D105,1,$F105)*Y$46) -> 0 | Z105: =IF(Z$6<$D105,0,INDEX($T$44:$BO$44,,Z$6-$D105+1)*INDEX($T$52:$BO$52,,$D105)*IF(Z$6=$D105,1,$F105)*Z$46) -> 0 | AA105: =IF(AA$6<$D105,0,INDEX($T$44:$BO$44,,AA$6-$D105+1)*INDEX($T$52:$BO$52,,$D105)*IF(AA$6=$D105,1,$F105)*AA$46) -> 242.6875 | ... BO105: =IF(BO$6<$D105,0,INDEX($T$44:$BO$44,,BO$6-$D105+1)*INDEX($T$52:$BO$52,,$D105)*IF(BO$6=$D105,1,$F105)*BO$46) -> 0
B106: =INDEX(T$4:BO$4,,D106) -> 46418 | C106: # | D106: =D105+1 -> 3 | F106: =F105 -> 1 | G106: x | H106: sum | I106: =IF(H106=Forecast!$H$195,T106,IF(H106=Forecast!$H$196,BO106,IF(H106=Forecast!$H$197,SUM(T106:BO106),IF(H106=Forecast!$H$198,AVERAGE(T106:BO106),0)))) -> 3203.9115 | T106: =IF(T$6<$D106,0,INDEX($T$44:$BO$44,,T$6-$D106+1)*INDEX($T$52:$BO$52,,$D106)*IF(T$6=$D106,1,$F106)*T$46) -> 0 | U106: =IF(U$6<$D106,0,INDEX($T$44:$BO$44,,U$6-$D106+1)*INDEX($T$52:$BO$52,,$D106)*IF(U$6=$D106,1,$F106)*U$46) -> 0 | V106: =IF(V$6<$D106,0,INDEX($T$44:$BO$44,,V$6-$D106+1)*INDEX($T$52:$BO$52,,$D106)*IF(V$6=$D106,1,$F106)*V$46) -> 1601.9802 | W106: =IF(W$6<$D106,0,INDEX($T$44:$BO$44,,W$6-$D106+1)*INDEX($T$52:$BO$52,,$D106)*IF(W$6=$D106,1,$F106)*W$46) -> 0 | X106: =IF(X$6<$D106,0,INDEX($T$44:$BO$44,,X$6-$D106+1)*INDEX($T$52:$BO$52,,$D106)*IF(X$6=$D106,1,$F106)*X$46) -> 0 | Y106: =IF(Y$6<$D106,0,INDEX($T$44:$BO$44,,Y$6-$D106+1)*INDEX($T$52:$BO$52,,$D106)*IF(Y$6=$D106,1,$F106)*Y$46) -> 800.99009 | Z106: =IF(Z$6<$D106,0,INDEX($T$44:$BO$44,,Z$6-$D106+1)*INDEX($T$52:$BO$52,,$D106)*IF(Z$6=$D106,1,$F106)*Z$46) -> 0 | AA106: =IF(AA$6<$D106,0,INDEX($T$44:$BO$44,,AA$6-$D106+1)*INDEX($T$52:$BO$52,,$D106)*IF(AA$6=$D106,1,$F106)*AA$46) -> 0 | ... BO106: =IF(BO$6<$D106,0,INDEX($T$44:$BO$44,,BO$6-$D106+1)*INDEX($T$52:$BO$52,,$D106)*IF(BO$6=$D106,1,$F106)*BO$46) -> 0.048888556
B107: =INDEX(T$4:BO$4,,D107) -> 46446 | C107: # | D107: =D106+1 -> 4 | F107: =F106 -> 1 | G107: x | H107: sum | I107: =IF(H107=Forecast!$H$195,T107,IF(H107=Forecast!$H$196,BO107,IF(H107=Forecast!$H$197,SUM(T107:BO107),IF(H107=Forecast!$H$198,AVERAGE(T107:BO107),0)))) -> 4974.6775 | T107: =IF(T$6<$D107,0,INDEX($T$44:$BO$44,,T$6-$D107+1)*INDEX($T$52:$BO$52,,$D107)*IF(T$6=$D107,1,$F107)*T$46) -> 0 | U107: =IF(U$6<$D107,0,INDEX($T$44:$BO$44,,U$6-$D107+1)*INDEX($T$52:$BO$52,,$D107)*IF(U$6=$D107,1,$F107)*U$46) -> 0 | V107: =IF(V$6<$D107,0,INDEX($T$44:$BO$44,,V$6-$D107+1)*INDEX($T$52:$BO$52,,$D107)*IF(V$6=$D107,1,$F107)*V$46) -> 0 | W107: =IF(W$6<$D107,0,INDEX($T$44:$BO$44,,W$6-$D107+1)*INDEX($T$52:$BO$52,,$D107)*IF(W$6=$D107,1,$F107)*W$46) -> 2487.4147 | X107: =IF(X$6<$D107,0,INDEX($T$44:$BO$44,,X$6-$D107+1)*INDEX($T$52:$BO$52,,$D107)*IF(X$6=$D107,1,$F107)*X$46) -> 0 | Y107: =IF(Y$6<$D107,0,INDEX($T$44:$BO$44,,Y$6-$D107+1)*INDEX($T$52:$BO$52,,$D107)*IF(Y$6=$D107,1,$F107)*Y$46) -> 0 | Z107: =IF(Z$6<$D107,0,INDEX($T$44:$BO$44,,Z$6-$D107+1)*INDEX($T$52:$BO$52,,$D107)*IF(Z$6=$D107,1,$F107)*Z$46) -> 1243.7073 | AA107: =IF(AA$6<$D107,0,INDEX($T$44:$BO$44,,AA$6-$D107+1)*INDEX($T$52:$BO$52,,$D107)*IF(AA$6=$D107,1,$F107)*AA$46) -> 0 | ... BO107: =IF(BO$6<$D107,0,INDEX($T$44:$BO$44,,BO$6-$D107+1)*INDEX($T$52:$BO$52,,$D107)*IF(BO$6=$D107,1,$F107)*BO$46) -> 0
B108: =INDEX(T$4:BO$4,,D108) -> 46477 | C108: # | D108: =D107+1 -> 5 | F108: =F107 -> 1 | G108: x | H108: sum | I108: =IF(H108=Forecast!$H$195,T108,IF(H108=Forecast!$H$196,BO108,IF(H108=Forecast!$H$197,SUM(T108:BO108),IF(H108=Forecast!$H$198,AVERAGE(T108:BO108),0)))) -> 7311.809 | T108: =IF(T$6<$D108,0,INDEX($T$44:$BO$44,,T$6-$D108+1)*INDEX($T$52:$BO$52,,$D108)*IF(T$6=$D108,1,$F108)*T$46) -> 0 | U108: =IF(U$6<$D108,0,INDEX($T$44:$BO$44,,U$6-$D108+1)*INDEX($T$52:$BO$52,,$D108)*IF(U$6=$D108,1,$F108)*U$46) -> 0 | V108: =IF(V$6<$D108,0,INDEX($T$44:$BO$44,,V$6-$D108+1)*INDEX($T$52:$BO$52,,$D108)*IF(V$6=$D108,1,$F108)*V$46) -> 0 | W108: =IF(W$6<$D108,0,INDEX($T$44:$BO$44,,W$6-$D108+1)*INDEX($T$52:$BO$52,,$D108)*IF(W$6=$D108,1,$F108)*W$46) -> 0 | X108: =IF(X$6<$D108,0,INDEX($T$44:$BO$44,,X$6-$D108+1)*INDEX($T$52:$BO$52,,$D108)*IF(X$6=$D108,1,$F108)*X$46) -> 3656.0161 | Y108: =IF(Y$6<$D108,0,INDEX($T$44:$BO$44,,Y$6-$D108+1)*INDEX($T$52:$BO$52,,$D108)*IF(Y$6=$D108,1,$F108)*Y$46) -> 0 | Z108: =IF(Z$6<$D108,0,INDEX($T$44:$BO$44,,Z$6-$D108+1)*INDEX($T$52:$BO$52,,$D108)*IF(Z$6=$D108,1,$F108)*Z$46) -> 0 | AA108: =IF(AA$6<$D108,0,INDEX($T$44:$BO$44,,AA$6-$D108+1)*INDEX($T$52:$BO$52,,$D108)*IF(AA$6=$D108,1,$F108)*AA$46) -> 1828.008 | ... BO108: =IF(BO$6<$D108,0,INDEX($T$44:$BO$44,,BO$6-$D108+1)*INDEX($T$52:$BO$52,,$D108)*IF(BO$6=$D108,1,$F108)*BO$46) -> 0
B109: =INDEX(T$4:BO$4,,D109) -> 46507 | C109: # | D109: =D108+1 -> 6 | F109: =F108 -> 1 | G109: x | H109: sum | I109: =IF(H109=Forecast!$H$195,T109,IF(H109=Forecast!$H$196,BO109,IF(H109=Forecast!$H$197,SUM(T109:BO109),IF(H109=Forecast!$H$198,AVERAGE(T109:BO109),0)))) -> 10231.669 | T109: =IF(T$6<$D109,0,INDEX($T$44:$BO$44,,T$6-$D109+1)*INDEX($T$52:$BO$52,,$D109)*IF(T$6=$D109,1,$F109)*T$46) -> 0 | U109: =IF(U$6<$D109,0,INDEX($T$44:$BO$44,,U$6-$D109+1)*INDEX($T$52:$BO$52,,$D109)*IF(U$6=$D109,1,$F109)*U$46) -> 0 | V109: =IF(V$6<$D109,0,INDEX($T$44:$BO$44,,V$6-$D109+1)*INDEX($T$52:$BO$52,,$D109)*IF(V$6=$D109,1,$F109)*V$46) -> 0 | W109: =IF(W$6<$D109,0,INDEX($T$44:$BO$44,,W$6-$D109+1)*INDEX($T$52:$BO$52,,$D109)*IF(W$6=$D109,1,$F109)*W$46) -> 0 | X109: =IF(X$6<$D109,0,INDEX($T$44:$BO$44,,X$6-$D109+1)*INDEX($T$52:$BO$52,,$D109)*IF(X$6=$D109,1,$F109)*X$46) -> 0 | Y109: =IF(Y$6<$D109,0,INDEX($T$44:$BO$44,,Y$6-$D109+1)*INDEX($T$52:$BO$52,,$D109)*IF(Y$6=$D109,1,$F109)*Y$46) -> 5115.9904 | Z109: =IF(Z$6<$D109,0,INDEX($T$44:$BO$44,,Z$6-$D109+1)*INDEX($T$52:$BO$52,,$D109)*IF(Z$6=$D109,1,$F109)*Z$46) -> 0 | AA109: =IF(AA$6<$D109,0,INDEX($T$44:$BO$44,,AA$6-$D109+1)*INDEX($T$52:$BO$52,,$D109)*IF(AA$6=$D109,1,$F109)*AA$46) -> 0 | ... BO109: =IF(BO$6<$D109,0,INDEX($T$44:$BO$44,,BO$6-$D109+1)*INDEX($T$52:$BO$52,,$D109)*IF(BO$6=$D109,1,$F109)*BO$46) -> 0.31225528
B110: =INDEX(T$4:BO$4,,D110) -> 46538 | C110: # | D110: =D109+1 -> 7 | F110: =F109 -> 1 | G110: x | H110: sum | I110: =IF(H110=Forecast!$H$195,T110,IF(H110=Forecast!$H$196,BO110,IF(H110=Forecast!$H$197,SUM(T110:BO110),IF(H110=Forecast!$H$198,AVERAGE(T110:BO110),0)))) -> 13704.232 | T110: =IF(T$6<$D110,0,INDEX($T$44:$BO$44,,T$6-$D110+1)*INDEX($T$52:$BO$52,,$D110)*IF(T$6=$D110,1,$F110)*T$46) -> 0 | U110: =IF(U$6<$D110,0,INDEX($T$44:$BO$44,,U$6-$D110+1)*INDEX($T$52:$BO$52,,$D110)*IF(U$6=$D110,1,$F110)*U$46) -> 0 | V110: =IF(V$6<$D110,0,INDEX($T$44:$BO$44,,V$6-$D110+1)*INDEX($T$52:$BO$52,,$D110)*IF(V$6=$D110,1,$F110)*V$46) -> 0 | W110: =IF(W$6<$D110,0,INDEX($T$44:$BO$44,,W$6-$D110+1)*INDEX($T$52:$BO$52,,$D110)*IF(W$6=$D110,1,$F110)*W$46) -> 0 | X110: =IF(X$6<$D110,0,INDEX($T$44:$BO$44,,X$6-$D110+1)*INDEX($T$52:$BO$52,,$D110)*IF(X$6=$D110,1,$F110)*X$46) -> 0 | Y110: =IF(Y$6<$D110,0,INDEX($T$44:$BO$44,,Y$6-$D110+1)*INDEX($T$52:$BO$52,,$D110)*IF(Y$6=$D110,1,$F110)*Y$46) -> 0 | Z110: =IF(Z$6<$D110,0,INDEX($T$44:$BO$44,,Z$6-$D110+1)*INDEX($T$52:$BO$52,,$D110)*IF(Z$6=$D110,1,$F110)*Z$46) -> 6852.5344 | AA110: =IF(AA$6<$D110,0,INDEX($T$44:$BO$44,,AA$6-$D110+1)*INDEX($T$52:$BO$52,,$D110)*IF(AA$6=$D110,1,$F110)*AA$46) -> 0 | ... BO110: =IF(BO$6<$D110,0,INDEX($T$44:$BO$44,,BO$6-$D110+1)*INDEX($T$52:$BO$52,,$D110)*IF(BO$6=$D110,1,$F110)*BO$46) -> 0
B111: =INDEX(T$4:BO$4,,D111) -> 46568 | C111: # | D111: =D110+1 -> 8 | F111: =F110 -> 1 | G111: x | H111: sum | I111: =IF(H111=Forecast!$H$195,T111,IF(H111=Forecast!$H$196,BO111,IF(H111=Forecast!$H$197,SUM(T111:BO111),IF(H111=Forecast!$H$198,AVERAGE(T111:BO111),0)))) -> 17658.169 | T111: =IF(T$6<$D111,0,INDEX($T$44:$BO$44,,T$6-$D111+1)*INDEX($T$52:$BO$52,,$D111)*IF(T$6=$D111,1,$F111)*T$46) -> 0 | U111: =IF(U$6<$D111,0,INDEX($T$44:$BO$44,,U$6-$D111+1)*INDEX($T$52:$BO$52,,$D111)*IF(U$6=$D111,1,$F111)*U$46) -> 0 | V111: =IF(V$6<$D111,0,INDEX($T$44:$BO$44,,V$6-$D111+1)*INDEX($T$52:$BO$52,,$D111)*IF(V$6=$D111,1,$F111)*V$46) -> 0 | W111: =IF(W$6<$D111,0,INDEX($T$44:$BO$44,,W$6-$D111+1)*INDEX($T$52:$BO$52,,$D111)*IF(W$6=$D111,1,$F111)*W$46) -> 0 | X111: =IF(X$6<$D111,0,INDEX($T$44:$BO$44,,X$6-$D111+1)*INDEX($T$52:$BO$52,,$D111)*IF(X$6=$D111,1,$F111)*X$46) -> 0 | Y111: =IF(Y$6<$D111,0,INDEX($T$44:$BO$44,,Y$6-$D111+1)*INDEX($T$52:$BO$52,,$D111)*IF(Y$6=$D111,1,$F111)*Y$46) -> 0 | Z111: =IF(Z$6<$D111,0,INDEX($T$44:$BO$44,,Z$6-$D111+1)*INDEX($T$52:$BO$52,,$D111)*IF(Z$6=$D111,1,$F111)*Z$46) -> 0 | AA111: =IF(AA$6<$D111,0,INDEX($T$44:$BO$44,,AA$6-$D111+1)*INDEX($T$52:$BO$52,,$D111)*IF(AA$6=$D111,1,$F111)*AA$46) -> 8829.6234 | ... BO111: =IF(BO$6<$D111,0,INDEX($T$44:$BO$44,,BO$6-$D111+1)*INDEX($T$52:$BO$52,,$D111)*IF(BO$6=$D111,1,$F111)*BO$46) -> 0
B112: =INDEX(T$4:BO$4,,D112) -> 46599 | C112: # | D112: =D111+1 -> 9 | F112: =F111 -> 1 | G112: x | H112: sum | I112: =IF(H112=Forecast!$H$195,T112,IF(H112=Forecast!$H$196,BO112,IF(H112=Forecast!$H$197,SUM(T112:BO112),IF(H112=Forecast!$H$198,AVERAGE(T112:BO112),0)))) -> 21988.684 | T112: =IF(T$6<$D112,0,INDEX($T$44:$BO$44,,T$6-$D112+1)*INDEX($T$52:$BO$52,,$D112)*IF(T$6=$D112,1,$F112)*T$46) -> 0 | U112: =IF(U$6<$D112,0,INDEX($T$44:$BO$44,,U$6-$D112+1)*INDEX($T$52:$BO$52,,$D112)*IF(U$6=$D112,1,$F112)*U$46) -> 0 | V112: =IF(V$6<$D112,0,INDEX($T$44:$BO$44,,V$6-$D112+1)*INDEX($T$52:$BO$52,,$D112)*IF(V$6=$D112,1,$F112)*V$46) -> 0 | W112: =IF(W$6<$D112,0,INDEX($T$44:$BO$44,,W$6-$D112+1)*INDEX($T$52:$BO$52,,$D112)*IF(W$6=$D112,1,$F112)*W$46) -> 0 | X112: =IF(X$6<$D112,0,INDEX($T$44:$BO$44,,X$6-$D112+1)*INDEX($T$52:$BO$52,,$D112)*IF(X$6=$D112,1,$F112)*X$46) -> 0 | Y112: =IF(Y$6<$D112,0,INDEX($T$44:$BO$44,,Y$6-$D112+1)*INDEX($T$52:$BO$52,,$D112)*IF(Y$6=$D112,1,$F112)*Y$46) -> 0 | Z112: =IF(Z$6<$D112,0,INDEX($T$44:$BO$44,,Z$6-$D112+1)*INDEX($T$52:$BO$52,,$D112)*IF(Z$6=$D112,1,$F112)*Z$46) -> 0 | AA112: =IF(AA$6<$D112,0,INDEX($T$44:$BO$44,,AA$6-$D112+1)*INDEX($T$52:$BO$52,,$D112)*IF(AA$6=$D112,1,$F112)*AA$46) -> 0 | ... BO112: =IF(BO$6<$D112,0,INDEX($T$44:$BO$44,,BO$6-$D112+1)*INDEX($T$52:$BO$52,,$D112)*IF(BO$6=$D112,1,$F112)*BO$46) -> 1.3421647
B113: =INDEX(T$4:BO$4,,D113) -> 46630 | C113: # | D113: =D112+1 -> 10 | F113: =F112 -> 1 | G113: x | H113: sum | I113: =IF(H113=Forecast!$H$195,T113,IF(H113=Forecast!$H$196,BO113,IF(H113=Forecast!$H$197,SUM(T113:BO113),IF(H113=Forecast!$H$198,AVERAGE(T113:BO113),0)))) -> 26570.719 | T113: =IF(T$6<$D113,0,INDEX($T$44:$BO$44,,T$6-$D113+1)*INDEX($T$52:$BO$52,,$D113)*IF(T$6=$D113,1,$F113)*T$46) -> 0 | U113: =IF(U$6<$D113,0,INDEX($T$44:$BO$44,,U$6-$D113+1)*INDEX($T$52:$BO$52,,$D113)*IF(U$6=$D113,1,$F113)*U$46) -> 0 | V113: =IF(V$6<$D113,0,INDEX($T$44:$BO$44,,V$6-$D113+1)*INDEX($T$52:$BO$52,,$D113)*IF(V$6=$D113,1,$F113)*V$46) -> 0 | W113: =IF(W$6<$D113,0,INDEX($T$44:$BO$44,,W$6-$D113+1)*INDEX($T$52:$BO$52,,$D113)*IF(W$6=$D113,1,$F113)*W$46) -> 0 | X113: =IF(X$6<$D113,0,INDEX($T$44:$BO$44,,X$6-$D113+1)*INDEX($T$52:$BO$52,,$D113)*IF(X$6=$D113,1,$F113)*X$46) -> 0 | Y113: =IF(Y$6<$D113,0,INDEX($T$44:$BO$44,,Y$6-$D113+1)*INDEX($T$52:$BO$52,,$D113)*IF(Y$6=$D113,1,$F113)*Y$46) -> 0 | Z113: =IF(Z$6<$D113,0,INDEX($T$44:$BO$44,,Z$6-$D113+1)*INDEX($T$52:$BO$52,,$D113)*IF(Z$6=$D113,1,$F113)*Z$46) -> 0 | AA113: =IF(AA$6<$D113,0,INDEX($T$44:$BO$44,,AA$6-$D113+1)*INDEX($T$52:$BO$52,,$D113)*IF(AA$6=$D113,1,$F113)*AA$46) -> 0 | ... BO113: =IF(BO$6<$D113,0,INDEX($T$44:$BO$44,,BO$6-$D113+1)*INDEX($T$52:$BO$52,,$D113)*IF(BO$6=$D113,1,$F113)*BO$46) -> 0
B114: =INDEX(T$4:BO$4,,D114) -> 46660 | C114: # | D114: =D113+1 -> 11 | F114: =F113 -> 1 | G114: x | H114: sum | I114: =IF(H114=Forecast!$H$195,T114,IF(H114=Forecast!$H$196,BO114,IF(H114=Forecast!$H$197,SUM(T114:BO114),IF(H114=Forecast!$H$198,AVERAGE(T114:BO114),0)))) -> 31278.704 | T114: =IF(T$6<$D114,0,INDEX($T$44:$BO$44,,T$6-$D114+1)*INDEX($T$52:$BO$52,,$D114)*IF(T$6=$D114,1,$F114)*T$46) -> 0 | U114: =IF(U$6<$D114,0,INDEX($T$44:$BO$44,,U$6-$D114+1)*INDEX($T$52:$BO$52,,$D114)*IF(U$6=$D114,1,$F114)*U$46) -> 0 | V114: =IF(V$6<$D114,0,INDEX($T$44:$BO$44,,V$6-$D114+1)*INDEX($T$52:$BO$52,,$D114)*IF(V$6=$D114,1,$F114)*V$46) -> 0 | W114: =IF(W$6<$D114,0,INDEX($T$44:$BO$44,,W$6-$D114+1)*INDEX($T$52:$BO$52,,$D114)*IF(W$6=$D114,1,$F114)*W$46) -> 0 | X114: =IF(X$6<$D114,0,INDEX($T$44:$BO$44,,X$6-$D114+1)*INDEX($T$52:$BO$52,,$D114)*IF(X$6=$D114,1,$F114)*X$46) -> 0 | Y114: =IF(Y$6<$D114,0,INDEX($T$44:$BO$44,,Y$6-$D114+1)*INDEX($T$52:$BO$52,,$D114)*IF(Y$6=$D114,1,$F114)*Y$46) -> 0 | Z114: =IF(Z$6<$D114,0,INDEX($T$44:$BO$44,,Z$6-$D114+1)*INDEX($T$52:$BO$52,,$D114)*IF(Z$6=$D114,1,$F114)*Z$46) -> 0 | AA114: =IF(AA$6<$D114,0,INDEX($T$44:$BO$44,,AA$6-$D114+1)*INDEX($T$52:$BO$52,,$D114)*IF(AA$6=$D114,1,$F114)*AA$46) -> 0 | ... BO114: =IF(BO$6<$D114,0,INDEX($T$44:$BO$44,,BO$6-$D114+1)*INDEX($T$52:$BO$52,,$D114)*IF(BO$6=$D114,1,$F114)*BO$46) -> 0
B115: =INDEX(T$4:BO$4,,D115) -> 46691 | C115: # | D115: =D114+1 -> 12 | F115: =F114 -> 1 | G115: x | H115: sum | I115: =IF(H115=Forecast!$H$195,T115,IF(H115=Forecast!$H$196,BO115,IF(H115=Forecast!$H$197,SUM(T115:BO115),IF(H115=Forecast!$H$198,AVERAGE(T115:BO115),0)))) -> 35989.556 | T115: =IF(T$6<$D115,0,INDEX($T$44:$BO$44,,T$6-$D115+1)*INDEX($T$52:$BO$52,,$D115)*IF(T$6=$D115,1,$F115)*T$46) -> 0 | U115: =IF(U$6<$D115,0,INDEX($T$44:$BO$44,,U$6-$D115+1)*INDEX($T$52:$BO$52,,$D115)*IF(U$6=$D115,1,$F115)*U$46) -> 0 | V115: =IF(V$6<$D115,0,INDEX($T$44:$BO$44,,V$6-$D115+1)*INDEX($T$52:$BO$52,,$D115)*IF(V$6=$D115,1,$F115)*V$46) -> 0 | W115: =IF(W$6<$D115,0,INDEX($T$44:$BO$44,,W$6-$D115+1)*INDEX($T$52:$BO$52,,$D115)*IF(W$6=$D115,1,$F115)*W$46) -> 0 | X115: =IF(X$6<$D115,0,INDEX($T$44:$BO$44,,X$6-$D115+1)*INDEX($T$52:$BO$52,,$D115)*IF(X$6=$D115,1,$F115)*X$46) -> 0 | Y115: =IF(Y$6<$D115,0,INDEX($T$44:$BO$44,,Y$6-$D115+1)*INDEX($T$52:$BO$52,,$D115)*IF(Y$6=$D115,1,$F115)*Y$46) -> 0 | Z115: =IF(Z$6<$D115,0,INDEX($T$44:$BO$44,,Z$6-$D115+1)*INDEX($T$52:$BO$52,,$D115)*IF(Z$6=$D115,1,$F115)*Z$46) -> 0 | AA115: =IF(AA$6<$D115,0,INDEX($T$44:$BO$44,,AA$6-$D115+1)*INDEX($T$52:$BO$52,,$D115)*IF(AA$6=$D115,1,$F115)*AA$46) -> 0 | ... BO115: =IF(BO$6<$D115,0,INDEX($T$44:$BO$44,,BO$6-$D115+1)*INDEX($T$52:$BO$52,,$D115)*IF(BO$6=$D115,1,$F115)*BO$46) -> 4.3937927
B116: =INDEX(T$4:BO$4,,D116) -> 46721 | C116: # | D116: =D115+1 -> 13 | F116: =F115 -> 1 | G116: x | H116: sum | I116: =IF(H116=Forecast!$H$195,T116,IF(H116=Forecast!$H$196,BO116,IF(H116=Forecast!$H$197,SUM(T116:BO116),IF(H116=Forecast!$H$198,AVERAGE(T116:BO116),0)))) -> 40591.896 | T116: =IF(T$6<$D116,0,INDEX($T$44:$BO$44,,T$6-$D116+1)*INDEX($T$52:$BO$52,,$D116)*IF(T$6=$D116,1,$F116)*T$46) -> 0 | U116: =IF(U$6<$D116,0,INDEX($T$44:$BO$44,,U$6-$D116+1)*INDEX($T$52:$BO$52,,$D116)*IF(U$6=$D116,1,$F116)*U$46) -> 0 | V116: =IF(V$6<$D116,0,INDEX($T$44:$BO$44,,V$6-$D116+1)*INDEX($T$52:$BO$52,,$D116)*IF(V$6=$D116,1,$F116)*V$46) -> 0 | W116: =IF(W$6<$D116,0,INDEX($T$44:$BO$44,,W$6-$D116+1)*INDEX($T$52:$BO$52,,$D116)*IF(W$6=$D116,1,$F116)*W$46) -> 0 | X116: =IF(X$6<$D116,0,INDEX($T$44:$BO$44,,X$6-$D116+1)*INDEX($T$52:$BO$52,,$D116)*IF(X$6=$D116,1,$F116)*X$46) -> 0 | Y116: =IF(Y$6<$D116,0,INDEX($T$44:$BO$44,,Y$6-$D116+1)*INDEX($T$52:$BO$52,,$D116)*IF(Y$6=$D116,1,$F116)*Y$46) -> 0 | Z116: =IF(Z$6<$D116,0,INDEX($T$44:$BO$44,,Z$6-$D116+1)*INDEX($T$52:$BO$52,,$D116)*IF(Z$6=$D116,1,$F116)*Z$46) -> 0 | AA116: =IF(AA$6<$D116,0,INDEX($T$44:$BO$44,,AA$6-$D116+1)*INDEX($T$52:$BO$52,,$D116)*IF(AA$6=$D116,1,$F116)*AA$46) -> 0 | ... BO116: =IF(BO$6<$D116,0,INDEX($T$44:$BO$44,,BO$6-$D116+1)*INDEX($T$52:$BO$52,,$D116)*IF(BO$6=$D116,1,$F116)*BO$46) -> 0
... B151: =INDEX(T$4:BO$4,,D151) -> 47787 | C151: # | D151: =D150+1 -> 48 | F151: =F150 -> 1 | G151: x | H151: sum | I151: =IF(H151=Forecast!$H$195,T151,IF(H151=Forecast!$H$196,BO151,IF(H151=Forecast!$H$197,SUM(T151:BO151),IF(H151=Forecast!$H$198,AVERAGE(T151:BO151),0)))) -> 40991.004 | T151: =IF(T$6<$D151,0,INDEX($T$44:$BO$44,,T$6-$D151+1)*INDEX($T$52:$BO$52,,$D151)*IF(T$6=$D151,1,$F151)*T$46) -> 0 | U151: =IF(U$6<$D151,0,INDEX($T$44:$BO$44,,U$6-$D151+1)*INDEX($T$52:$BO$52,,$D151)*IF(U$6=$D151,1,$F151)*U$46) -> 0 | V151: =IF(V$6<$D151,0,INDEX($T$44:$BO$44,,V$6-$D151+1)*INDEX($T$52:$BO$52,,$D151)*IF(V$6=$D151,1,$F151)*V$46) -> 0 | W151: =IF(W$6<$D151,0,INDEX($T$44:$BO$44,,W$6-$D151+1)*INDEX($T$52:$BO$52,,$D151)*IF(W$6=$D151,1,$F151)*W$46) -> 0 | X151: =IF(X$6<$D151,0,INDEX($T$44:$BO$44,,X$6-$D151+1)*INDEX($T$52:$BO$52,,$D151)*IF(X$6=$D151,1,$F151)*X$46) -> 0 | Y151: =IF(Y$6<$D151,0,INDEX($T$44:$BO$44,,Y$6-$D151+1)*INDEX($T$52:$BO$52,,$D151)*IF(Y$6=$D151,1,$F151)*Y$46) -> 0 | Z151: =IF(Z$6<$D151,0,INDEX($T$44:$BO$44,,Z$6-$D151+1)*INDEX($T$52:$BO$52,,$D151)*IF(Z$6=$D151,1,$F151)*Z$46) -> 0 | AA151: =IF(AA$6<$D151,0,INDEX($T$44:$BO$44,,AA$6-$D151+1)*INDEX($T$52:$BO$52,,$D151)*IF(AA$6=$D151,1,$F151)*AA$46) -> 0 | ... BO151: =IF(BO$6<$D151,0,INDEX($T$44:$BO$44,,BO$6-$D151+1)*INDEX($T$52:$BO$52,,$D151)*IF(BO$6=$D151,1,$F151)*BO$46) -> 40991.004
B152: Orders, from New Customers | C152: # | D152: this uses the total orders forecast and backs out the new customers using the % of returning customers assumption | H152: sum | I152: =IF(H152=Forecast!$H$195,T152,IF(H152=Forecast!$H$196,BO152,IF(H152=Forecast!$H$197,SUM(T152:BO152),IF(H152=Forecast!$H$198,AVERAGE(T152:BO152),0)))) -> 1404054.1 | T152: =T52 -> 550 | U152: =U52 -> 970.75 | V152: =V52 -> 1601.9802 | W152: =W52 -> 2487.4147 | X152: =X52 -> 3656.0161 | Y152: =Y52 -> 5115.9904 | Z152: =Z52 -> 6852.5344 | AA152: =AA52 -> 8829.6234 | ... BO152: =BO52 -> 40991.004
B153: Orders, from Repeat Customers | C153: # | D153: orders from repeat customers is calculated from the forecast of orders less the orders from new customers. This separates out repeat and new customers so that the acquisition costs can be modeled separately. | H153: sum | I153: =IF(H153=Forecast!$H$195,T153,IF(H153=Forecast!$H$196,BO153,IF(H153=Forecast!$H$197,SUM(T153:BO153),IF(H153=Forecast!$H$198,AVERAGE(T153:BO153),0)))) -> 1174617.9 | T153: =T54-T152 -> 6960.724 | U153: =U54-U152 -> 1660.9412 | V153: =V54-V152 -> 1749.4997 | W153: =W54-W152 -> 1063.9471 | X153: =X54-X152 -> 1315.8456 | Y153: =Y54-Y152 -> 1675.7399 | Z153: =Z54-Z152 -> 1775.6809 | AA153: =AA54-AA152 -> 2485.9308 | ... BO153: =BO54-BO152 -> 40692.294
B154: Cumulative Orders from New Customers | C154: # | D154: orders from new customers this period + cumulative new customers previous period | H154: sum | I154: =IF(H154=Forecast!$H$195,T154,IF(H154=Forecast!$H$196,BO154,IF(H154=Forecast!$H$197,SUM(T154:BO154),IF(H154=Forecast!$H$198,AVERAGE(T154:BO154),0)))) -> 26001956 | T154: =S154+T152 -> 550 | U154: =T154+U152 -> 1520.75 | V154: =U154+V152 -> 3122.7302 | W154: =V154+W152 -> 5610.1448 | X154: =W154+X152 -> 9266.1609 | Y154: =X154+Y152 -> 14382.151 | Z154: =Y154+Z152 -> 21234.686 | AA154: =Z154+AA152 -> 30064.309 | ... BO154: =BN154+BO152 -> 1404054.1
B155: Cumulative Orders from Repeat Customers | C155: # | D155: orders from repeat customers this period + cumulative repeat customers previous period | H155: sum | I155: =IF(H155=Forecast!$H$195,T155,IF(H155=Forecast!$H$196,BO155,IF(H155=Forecast!$H$197,SUM(T155:BO155),IF(H155=Forecast!$H$198,AVERAGE(T155:BO155),0)))) -> 19253673 | T155: =S155+T153 -> 6960.724 | U155: =T155+U153 -> 8621.6651 | V155: =U155+V153 -> 10371.165 | W155: =V155+W153 -> 11435.112 | X155: =W155+X153 -> 12750.957 | Y155: =X155+Y153 -> 14426.697 | Z155: =Y155+Z153 -> 16202.378 | AA155: =Z155+AA153 -> 18688.309 | ... BO155: =BN155+BO153 -> 1174617.9
B156: % of Orders from New Customers | C156: % | D156: calculated based on the churn and repeat cycles | H156: average | I156: =IF(H156=Forecast!$H$195,T156,IF(H156=Forecast!$H$196,BO156,IF(H156=Forecast!$H$197,SUM(T156:BO156),IF(H156=Forecast!$H$198,AVERAGE(T156:BO156),0)))) -> 0.57144395 | T156: =IFERROR(T152/T54,0) -> 0.073228627 | U156: =IFERROR(U152/U54,0) -> 0.36886927 | V156: =IFERROR(V152/V54,0) -> 0.47799188 | W156: =IFERROR(W152/W54,0) -> 0.70041152 | X156: =IFERROR(X152/X54,0) -> 0.73534147 | Y156: =IFERROR(Y152/Y54,0) -> 0.7532676 | Z156: =IFERROR(Z152/Z54,0) -> 0.79420068 | AA156: =IFERROR(AA152/AA54,0) -> 0.78030852 | ... BO156: =IFERROR(BO152/BO54,0) -> 0.50182846
B158: Revenues and Costs per Order
B159: ='Get Started'!B17 -> Average Revenue per Order, new Customer | C159: ='Get Started'!D$7 -> £ | D159: per period | H159: average | I159: =IF(H159=Forecast!$H$195,T159,IF(H159=Forecast!$H$196,BO159,IF(H159=Forecast!$H$197,SUM(T159:BO159),IF(H159=Forecast!$H$198,AVERAGE(T159:BO159),0)))) -> 300.94238 | T159: =IF(EOMONTH(T33,0)=T4,T16,S159*(1+T161)) -> 87 | U159: =IF(EOMONTH(U33,0)=U4,U16,T159*(1+U161)) -> 95.265 | V159: =IF(EOMONTH(V33,0)=V4,V16,U159*(1+V161)) -> 103.86267 | W159: =IF(EOMONTH(W33,0)=W4,W16,V159*(1+W161)) -> 112.76759 | X159: =IF(EOMONTH(X33,0)=X4,X16,W159*(1+X161)) -> 121.95258 | Y159: =IF(EOMONTH(Y33,0)=Y4,Y16,X159*(1+Y161)) -> 131.38904 | Z159: =IF(EOMONTH(Z33,0)=Z4,Z16,Y159*(1+Z161)) -> 141.04734 | AA159: =IF(EOMONTH(AA33,0)=AA4,AA16,Z159*(1+AA161)) -> 150.8972 | ... BO159: =IF(EOMONTH(BO33,0)=BO4,BO16,BN159*(1+BO161)) -> 469.3659
B160: ='Get Started'!B18 -> Average Revenue per Order, repeat Customer | C160: ='Get Started'!D$7 -> £ | D160: per period | H160: average | I160: =IF(H160=Forecast!$H$195,T160,IF(H160=Forecast!$H$196,BO160,IF(H160=Forecast!$H$197,SUM(T160:BO160),IF(H160=Forecast!$H$198,AVERAGE(T160:BO160),0)))) -> 300.94238 | T160: =IF(EOMONTH(T$33,0)=T$4,T17,S160*(1+T161)) -> 87 | U160: =IF(EOMONTH(U$33,0)=U$4,U17,T160*(1+U161)) -> 95.265 | V160: =IF(EOMONTH(V$33,0)=V$4,V17,U160*(1+V161)) -> 103.86267 | W160: =IF(EOMONTH(W$33,0)=W$4,W17,V160*(1+W161)) -> 112.76759 | X160: =IF(EOMONTH(X$33,0)=X$4,X17,W160*(1+X161)) -> 121.95258 | Y160: =IF(EOMONTH(Y$33,0)=Y$4,Y17,X160*(1+Y161)) -> 131.38904 | Z160: =IF(EOMONTH(Z$33,0)=Z$4,Z17,Y160*(1+Z161)) -> 141.04734 | AA160: =IF(EOMONTH(AA$33,0)=AA$4,AA17,Z160*(1+AA161)) -> 150.8972 | ... BO160: =IF(EOMONTH(BO$33,0)=BO$4,BO17,BN160*(1+BO161)) -> 469.3659
B161: ="Rate of Change in Average Revenue per Order" -> Rate of Change in Average Revenue per Order | C161: % | D161: rate of change per period | H161: average | I161: =IF(H161=Forecast!$H$195,T161,IF(H161=Forecast!$H$196,BO161,IF(H161=Forecast!$H$197,SUM(T161:BO161),IF(H161=Forecast!$H$198,AVERAGE(T161:BO161),0)))) -> 0.038114267 | T161: =IF(EOMONTH(T33,0)=T4,T18,S161*(1+T19)) -> 0.1 | U161: =IF(EOMONTH(U33,0)=U4,U18,T161*(1+U19)) -> 0.095 | V161: =IF(EOMONTH(V33,0)=V4,V18,U161*(1+V19)) -> 0.09025 | W161: =IF(EOMONTH(W33,0)=W4,W18,V161*(1+W19)) -> 0.0857375 | X161: =IF(EOMONTH(X33,0)=X4,X18,W161*(1+X19)) -> 0.081450625 | Y161: =IF(EOMONTH(Y33,0)=Y4,Y18,X161*(1+Y19)) -> 0.077378094 | Z161: =IF(EOMONTH(Z33,0)=Z4,Z18,Y161*(1+Z19)) -> 0.073509189 | AA161: =IF(EOMONTH(AA33,0)=AA4,AA18,Z161*(1+AA19)) -> 0.06983373 | ... BO161: =IF(EOMONTH(BO33,0)=BO4,BO18,BN161*(1+BO19)) -> 0.0089744832
B162: =B20 -> Cost of Sales | C162: % | D162: per period | H162: average | I162: =IF(H162=Forecast!$H$195,T162,IF(H162=Forecast!$H$196,BO162,IF(H162=Forecast!$H$197,SUM(T162:BO162),IF(H162=Forecast!$H$198,AVERAGE(T162:BO162),0)))) -> 0.25 | T162: =IF(EOMONTH(T$33,0)=T$4,T20,S162*(1+T165)) -> 0.25 | U162: =IF(EOMONTH(U$33,0)=U$4,U20,T162*(1+U165)) -> 0.25 | V162: =IF(EOMONTH(V$33,0)=V$4,V20,U162*(1+V165)) -> 0.25 | W162: =IF(EOMONTH(W$33,0)=W$4,W20,V162*(1+W165)) -> 0.25 | X162: =IF(EOMONTH(X$33,0)=X$4,X20,W162*(1+X165)) -> 0.25 | Y162: =IF(EOMONTH(Y$33,0)=Y$4,Y20,X162*(1+Y165)) -> 0.25 | Z162: =IF(EOMONTH(Z$33,0)=Z$4,Z20,Y162*(1+Z165)) -> 0.25 | AA162: =IF(EOMONTH(AA$33,0)=AA$4,AA20,Z162*(1+AA165)) -> 0.25 | ... BO162: =IF(EOMONTH(BO$33,0)=BO$4,BO20,BN162*(1+BO165)) -> 0.25
B163: =B21 -> Additional Cost of Sales | C163: % | D163: per period | H163: average | I163: =IF(H163=Forecast!$H$195,T163,IF(H163=Forecast!$H$196,BO163,IF(H163=Forecast!$H$197,SUM(T163:BO163),IF(H163=Forecast!$H$198,AVERAGE(T163:BO163),0)))) -> 0.1 | T163: =IF(EOMONTH(T$33,0)=T$4,T21,S163*(1+T165)) -> 0.1 | U163: =IF(EOMONTH(U$33,0)=U$4,U21,T163*(1+U165)) -> 0.1 | V163: =IF(EOMONTH(V$33,0)=V$4,V21,U163*(1+V165)) -> 0.1 | W163: =IF(EOMONTH(W$33,0)=W$4,W21,V163*(1+W165)) -> 0.1 | X163: =IF(EOMONTH(X$33,0)=X$4,X21,W163*(1+X165)) -> 0.1 | Y163: =IF(EOMONTH(Y$33,0)=Y$4,Y21,X163*(1+Y165)) -> 0.1 | Z163: =IF(EOMONTH(Z$33,0)=Z$4,Z21,Y163*(1+Z165)) -> 0.1 | AA163: =IF(EOMONTH(AA$33,0)=AA$4,AA21,Z163*(1+AA165)) -> 0.1 | ... BO163: =IF(EOMONTH(BO$33,0)=BO$4,BO21,BN163*(1+BO165)) -> 0.1
B164: =B22 -> Additional Cost of Sales | C164: % | D164: per period | H164: average | I164: =IF(H164=Forecast!$H$195,T164,IF(H164=Forecast!$H$196,BO164,IF(H164=Forecast!$H$197,SUM(T164:BO164),IF(H164=Forecast!$H$198,AVERAGE(T164:BO164),0)))) -> 0 | T164: =IF(EOMONTH(T$33,0)=T$4,T22,S164*(1+T165)) -> 0 | U164: =IF(EOMONTH(U$33,0)=U$4,U22,T164*(1+U165)) -> 0 | V164: =IF(EOMONTH(V$33,0)=V$4,V22,U164*(1+V165)) -> 0 | W164: =IF(EOMONTH(W$33,0)=W$4,W22,V164*(1+W165)) -> 0 | X164: =IF(EOMONTH(X$33,0)=X$4,X22,W164*(1+X165)) -> 0 | Y164: =IF(EOMONTH(Y$33,0)=Y$4,Y22,X164*(1+Y165)) -> 0 | Z164: =IF(EOMONTH(Z$33,0)=Z$4,Z22,Y164*(1+Z165)) -> 0 | AA164: =IF(EOMONTH(AA$33,0)=AA$4,AA22,Z164*(1+AA165)) -> 0 | ... BO164: =IF(EOMONTH(BO$33,0)=BO$4,BO22,BN164*(1+BO165)) -> 0
B165: Rate of Change, Cost of Sales | C165: % | D165: rate of change per period | H165: average | I165: =IF(H165=Forecast!$H$195,T165,IF(H165=Forecast!$H$196,BO165,IF(H165=Forecast!$H$197,SUM(T165:BO165),IF(H165=Forecast!$H$198,AVERAGE(T165:BO165),0)))) -> 0 | T165: =IF(EOMONTH(T33,0)=T4,T23,S165*(1+T24)) -> 0 | U165: =IF(EOMONTH(U33,0)=U4,U23,T165*(1+U24)) -> 0 | V165: =IF(EOMONTH(V33,0)=V4,V23,U165*(1+V24)) -> 0 | W165: =IF(EOMONTH(W33,0)=W4,W23,V165*(1+W24)) -> 0 | X165: =IF(EOMONTH(X33,0)=X4,X23,W165*(1+X24)) -> 0 | Y165: =IF(EOMONTH(Y33,0)=Y4,Y23,X165*(1+Y24)) -> 0 | Z165: =IF(EOMONTH(Z33,0)=Z4,Z23,Y165*(1+Z24)) -> 0 | AA165: =IF(EOMONTH(AA33,0)=AA4,AA23,Z165*(1+AA24)) -> 0 | ... BO165: =IF(EOMONTH(BO33,0)=BO4,BO23,BN165*(1+BO24)) -> 0
B166: =B27 -> Customer Acquisition Cost (CAC), new customer | C166: ='Get Started'!D$7 -> £ | D166: per period | H166: average | I166: =IF(H166=Forecast!$H$195,T166,IF(H166=Forecast!$H$196,BO166,IF(H166=Forecast!$H$197,SUM(T166:BO166),IF(H166=Forecast!$H$198,AVERAGE(T166:BO166),0)))) -> 30 | T166: =IF(EOMONTH(T$33,0)=T$4,T27,S166*(1+T168)) -> 30 | U166: =IF(EOMONTH(U$33,0)=U$4,U27,T166*(1+U168)) -> 30 | V166: =IF(EOMONTH(V$33,0)=V$4,V27,U166*(1+V168)) -> 30 | W166: =IF(EOMONTH(W$33,0)=W$4,W27,V166*(1+W168)) -> 30 | X166: =IF(EOMONTH(X$33,0)=X$4,X27,W166*(1+X168)) -> 30 | Y166: =IF(EOMONTH(Y$33,0)=Y$4,Y27,X166*(1+Y168)) -> 30 | Z166: =IF(EOMONTH(Z$33,0)=Z$4,Z27,Y166*(1+Z168)) -> 30 | AA166: =IF(EOMONTH(AA$33,0)=AA$4,AA27,Z166*(1+AA168)) -> 30 | ... BO166: =IF(EOMONTH(BO$33,0)=BO$4,BO27,BN166*(1+BO168)) -> 30
B167: =B28 -> Customer Acquisition Cost (CAC), repeat customer | C167: ='Get Started'!D$7 -> £ | D167: per period | H167: average | I167: =IF(H167=Forecast!$H$195,T167,IF(H167=Forecast!$H$196,BO167,IF(H167=Forecast!$H$197,SUM(T167:BO167),IF(H167=Forecast!$H$198,AVERAGE(T167:BO167),0)))) -> 10 | T167: =IF(EOMONTH(T$33,0)=T$4,T28,S167*(1+T168)) -> 10 | U167: =IF(EOMONTH(U$33,0)=U$4,U28,T167*(1+U168)) -> 10 | V167: =IF(EOMONTH(V$33,0)=V$4,V28,U167*(1+V168)) -> 10 | W167: =IF(EOMONTH(W$33,0)=W$4,W28,V167*(1+W168)) -> 10 | X167: =IF(EOMONTH(X$33,0)=X$4,X28,W167*(1+X168)) -> 10 | Y167: =IF(EOMONTH(Y$33,0)=Y$4,Y28,X167*(1+Y168)) -> 10 | Z167: =IF(EOMONTH(Z$33,0)=Z$4,Z28,Y167*(1+Z168)) -> 10 | AA167: =IF(EOMONTH(AA$33,0)=AA$4,AA28,Z167*(1+AA168)) -> 10 | ... BO167: =IF(EOMONTH(BO$33,0)=BO$4,BO28,BN167*(1+BO168)) -> 10
B168: Rate of Change, CAC | C168: % | D168: rate of change per period | H168: average | I168: =IF(H168=Forecast!$H$195,T168,IF(H168=Forecast!$H$196,BO168,IF(H168=Forecast!$H$197,SUM(T168:BO168),IF(H168=Forecast!$H$198,AVERAGE(T168:BO168),0)))) -> 0 | T168: =IF(EOMONTH(T33,0)=T4,T29,S168*(1+T30)) -> 0 | U168: =IF(EOMONTH(U33,0)=U4,U29,T168*(1+U30)) -> 0 | V168: =IF(EOMONTH(V33,0)=V4,V29,U168*(1+V30)) -> 0 | W168: =IF(EOMONTH(W33,0)=W4,W29,V168*(1+W30)) -> 0 | X168: =IF(EOMONTH(X33,0)=X4,X29,W168*(1+X30)) -> 0 | Y168: =IF(EOMONTH(Y33,0)=Y4,Y29,X168*(1+Y30)) -> 0 | Z168: =IF(EOMONTH(Z33,0)=Z4,Z29,Y168*(1+Z30)) -> 0 | AA168: =IF(EOMONTH(AA33,0)=AA4,AA29,Z168*(1+AA30)) -> 0 | ... BO168: =IF(EOMONTH(BO33,0)=BO4,BO29,BN168*(1+BO30)) -> 0
B170: Revenues, Billings, Expenses
B171: Revenues | C171: ='Get Started'!D$7 -> £ | D171: average revenue per order * orders | H171: sum | I171: =IF(H171="initial",T171,IF(H171="final",BO171,IF(H171="sum",SUM(T171:BO171)))) -> 9.3403825e+08 | S171: =B171 -> Revenues | T171: =T152*T159+T160*T153 -> 653432.98 | U171: =U152*U159+U160*U153 -> 250708.06 | V171: =V152*V159+V160*V153 -> 348093.64 | W171: =W152*W159+W160*W153 -> 400478.51 | X171: =X152*X159+X160*X153 -> 606331.37 | Y171: =Y152*Y159+Y160*Y153 -> 892358.94 | Z171: =Z152*Z159+Z160*Z153 -> 1216986.8 | AA171: =AA152*AA159+AA160*AA153 -> 1707485.5 | ... BO171: =BO152*BO159+BO160*BO153 -> 38339355
B172: Shipping Revenues | C172: ='Get Started'!D$7 -> £ | D172: orders * shipping revenue per order | H172: sum | I172: =IF(H172="initial",T172,IF(H172="final",BO172,IF(H172="sum",SUM(T172:BO172)))) -> 0 | S172: =B172 -> Shipping Revenues | T172: =T54*T25 -> 0 | U172: =U54*U25 -> 0 | V172: =V54*V25 -> 0 | W172: =W54*W25 -> 0 | X172: =X54*X25 -> 0 | Y172: =Y54*Y25 -> 0 | Z172: =Z54*Z25 -> 0 | AA172: =AA54*AA25 -> 0 | ... BO172: =BO54*BO25 -> 0
B173: Total Revenues | C173: ='Get Started'!D$7 -> £ | D173: product revenues + shipping revenues | H173: sum | I173: =IF(H173="initial",T173,IF(H173="final",BO173,IF(H173="sum",SUM(T173:BO173)))) -> 9.3403825e+08 | S173: =B173 -> Total Revenues | T173: =T171+T172 -> 653432.98 | U173: =U171+U172 -> 250708.06 | V173: =V171+V172 -> 348093.64 | W173: =W171+W172 -> 400478.51 | X173: =X171+X172 -> 606331.37 | Y173: =Y171+Y172 -> 892358.94 | Z173: =Z171+Z172 -> 1216986.8 | AA173: =AA171+AA172 -> 1707485.5 | ... BO173: =BO171+BO172 -> 38339355
B174: Cost of Sales | C174: ='Get Started'!D$7 -> £ | D174: average cost of sales per order * orders | H174: sum | I174: =IF(H174="initial",T174,IF(H174="final",BO174,IF(H174="sum",SUM(T174:BO174)))) -> 2.3350956e+08 | S174: =B174 -> Cost of Sales | T174: =T171*T162 -> 163358.25 | U174: =U171*U162 -> 62677.015 | V174: =V171*V162 -> 87023.409 | W174: =W171*W162 -> 100119.63 | X174: =X171*X162 -> 151582.84 | Y174: =Y171*Y162 -> 223089.73 | Z174: =Z171*Z162 -> 304246.71 | AA174: =AA171*AA162 -> 426871.38 | ... BO174: =BO171*BO162 -> 9584838.7
B175: ='Get Started'!B23 -> Additional Cost of Sales | C175: ='Get Started'!D$7 -> £ | D175: ="orders * average cost, as % of revenue" -> orders * average cost, as % of revenue | H175: sum | I175: =IF(H175="initial",T175,IF(H175="final",BO175,IF(H175="sum",SUM(T175:BO175)))) -> 93403825 | S175: =B175 -> Additional Cost of Sales | T175: =T171*T163 -> 65343.298 | U175: =U171*U163 -> 25070.806 | V175: =V171*V163 -> 34809.364 | W175: =W171*W163 -> 40047.851 | X175: =X171*X163 -> 60633.137 | Y175: =Y171*Y163 -> 89235.894 | Z175: =Z171*Z163 -> 121698.68 | AA175: =AA171*AA163 -> 170748.55 | ... BO175: =BO171*BO163 -> 3833935.5
B176: ='Get Started'!B24 -> Additional Cost of Sales | C176: ='Get Started'!D$7 -> £ | D176: ="orders * average cost, as % of revenue" -> orders * average cost, as % of revenue | H176: sum | I176: =IF(H176="initial",T176,IF(H176="final",BO176,IF(H176="sum",SUM(T176:BO176)))) -> 0 | S176: =B176 -> Additional Cost of Sales | T176: =T171*T164 -> 0 | U176: =U171*U164 -> 0 | V176: =V171*V164 -> 0 | W176: =W171*W164 -> 0 | X176: =X171*X164 -> 0 | Y176: =Y171*Y164 -> 0 | Z176: =Z171*Z164 -> 0 | AA176: =AA171*AA164 -> 0 | ... BO176: =BO171*BO164 -> 0
B177: Shipping Cost of Sales | C177: ='Get Started'!D$7 -> £ | D177: orders * shipping costs per order | H177: sum | I177: =IF(H177="initial",T177,IF(H177="final",BO177,IF(H177="sum",SUM(T177:BO177)))) -> 0 | S177: =B177 -> Shipping Cost of Sales | T177: =T54*T26 -> 0 | U177: =U54*U26 -> 0 | V177: =V54*V26 -> 0 | W177: =W54*W26 -> 0 | X177: =X54*X26 -> 0 | Y177: =Y54*Y26 -> 0 | Z177: =Z54*Z26 -> 0 | AA177: =AA54*AA26 -> 0 | ... BO177: =BO54*BO26 -> 0
...

Sheet Unit Economics
B2: Unit Economics
B3: Mauli transaction illustration; linked Foresight assumptions are not validated client economics.
B5: Per unit economics | D5: Amount | E5: Type, Notes
B7: Optional: Hide or show the column notes | D7: hide
B9: Revenues
B10: Recurring revenue (unused) | C10: ='Get Started'!D7 -> £ | D10: 0 | E10: Recurring
B11: One-time fee (unused) | C11: =C$10 -> £ | D11: 0 | E11: One time
B12: Order revenue incl. shipping | C12: =C$10 -> £ | D12: ='Get Started'!D17+'Get Started'!D28 -> 87 | E12: Transaction
B14: Cost of Sales
B15: Recurring costs (unused) | C15: % | D15: 0 | E15: Recurring
B16: One-time costs (unused) | C16: % | D16: 0 | E16: One time
B17: Order costs incl. shipping | C17: % | D17: =IF(D12=0,0,('Get Started'!D17*SUM('Get Started'!D22:D24)+'Get Started'!D29)/D12) -> 0.35 | E17: Transaction
B19: Optional: Discounts | E19: =IF(D7="hide","","optional, used in case you offer discounts for first subscription or first purchase")
B20: Discounts for recurring | C20: =C$10 -> £ | D20: 0 | E20: =IF(D7="hide","","total, over billing period")
B21: Discounts for transaction | C21: =C$10 -> £ | D21: 0 | E21: =IF(D7="hide","","total, first transaction only")
B23: Churn and Growth, Recurring
B24: Recurring - Period for billing, # of months | C24: # | D24: 3 | E24: =IF(D7="hide","","defines the billing cycle, so that cash collection can be separate from revenues. By default this equals the period for churn, but you can overwrite and change it")
B25: Recurring - Period for churn, growth, # months | C25: # | D25: 12 | E25: =IF(D7="hide","","define the length of a cycle for churn. Annual = 12, monthly = 1")
B26: ="% Growth in Gross Margin per unit, linear annual growth" -> % Growth in Gross Margin per unit, linear annual growth | C26: % | D26: 0 | E26: =IF(D7="hide","","annual rate, linear growth")
B27: ="% Churn, every "&MAX(1,D$25)&" month"&IF(D$25>1,"s","") -> % Churn, every 12 months | C27: % | D27: 0.1 | E27: =IF(D7="hide","","% that do not renew")
B28: Average Customer Lifetime | C28: # | D28: =IFERROR(1/(D27/MAX(1,D25)),0) -> 120 | E28: =IF(D7="hide","","# months")
B30: Timing, One time
B31: Months after acquisition when one-time occurs | C31: # | D31: 0 | E31: =IF(D7="hide","","month"&IF(D31>1,"s","")&"; this will be zero for upfront, one-time fees, perhaps assume 12 for one-time fees that happen after 1 year")
B33: Churn and Growth, Transaction
B34: Transaction - Period for churn, growth, # months | C34: # | D34: ='Get Started'!D44 -> 3 | E34: =IF(D7="hide","","month"&IF(D34>1,"s",""))
B35: ="% Growth in Gross Margin per unit, linear annual growth" -> % Growth in Gross Margin per unit, linear annual growth | C35: % | D35: 0 | E35: =IF(D7="hide","","annual rate, linear growth")
B36: ="% Churn, every period" -> % Churn, every period | C36: % | D36: ='Get Started'!D43 -> 0.5 | E36: =IF(D7="hide","","% that do not repeat")
B37: Average # Repeat Transactions per year | C37: # | D37: =IFERROR(12/D34,0) -> 4 | E37: =IF(D7="hide","","average lifetime one time purchases, before churn")
B38: Average # of Lifetime Transactions | C38: # | D38: =IFERROR(1/(D36/MAX(1,D34))/MAX(1,D34),0) -> 2 | E38: =IF(D7="hide","","calculated")
B40: Discount Rate | C40: % | D40: 0 | E40: =IF(D7="hide","","optional, assume an annual rate. used if you want to discount the future cash flows, using methodology from https://www.forentrepreneurs.com/ltv/ ")
B41: ="K, "&E60 -> K, Recurring | C41: # | D41: =IFERROR((1-D27/MAX(1,D25))*(1-D40),1) -> 0.99166667 | E41: =IF(D7="hide","","optional, only used if using discount rate")
B42: ="K, "&E62 -> K, Transaction | C42: # | D42: =IFERROR((1-D36/MAX(1,D34))*(1-D40),1) -> 0.83333333 | E42: =IF(D7="hide","","optional, only used if using discount rate")
B44: Acquisition and Retention Costs
B45: Customer Acquisition Cost (CAC) | C45: =C$10 -> £ | D45: ='Get Started'!D31 -> 30 | E45: =IF(D7="hide","","may need to adjust based on one time discounts, which costs to use from CAC forecast, and other business-specific issues")
B46: ="Cost of Retention and Expansion, "&E60 -> Cost of Retention and Expansion, Recurring | C46: =C$10 -> £ | D46: 0 | E46: =IF(D7="hide","","For subscription renewals")
B47: ="Cost of Repeat and Expansion, "&E62 -> Cost of Repeat and Expansion, Transaction | C47: =C$10 -> £ | D47: ='Get Started'!D32 -> 10 | E47: =IF(D7="hide","","For repeat transactions")
B49: ="LTV, "&E60 -> LTV, Recurring | C49: =C$10 -> £ | D49: =IFERROR(D69*(1/(1-D41)+D26*D41/(1-D41)^2)-D20,0) -> 0 | E49: =IF(D7="hide","",IF(D27=0,"LTV = "&AZ77&" months * gross margin per month, since no churn is assumed the model uses the max lifetime as used in the cash flow forecast","formula for LTV from https://www.forentrepreneurs.com/ltv/ to use discount rate (optional), and growth in average revenue (optional)"))
B50: ="LTV, "&E61 -> LTV, One time | C50: =C$10 -> £ | D50: =D67/(1+$D$40/12)^D31 -> 0 | E50: =IF(D7="hide","","LTV = revenues less cost of sales for this one time cash flow assumed in the first month of forecast")
B51: ="LTV, "&E62 -> LTV, Transaction | C51: =C$10 -> £ | D51: =IFERROR((D71*(1/(1-D42)+D35*D42/(1-D42)^2))/D34-D21,0) -> 93.1 | E51: =IF(D7="hide","",IF(D36=0,"LTV = "&AZ77&" months * gross margin per month, since no churn is assumed the model uses the max lifetime as used in the cash flow forecast","formula for LTV from https://www.forentrepreneurs.com/ltv/ to use discount rate (optional), and growth in average revenue (optional)"))
B52: LTV | C52: =C$10 -> £ | D52: =IF(SUM(D49,D51)=0,BA134,SUM(D49:D51)) -> 93.1 | E52: =IF(D7="hide","","sum of all LTVs")
B53: LTV / CAC | C53: =C$10 -> £ | D53: =IFERROR(D52/ABS(D45),0) -> 3.1033333 | E53: =IF(D7="hide","","LTV / CAC, to help measure profitability performance")
B54: CAC Payback | C54: # | D54: =IFERROR(ABS(D45)/(D69+D70+D71),1) -> 0.64446831 | E54: =IF(D7="hide","","# of months to payback the customer acquisition costs, based on gross margin")
B56: Details for LTV calculations and Cash Flows per month + | E56: click on the "+" sign in the margin to see the detail behind the calculations
B58: Revenues, Cost of Sales, Gross Margin for LTV calculations
B60: ="Total Revenues, "&E60 -> Total Revenues, Recurring | C60: =C$10 -> £ | D60: =SUMIFS(D$10:D$12,E$10:E$12,E60) -> 0 | E60: Recurring | V60: calculated
B61: ="Total Revenues, "&E61 -> Total Revenues, One time | C61: =C$10 -> £ | D61: =SUMIFS(D$10:D$12,E$10:E$12,E61) -> 0 | E61: One time | V61: calculated
B62: ="Total Revenues, "&E62 -> Total Revenues, Transaction | C62: =C$10 -> £ | D62: =SUMIFS(D$10:D$12,E$10:E$12,E62) -> 87 | E62: Transaction | V62: calculated
B63: ="Total Cost of Sales, "&E63 -> Total Cost of Sales, Recurring | C63: % | D63: =SUMIFS(D$15:D$17,E$15:E$17,E63) -> 0 | E63: =E60 -> Recurring | V63: calculated
B64: ="Total Cost of Sales, "&E64 -> Total Cost of Sales, One time | C64: % | D64: =SUMIFS(D$15:D$17,E$15:E$17,E64) -> 0 | E64: =E61 -> One time | V64: calculated
B65: ="Total Cost of Sales, "&E65 -> Total Cost of Sales, Transaction | C65: % | D65: =SUMIFS(D$15:D$17,E$15:E$17,E65) -> 0.35 | E65: =E62 -> Transaction | V65: calculated
B66: ="Gross Margin, "&E60 -> Gross Margin, Recurring | C66: =C$10 -> £ | D66: =ABS(D60)-ABS(D63)*D60 -> 0 | V66: calculated
B67: Gross Margin, One time | C67: =C$10 -> £ | D67: =ABS(D61)-ABS(D64)*D61 -> 0
B68: ="Gross Margin, "&E62 -> Gross Margin, Transaction | C68: =C$10 -> £ | D68: =ABS(D62)-ABS(D65)*D62 -> 56.55 | V68: calculated
B69: =B66&", less "&LOWER(B46) -> Gross Margin, Recurring, less cost of retention and expansion, recurring | C69: =C$10 -> £ | D69: =D66-ABS(D46) -> 0 | E69: includes costs of retention, expansion, and repeat in the gross margin calculation, reflecting CORE expenses as per https://www.forentrepreneurs.com/ltv/
B70: =B67 -> Gross Margin, One time | C70: =C$10 -> £ | D70: =D67 -> 0 | E70: same as gross margin above
B71: =B68&", less "&LOWER(B69) -> Gross Margin, Transaction, less gross margin, recurring, less cost of retention and expansion, recurring | C71: =C$10 -> £ | D71: =D68-ABS(D47) -> 46.55 | E71: includes costs of retention, expansion, and repeat in the gross margin calculation, reflecting CORE expenses as per https://www.forentrepreneurs.com/ltv/
B74: Per month cash flows | D74: calculated to show cash flows per month, unhide to see the calculations that support the chart above
B76: Timescale
B77: Month from acquisition | D77: 0 | E77: =D77+1 -> 1 | F77: =E77+1 -> 2 | G77: =F77+1 -> 3 | H77: =G77+1 -> 4 | I77: =H77+1 -> 5 | J77: =I77+1 -> 6 | K77: =J77+1 -> 7 | L77: =K77+1 -> 8 | ... AZ77: =AY77+1 -> 48 | BA77: =AZ77&" month total" -> 48 month total
B78: Recurring (Timing of Billing Cycle) | C78: # | D78: =D77 -> 0 | E78: =IF(MOD(E$77,MAX(1,$D24))=0,1+D78,D78) -> 0 | F78: =IF(MOD(F$77,MAX(1,$D24))=0,1+E78,E78) -> 0 | G78: =IF(MOD(G$77,MAX(1,$D24))=0,1+F78,F78) -> 1 | H78: =IF(MOD(H$77,MAX(1,$D24))=0,1+G78,G78) -> 1 | I78: =IF(MOD(I$77,MAX(1,$D24))=0,1+H78,H78) -> 1 | J78: =IF(MOD(J$77,MAX(1,$D24))=0,1+I78,I78) -> 2 | K78: =IF(MOD(K$77,MAX(1,$D24))=0,1+J78,J78) -> 2 | L78: =IF(MOD(L$77,MAX(1,$D24))=0,1+K78,K78) -> 2 | ... AZ78: =IF(MOD(AZ$77,MAX(1,$D24))=0,1+AY78,AY78) -> 16
B79: Recurring (Timing of Renewal / Churn) | C79: # | D79: =D77 -> 0 | E79: =IF(MOD(E$77,MAX(1,$D25))=0,1+D79,D79) -> 0 | F79: =IF(MOD(F$77,MAX(1,$D25))=0,1+E79,E79) -> 0 | G79: =IF(MOD(G$77,MAX(1,$D25))=0,1+F79,F79) -> 0 | H79: =IF(MOD(H$77,MAX(1,$D25))=0,1+G79,G79) -> 0 | I79: =IF(MOD(I$77,MAX(1,$D25))=0,1+H79,H79) -> 0 | J79: =IF(MOD(J$77,MAX(1,$D25))=0,1+I79,I79) -> 0 | K79: =IF(MOD(K$77,MAX(1,$D25))=0,1+J79,J79) -> 0 | L79: =IF(MOD(L$77,MAX(1,$D25))=0,1+K79,K79) -> 0 | ... AZ79: =IF(MOD(AZ$77,MAX(1,$D25))=0,1+AY79,AY79) -> 4
B80: Repeat (Timing of Repeat / Churn) | C80: # | D80: =D77 -> 0 | E80: =IF($D34=0,0,IF(MOD(E$77,$D34)=0,1+D80,D80)) -> 0 | F80: =IF($D34=0,0,IF(MOD(F$77,$D34)=0,1+E80,E80)) -> 0 | G80: =IF($D34=0,0,IF(MOD(G$77,$D34)=0,1+F80,F80)) -> 1 | H80: =IF($D34=0,0,IF(MOD(H$77,$D34)=0,1+G80,G80)) -> 1 | I80: =IF($D34=0,0,IF(MOD(I$77,$D34)=0,1+H80,H80)) -> 1 | J80: =IF($D34=0,0,IF(MOD(J$77,$D34)=0,1+I80,I80)) -> 2 | K80: =IF($D34=0,0,IF(MOD(K$77,$D34)=0,1+J80,J80)) -> 2 | L80: =IF($D34=0,0,IF(MOD(L$77,$D34)=0,1+K80,K80)) -> 2 | ... AZ80: =IF($D34=0,0,IF(MOD(AZ$77,$D34)=0,1+AY80,AY80)) -> 16
B81: Transactions (New and Repeat) | C81: # | D81: 1 | E81: =IF($D37=0,0,IF(MOD(E77,ROUND((12)/MAX($D37,0),0))=0,1,0)) -> 0 | F81: =IF($D37=0,0,IF(MOD(F77,ROUND((12)/MAX($D37,0),0))=0,1,0)) -> 0 | G81: =IF($D37=0,0,IF(MOD(G77,ROUND((12)/MAX($D37,0),0))=0,1,0)) -> 1 | H81: =IF($D37=0,0,IF(MOD(H77,ROUND((12)/MAX($D37,0),0))=0,1,0)) -> 0 | I81: =IF($D37=0,0,IF(MOD(I77,ROUND((12)/MAX($D37,0),0))=0,1,0)) -> 0 | J81: =IF($D37=0,0,IF(MOD(J77,ROUND((12)/MAX($D37,0),0))=0,1,0)) -> 1 | K81: =IF($D37=0,0,IF(MOD(K77,ROUND((12)/MAX($D37,0),0))=0,1,0)) -> 0 | L81: =IF($D37=0,0,IF(MOD(L77,ROUND((12)/MAX($D37,0),0))=0,1,0)) -> 0 | ... AZ81: =IF($D37=0,0,IF(MOD(AZ77,ROUND((12)/MAX($D37,0),0))=0,1,0)) -> 1 | BA81: =SUM(D81:AZ81) -> 17
B82: ="Retention, "&E60 -> Retention, Recurring | C82: % | D82: 1 | E82: =$D82*(1-$D27)^E79 -> 1 | F82: =$D82*(1-$D27)^F79 -> 1 | G82: =$D82*(1-$D27)^G79 -> 1 | H82: =$D82*(1-$D27)^H79 -> 1 | I82: =$D82*(1-$D27)^I79 -> 1 | J82: =$D82*(1-$D27)^J79 -> 1 | K82: =$D82*(1-$D27)^K79 -> 1 | L82: =$D82*(1-$D27)^L79 -> 1 | ... AZ82: =$D82*(1-$D27)^AZ79 -> 0.6561
B83: ="Retention, "&E61 -> Retention, One time | C83: % | D83: 1 | E83: =D83 -> 1 | F83: =E83 -> 1 | G83: =F83 -> 1 | H83: =G83 -> 1 | I83: =H83 -> 1 | J83: =I83 -> 1 | K83: =J83 -> 1 | L83: =K83 -> 1 | ... AZ83: =AY83 -> 1
B84: ="Retention, "&E62 -> Retention, Transaction | C84: % | D84: =D82 -> 1 | E84: =$D84*(1-$D36)^E80 -> 1 | F84: =$D84*(1-$D36)^F80 -> 1 | G84: =$D84*(1-$D36)^G80 -> 0.5 | H84: =$D84*(1-$D36)^H80 -> 0.5 | I84: =$D84*(1-$D36)^I80 -> 0.5 | J84: =$D84*(1-$D36)^J80 -> 0.25 | K84: =$D84*(1-$D36)^K80 -> 0.25 | L84: =$D84*(1-$D36)^L80 -> 0.25 | ... AZ84: =$D84*(1-$D36)^AZ80 -> 1.5258789e-05
B86: Unit Economics, net of churn, per period | D86: this section estimates gross margin and acquisition costs, net of churn, so it shows how the total LTV accrues over time
B88: Revenues, net of churn
B89: ="Revenues, "&E60 -> Revenues, Recurring | C89: =C$10 -> £ | D89: =IF(D77=0,$D60,IF(D79<>C79,IFERROR($D60*(1+$D26/(12*MAX(1,$D25)))^D79*D82,0),C89)) -> 0 | E89: =IF(E77=0,$D60,IF(E79<>D79,IFERROR($D60*(1+$D26/(12*MAX(1,$D25)))^E79*E82,0),D89)) -> 0 | F89: =IF(F77=0,$D60,IF(F79<>E79,IFERROR($D60*(1+$D26/(12*MAX(1,$D25)))^F79*F82,0),E89)) -> 0 | G89: =IF(G77=0,$D60,IF(G79<>F79,IFERROR($D60*(1+$D26/(12*MAX(1,$D25)))^G79*G82,0),F89)) -> 0 | H89: =IF(H77=0,$D60,IF(H79<>G79,IFERROR($D60*(1+$D26/(12*MAX(1,$D25)))^H79*H82,0),G89)) -> 0 | I89: =IF(I77=0,$D60,IF(I79<>H79,IFERROR($D60*(1+$D26/(12*MAX(1,$D25)))^I79*I82,0),H89)) -> 0 | J89: =IF(J77=0,$D60,IF(J79<>I79,IFERROR($D60*(1+$D26/(12*MAX(1,$D25)))^J79*J82,0),I89)) -> 0 | K89: =IF(K77=0,$D60,IF(K79<>J79,IFERROR($D60*(1+$D26/(12*MAX(1,$D25)))^K79*K82,0),J89)) -> 0 | ... AZ89: =IF(AZ77=0,$D60,IF(AZ79<>AY79,IFERROR($D60*(1+$D26/(12*MAX(1,$D25)))^AZ79*AZ82,0),AY89)) -> 0 | BA89: =SUM(D89:AZ89) -> 0
B90: ="Revenues, "&E61 -> Revenues, One time | C90: =C$10 -> £ | D90: =IF(D77=$D31,$D61*D83,0) -> 0 | E90: =IF(E77=$D31,$D61*E83,0) -> 0 | F90: =IF(F77=$D31,$D61*F83,0) -> 0 | G90: =IF(G77=$D31,$D61*G83,0) -> 0 | H90: =IF(H77=$D31,$D61*H83,0) -> 0 | I90: =IF(I77=$D31,$D61*I83,0) -> 0 | J90: =IF(J77=$D31,$D61*J83,0) -> 0 | K90: =IF(K77=$D31,$D61*K83,0) -> 0 | ... AZ90: =IF(AZ77=$D31,$D61*AZ83,0) -> 0 | BA90: =SUM(D90:AZ90) -> 0
B91: ="Revenues, "&E62 -> Revenues, Transaction | C91: =C$10 -> £ | D91: =IF(D77=0,$D62*D81,IFERROR($D62*D81*(1+$D35/(12*$D34))^D80*D84,0)) -> 87 | E91: =IF(E77=0,$D62*E81,IFERROR($D62*E81*(1+$D35/(12*$D34))^E80*E84,0)) -> 0 | F91: =IF(F77=0,$D62*F81,IFERROR($D62*F81*(1+$D35/(12*$D34))^F80*F84,0)) -> 0 | G91: =IF(G77=0,$D62*G81,IFERROR($D62*G81*(1+$D35/(12*$D34))^G80*G84,0)) -> 43.5 | H91: =IF(H77=0,$D62*H81,IFERROR($D62*H81*(1+$D35/(12*$D34))^H80*H84,0)) -> 0 | I91: =IF(I77=0,$D62*I81,IFERROR($D62*I81*(1+$D35/(12*$D34))^I80*I84,0)) -> 0 | J91: =IF(J77=0,$D62*J81,IFERROR($D62*J81*(1+$D35/(12*$D34))^J80*J84,0)) -> 21.75 | K91: =IF(K77=0,$D62*K81,IFERROR($D62*K81*(1+$D35/(12*$D34))^K80*K84,0)) -> 0 | ... AZ91: =IF(AZ77=0,$D62*AZ81,IFERROR($D62*AZ81*(1+$D35/(12*$D34))^AZ80*AZ84,0)) -> 0.0013275146 | BA91: =SUM(D91:AZ91) -> 173.99867
B93: Cost of Sales, net of churn
B94: ="Cost of Sales, "&E60 -> Cost of Sales, Recurring | C94: =C$10 -> £ | D94: =IF(D77=0,ABS($D63)*$D60,IF(D79<>C79,IFERROR($D63*$D60*(1+$D26/(12*MAX(1,$D25)))^D79*D82,0),C94)) -> 0 | E94: =IF(E77=0,ABS($D63)*$D60,IF(E79<>D79,IFERROR($D63*$D60*(1+$D26/(12*MAX(1,$D25)))^E79*E82,0),D94)) -> 0 | F94: =IF(F77=0,ABS($D63)*$D60,IF(F79<>E79,IFERROR($D63*$D60*(1+$D26/(12*MAX(1,$D25)))^F79*F82,0),E94)) -> 0 | G94: =IF(G77=0,ABS($D63)*$D60,IF(G79<>F79,IFERROR($D63*$D60*(1+$D26/(12*MAX(1,$D25)))^G79*G82,0),F94)) -> 0 | H94: =IF(H77=0,ABS($D63)*$D60,IF(H79<>G79,IFERROR($D63*$D60*(1+$D26/(12*MAX(1,$D25)))^H79*H82,0),G94)) -> 0 | I94: =IF(I77=0,ABS($D63)*$D60,IF(I79<>H79,IFERROR($D63*$D60*(1+$D26/(12*MAX(1,$D25)))^I79*I82,0),H94)) -> 0 | J94: =IF(J77=0,ABS($D63)*$D60,IF(J79<>I79,IFERROR($D63*$D60*(1+$D26/(12*MAX(1,$D25)))^J79*J82,0),I94)) -> 0 | K94: =IF(K77=0,ABS($D63)*$D60,IF(K79<>J79,IFERROR($D63*$D60*(1+$D26/(12*MAX(1,$D25)))^K79*K82,0),J94)) -> 0 | ... AZ94: =IF(AZ77=0,ABS($D63)*$D60,IF(AZ79<>AY79,IFERROR($D63*$D60*(1+$D26/(12*MAX(1,$D25)))^AZ79*AZ82,0),AY94)) -> 0 | BA94: =SUM(D94:AZ94) -> 0
B95: ="Cost of Sales, "&E61 -> Cost of Sales, One time | C95: =C$10 -> £ | D95: =IF(D77=$D31,ABS($D64)*$D61*D83,0) -> 0 | E95: =IF(E77=$D31,ABS($D64)*$D61*E83,0) -> 0 | F95: =IF(F77=$D31,ABS($D64)*$D61*F83,0) -> 0 | G95: =IF(G77=$D31,ABS($D64)*$D61*G83,0) -> 0 | H95: =IF(H77=$D31,ABS($D64)*$D61*H83,0) -> 0 | I95: =IF(I77=$D31,ABS($D64)*$D61*I83,0) -> 0 | J95: =IF(J77=$D31,ABS($D64)*$D61*J83,0) -> 0 | K95: =IF(K77=$D31,ABS($D64)*$D61*K83,0) -> 0 | ... AZ95: =IF(AZ77=$D31,ABS($D64)*$D61*AZ83,0) -> 0 | BA95: =SUM(D95:AZ95) -> 0
B96: ="Cost of Sales, "&E62 -> Cost of Sales, Transaction | C96: =C$10 -> £ | D96: =IF(D77=0,ABS($D65)*$D62*D81,IFERROR(ABS($D65)*$D62*D81*(1+$D35/(12*$D34))^D80*D84,0)) -> 30.45 | E96: =IF(E77=0,ABS($D65)*$D62*E81,IFERROR(ABS($D65)*$D62*E81*(1+$D35/(12*$D34))^E80*E84,0)) -> 0 | F96: =IF(F77=0,ABS($D65)*$D62*F81,IFERROR(ABS($D65)*$D62*F81*(1+$D35/(12*$D34))^F80*F84,0)) -> 0 | G96: =IF(G77=0,ABS($D65)*$D62*G81,IFERROR(ABS($D65)*$D62*G81*(1+$D35/(12*$D34))^G80*G84,0)) -> 15.225 | H96: =IF(H77=0,ABS($D65)*$D62*H81,IFERROR(ABS($D65)*$D62*H81*(1+$D35/(12*$D34))^H80*H84,0)) -> 0 | I96: =IF(I77=0,ABS($D65)*$D62*I81,IFERROR(ABS($D65)*$D62*I81*(1+$D35/(12*$D34))^I80*I84,0)) -> 0 | J96: =IF(J77=0,ABS($D65)*$D62*J81,IFERROR(ABS($D65)*$D62*J81*(1+$D35/(12*$D34))^J80*J84,0)) -> 7.6125 | K96: =IF(K77=0,ABS($D65)*$D62*K81,IFERROR(ABS($D65)*$D62*K81*(1+$D35/(12*$D34))^K80*K84,0)) -> 0 | ... AZ96: =IF(AZ77=0,ABS($D65)*$D62*AZ81,IFERROR(ABS($D65)*$D62*AZ81*(1+$D35/(12*$D34))^AZ80*AZ84,0)) -> 0.00046463013 | BA96: =SUM(D96:AZ96) -> 60.899535
B98: Discounts, net of churn
B99: ="Discounts, "&E60 -> Discounts, Recurring | C99: =C$10 -> £ | D99: =IF(D77<=MAX(1,$D24)-1,ABS($D20)/MAX(1,$D24),0) -> 0 | E99: =IF(E77<=MAX(1,$D24)-1,ABS($D20)/MAX(1,$D24),0) -> 0 | F99: =IF(F77<=MAX(1,$D24)-1,ABS($D20)/MAX(1,$D24),0) -> 0 | G99: =IF(G77<=MAX(1,$D24)-1,ABS($D20)/MAX(1,$D24),0) -> 0 | H99: =IF(H77<=MAX(1,$D24)-1,ABS($D20)/MAX(1,$D24),0) -> 0 | I99: =IF(I77<=MAX(1,$D24)-1,ABS($D20)/MAX(1,$D24),0) -> 0 | J99: =IF(J77<=MAX(1,$D24)-1,ABS($D20)/MAX(1,$D24),0) -> 0 | K99: =IF(K77<=MAX(1,$D24)-1,ABS($D20)/MAX(1,$D24),0) -> 0 | ... AZ99: =IF(AZ77<=MAX(1,$D24)-1,ABS($D20)/MAX(1,$D24),0) -> 0 | BA99: =SUM(D99:AZ99) -> 0
B100: ="Discounts, "&E61 -> Discounts, One time | C100: =C$10 -> £ | D100: 0 | E100: 0 | F100: 0 | G100: 0 | H100: 0 | I100: 0 | J100: 0 | K100: 0 | L100: 0 | M100: 0 | N100: 0 | O100: 0 | P100: 0 | Q100: 0 | R100: 0 | S100: 0 | T100: 0 | U100: 0 | V100: 0 | W100: 0 | X100: 0 | Y100: 0 | Z100: 0 | AA100: 0 | AB100: 0 | AC100: 0 | AD100: 0 | AE100: 0 | AF100: 0 | AG100: 0 | AH100: 0 | AI100: 0 | AJ100: 0 | AK100: 0 | AL100: 0 | AM100: 0 | AN100: 0 | AO100: 0 | AP100: 0 | AQ100: 0 | AR100: 0 | AS100: 0 | AT100: 0 | AU100: 0 | AV100: 0 | AW100: 0 | AX100: 0 | AY100: 0 | AZ100: 0 | BA100: =SUM(D100:AZ100) -> 0
B101: ="Discounts, "&E62 -> Discounts, Transaction | C101: =C$10 -> £ | D101: =IF(D77=0,ABS($D21),0) -> 0 | E101: =IF(E77=0,ABS($D21),0) -> 0 | F101: =IF(F77=0,ABS($D21),0) -> 0 | G101: =IF(G77=0,ABS($D21),0) -> 0 | H101: =IF(H77=0,ABS($D21),0) -> 0 | I101: =IF(I77=0,ABS($D21),0) -> 0 | J101: =IF(J77=0,ABS($D21),0) -> 0 | K101: =IF(K77=0,ABS($D21),0) -> 0 | ... AZ101: =IF(AZ77=0,ABS($D21),0) -> 0 | BA101: =SUM(D101:AZ101) -> 0
B103: Billings, net discounts, net of churn
B104: ="Billings, "&E60 -> Billings, Recurring | C104: =C$10 -> £ | D104: =IF(OR(D78<>C78,D77=0),D89*MAX(1,$D24),0)-IF(D77=0,ABS($D20),0) -> 0 | E104: =IF(OR(E78<>D78,E77=0),E89*MAX(1,$D24),0)-IF(E77=0,ABS($D20),0) -> 0 | F104: =IF(OR(F78<>E78,F77=0),F89*MAX(1,$D24),0)-IF(F77=0,ABS($D20),0) -> 0 | G104: =IF(OR(G78<>F78,G77=0),G89*MAX(1,$D24),0)-IF(G77=0,ABS($D20),0) -> 0 | H104: =IF(OR(H78<>G78,H77=0),H89*MAX(1,$D24),0)-IF(H77=0,ABS($D20),0) -> 0 | I104: =IF(OR(I78<>H78,I77=0),I89*MAX(1,$D24),0)-IF(I77=0,ABS($D20),0) -> 0 | J104: =IF(OR(J78<>I78,J77=0),J89*MAX(1,$D24),0)-IF(J77=0,ABS($D20),0) -> 0 | K104: =IF(OR(K78<>J78,K77=0),K89*MAX(1,$D24),0)-IF(K77=0,ABS($D20),0) -> 0 | ... AZ104: =IF(OR(AZ78<>AY78,AZ77=0),AZ89*MAX(1,$D24),0)-IF(AZ77=0,ABS($D20),0) -> 0 | BA104: =SUM(D104:AZ104) -> 0
B105: ="Billings, "&E61 -> Billings, One time | C105: =C$10 -> £ | D105: =D90 -> 0 | E105: =E90 -> 0 | F105: =F90 -> 0 | G105: =G90 -> 0 | H105: =H90 -> 0 | I105: =I90 -> 0 | J105: =J90 -> 0 | K105: =K90 -> 0 | ... AZ105: =AZ90 -> 0 | BA105: =SUM(D105:AZ105) -> 0
B106: ="Billings, "&E62 -> Billings, Transaction | C106: =C$10 -> £ | D106: =D91-IF(D77=0,ABS($D21),0) -> 87 | E106: =E91-IF(E77=0,ABS($D21),0) -> 0 | F106: =F91-IF(F77=0,ABS($D21),0) -> 0 | G106: =G91-IF(G77=0,ABS($D21),0) -> 43.5 | H106: =H91-IF(H77=0,ABS($D21),0) -> 0 | I106: =I91-IF(I77=0,ABS($D21),0) -> 0 | J106: =J91-IF(J77=0,ABS($D21),0) -> 21.75 | K106: =K91-IF(K77=0,ABS($D21),0) -> 0 | ... AZ106: =AZ91-IF(AZ77=0,ABS($D21),0) -> 0.0013275146 | BA106: =SUM(D106:AZ106) -> 173.99867
B108: Acquisition and Retention Costs, net of churn
B109: Acquisition Costs | C109: =C$10 -> £ | D109: =IF(D77=0,ABS($D45)*-1,0) -> -30 | E109: =IF(E77=0,ABS($D45)*-1,0) -> 0 | F109: =IF(F77=0,ABS($D45)*-1,0) -> 0 | G109: =IF(G77=0,ABS($D45)*-1,0) -> 0 | H109: =IF(H77=0,ABS($D45)*-1,0) -> 0 | I109: =IF(I77=0,ABS($D45)*-1,0) -> 0 | J109: =IF(J77=0,ABS($D45)*-1,0) -> 0 | K109: =IF(K77=0,ABS($D45)*-1,0) -> 0 | ... AZ109: =IF(AZ77=0,ABS($D45)*-1,0) -> 0 | BA109: =SUM(D109:AZ109) -> -30
B110: Retention Costs | C110: =C$10 -> £ | D110: =IF(D77=0,0,IF(D79<>C79,ABS($D46)*D82*-1,0)) -> 0 | E110: =IF(E77=0,0,IF(E79<>D79,ABS($D46)*E82*-1,0)) -> 0 | F110: =IF(F77=0,0,IF(F79<>E79,ABS($D46)*F82*-1,0)) -> 0 | G110: =IF(G77=0,0,IF(G79<>F79,ABS($D46)*G82*-1,0)) -> 0 | H110: =IF(H77=0,0,IF(H79<>G79,ABS($D46)*H82*-1,0)) -> 0 | I110: =IF(I77=0,0,IF(I79<>H79,ABS($D46)*I82*-1,0)) -> 0 | J110: =IF(J77=0,0,IF(J79<>I79,ABS($D46)*J82*-1,0)) -> 0 | K110: =IF(K77=0,0,IF(K79<>J79,ABS($D46)*K82*-1,0)) -> 0 | ... AZ110: =IF(AZ77=0,0,IF(AZ79<>AY79,ABS($D46)*AZ82*-1,0)) -> 0 | BA110: =SUM(D110:AZ110) -> 0
B111: Repeat Acquisition Costs | C111: =C$10 -> £ | D111: =IF(D77=0,0,ABS($D47)*D84*D81*-1) -> 0 | E111: =IF(E77=0,0,ABS($D47)*E84*E81*-1) -> 0 | F111: =IF(F77=0,0,ABS($D47)*F84*F81*-1) -> 0 | G111: =IF(G77=0,0,ABS($D47)*G84*G81*-1) -> -5 | H111: =IF(H77=0,0,ABS($D47)*H84*H81*-1) -> 0 | I111: =IF(I77=0,0,ABS($D47)*I84*I81*-1) -> 0 | J111: =IF(J77=0,0,ABS($D47)*J84*J81*-1) -> -2.5 | K111: =IF(K77=0,0,ABS($D47)*K84*K81*-1) -> 0 | ... AZ111: =IF(AZ77=0,0,ABS($D47)*AZ84*AZ81*-1) -> -0.00015258789 | BA111: =SUM(D111:AZ111) -> -9.9998474
B113: Billings, net of churn | C113: =C$10 -> £ | D113: =SUM(D104:D106) -> 87 | E113: =SUM(E104:E106) -> 0 | F113: =SUM(F104:F106) -> 0 | G113: =SUM(G104:G106) -> 43.5 | H113: =SUM(H104:H106) -> 0 | I113: =SUM(I104:I106) -> 0 | J113: =SUM(J104:J106) -> 21.75 | K113: =SUM(K104:K106) -> 0 | ... AZ113: =SUM(AZ104:AZ106) -> 0.0013275146 | BA113: =SUM(D113:AZ113) -> 173.99867
B114: Net Revenues, net of churn | C114: =C$10 -> £ | D114: =SUM(D89:D91) -> 87 | E114: =SUM(E89:E91) -> 0 | F114: =SUM(F89:F91) -> 0 | G114: =SUM(G89:G91) -> 43.5 | H114: =SUM(H89:H91) -> 0 | I114: =SUM(I89:I91) -> 0 | J114: =SUM(J89:J91) -> 21.75 | K114: =SUM(K89:K91) -> 0 | ... AZ114: =SUM(AZ89:AZ91) -> 0.0013275146 | BA114: =SUM(D114:AZ114) -> 173.99867
B115: Cost of Sales, net of churn | C115: =C$10 -> £ | D115: =SUM(D94:D96) -> 30.45 | E115: =SUM(E94:E96) -> 0 | F115: =SUM(F94:F96) -> 0 | G115: =SUM(G94:G96) -> 15.225 | H115: =SUM(H94:H96) -> 0 | I115: =SUM(I94:I96) -> 0 | J115: =SUM(J94:J96) -> 7.6125 | K115: =SUM(K94:K96) -> 0 | ... AZ115: =SUM(AZ94:AZ96) -> 0.00046463013 | BA115: =SUM(D115:AZ115) -> 60.899535
B116: Acquisition and Retention Costs, net of churn | C116: =C$10 -> £ | D116: =SUM(D109:D111)*-1 -> 30 | E116: =SUM(E109:E111)*-1 -> 0 | F116: =SUM(F109:F111)*-1 -> 0 | G116: =SUM(G109:G111)*-1 -> 5 | H116: =SUM(H109:H111)*-1 -> 0 | I116: =SUM(I109:I111)*-1 -> 0 | J116: =SUM(J109:J111)*-1 -> 2.5 | K116: =SUM(K109:K111)*-1 -> 0 | ... AZ116: =SUM(AZ109:AZ111)*-1 -> 0.00015258789 | BA116: =SUM(D116:AZ116) -> 39.999847
B118: Gross Margin, net of churn
B119: Net Gross Margin, net of churn, per period | C119: =C$10 -> £ | D119: {=SUMPRODUCT(D89:D91-D94:D96-D99:D101,D82:D84)} -> 56.55 | E119: {=SUMPRODUCT(E89:E91-E94:E96-E99:E101,E82:E84)} -> 0 | F119: {=SUMPRODUCT(F89:F91-F94:F96-F99:F101,F82:F84)} -> 0 | G119: {=SUMPRODUCT(G89:G91-G94:G96-G99:G101,G82:G84)} -> 14.1375 | H119: {=SUMPRODUCT(H89:H91-H94:H96-H99:H101,H82:H84)} -> 0 | I119: {=SUMPRODUCT(I89:I91-I94:I96-I99:I101,I82:I84)} -> 0 | J119: {=SUMPRODUCT(J89:J91-J94:J96-J99:J101,J82:J84)} -> 3.534375 | K119: {=SUMPRODUCT(K89:K91-K94:K96-K99:K101,K82:K84)} -> 0 | ... AZ119: {=SUMPRODUCT(AZ89:AZ91-AZ94:AZ96-AZ99:AZ101,AZ82:AZ84)} -> 1.3166573e-08 | BA119: =SUM(D119:AZ119) -> 75.4
B120: Cumulative Gross Margin, net of churn | C120: =C$10 -> £ | D120: =D119 -> 56.55 | E120: =IFERROR(D120+E119,0) -> 56.55 | F120: =IFERROR(E120+F119,0) -> 56.55 | G120: =IFERROR(F120+G119,0) -> 70.6875 | H120: =IFERROR(G120+H119,0) -> 70.6875 | I120: =IFERROR(H120+I119,0) -> 70.6875 | J120: =IFERROR(I120+J119,0) -> 74.221875 | K120: =IFERROR(J120+K119,0) -> 74.221875 | L120: =IFERROR(K120+L119,0) -> 74.221875 | ... AZ120: =IFERROR(AY120+AZ119,0) -> 75.4 | BA120: =AZ120 -> 75.4
B121: =B119&", discounted" -> Net Gross Margin, net of churn, per period, discounted | C121: =C$10 -> £ | D121: =D119/(1+$D$40/12)^D$77 -> 56.55 | E121: =E119/(1+$D$40/12)^E$77 -> 0 | F121: =F119/(1+$D$40/12)^F$77 -> 0 | G121: =G119/(1+$D$40/12)^G$77 -> 14.1375 | H121: =H119/(1+$D$40/12)^H$77 -> 0 | I121: =I119/(1+$D$40/12)^I$77 -> 0 | J121: =J119/(1+$D$40/12)^J$77 -> 3.534375 | K121: =K119/(1+$D$40/12)^K$77 -> 0 | ... AZ121: =AZ119/(1+$D$40/12)^AZ$77 -> 1.3166573e-08 | BA121: =SUM(D121:AZ121) -> 75.4
B122: =B120&", discounted" -> Cumulative Gross Margin, net of churn, discounted | C122: =C$10 -> £ | D122: =D121 -> 56.55 | E122: =IFERROR(D122+E121,0) -> 56.55 | F122: =IFERROR(E122+F121,0) -> 56.55 | G122: =IFERROR(F122+G121,0) -> 70.6875 | H122: =IFERROR(G122+H121,0) -> 70.6875 | I122: =IFERROR(H122+I121,0) -> 70.6875 | J122: =IFERROR(I122+J121,0) -> 74.221875 | K122: =IFERROR(J122+K121,0) -> 74.221875 | L122: =IFERROR(K122+L121,0) -> 74.221875 | ... AZ122: =IFERROR(AY122+AZ121,0) -> 75.4 | BA122: =AZ122 -> 75.4
B124: Billings less Cost of Sales, net of churn | D124: these are calculated only for the graph
B125: ="Billings less cost of sales, "&E60&", net of churn" -> Billings less cost of sales, Recurring, net of churn | C125: =C$10 -> £ | D125: =(D104-D94)*D82 -> 0 | E125: =(E104-E94)*E82 -> 0 | F125: =(F104-F94)*F82 -> 0 | G125: =(G104-G94)*G82 -> 0 | H125: =(H104-H94)*H82 -> 0 | I125: =(I104-I94)*I82 -> 0 | J125: =(J104-J94)*J82 -> 0 | K125: =(K104-K94)*K82 -> 0 | ... AZ125: =(AZ104-AZ94)*AZ82 -> 0 | BA125: =SUM(D125:AZ125) -> 0
B126: ="Billings less cost of sales, "&E61&", net of churn" -> Billings less cost of sales, One time, net of churn | C126: =C$10 -> £ | D126: =(D105-D95)*D83 -> 0 | E126: =(E105-E95)*E83 -> 0 | F126: =(F105-F95)*F83 -> 0 | G126: =(G105-G95)*G83 -> 0 | H126: =(H105-H95)*H83 -> 0 | I126: =(I105-I95)*I83 -> 0 | J126: =(J105-J95)*J83 -> 0 | K126: =(K105-K95)*K83 -> 0 | ... AZ126: =(AZ105-AZ95)*AZ83 -> 0 | BA126: =SUM(D126:AZ126) -> 0
B127: ="Billings less cost of sales, "&E62&", net of churn" -> Billings less cost of sales, Transaction, net of churn | C127: =C$10 -> £ | D127: =(D106-D96)*D84 -> 56.55 | E127: =(E106-E96)*E84 -> 0 | F127: =(F106-F96)*F84 -> 0 | G127: =(G106-G96)*G84 -> 14.1375 | H127: =(H106-H96)*H84 -> 0 | I127: =(I106-I96)*I84 -> 0 | J127: =(J106-J96)*J84 -> 3.534375 | K127: =(K106-K96)*K84 -> 0 | ... AZ127: =(AZ106-AZ96)*AZ84 -> 1.3166573e-08 | BA127: =SUM(D127:AZ127) -> 75.4
...

Sheet Historicals
B2: Historical Performance by Cohort — template example
B4: Period | C4: Unit | D4: Note | S4: 0 | T4: =T6 -> 1 | U4: =U6 -> 2 | V4: =V6 -> 3 | W4: =W6 -> 4 | X4: =X6 -> 5 | Y4: =Y6 -> 6 | Z4: =Z6 -> 7 | AA4: =AA6 -> 8 | ... BO4: =BO6 -> 48
B5: Timestep | C5: # | D5: where the first month in the period = 0 | T5: 0 | U5: =T5+1 -> 1 | V5: =U5+1 -> 2 | W5: =V5+1 -> 3 | X5: =W5+1 -> 4 | Y5: =X5+1 -> 5 | Z5: =Y5+1 -> 6 | AA5: =Z5+1 -> 7 | AB5: =AA5+1 -> 8 | ... BO5: =BN5+1 -> 47
B6: Period # in Model | C6: # | D6: ="the model structure runs for "&BO6&" months. Month 0 is a pre-structure month, meant to capture opening items that help calculate the first month" -> the model structure runs for 48 months. Month 0 is a pre-structure month, meant to capture opening items that help calculate the first month | T6: 1 | U6: =T6+1 -> 2 | V6: =U6+1 -> 3 | W6: =V6+1 -> 4 | X6: =W6+1 -> 5 | Y6: =X6+1 -> 6 | Z6: =Y6+1 -> 7 | AA6: =Z6+1 -> 8 | AB6: =AA6+1 -> 9 | ... BO6: =BN6+1 -> 48
B7: Month | D7: month when cohort started, using dates from get started | T7: ='Get Started'!D12 -> 45596 | U7: =EDATE(T7,1) -> 45626 | V7: =EDATE(U7,1) -> 45656 | W7: =EDATE(V7,1) -> 45687 | X7: =EDATE(W7,1) -> 45716 | Y7: =EDATE(X7,1) -> 45744 | Z7: =EDATE(Y7,1) -> 45775 | AA7: =EDATE(Z7,1) -> 45805 | AB7: =EDATE(AA7,1) -> 45836 | ... BO7: =EDATE(BN7,1) -> 47024
B10: Orders | C10: # | D10: sum of the cohorts below | H10: sum | I10: =IF(H10=Forecast!$H$195,T10,IF(H10=Forecast!$H$196,BO10,IF(H10=Forecast!$H$197,SUM(T10:BO10),IF(H10=Forecast!$H$198,AVERAGE(T10:BO10),0)))) -> 109859.81 | S10: =SUM(S11:S59) -> 28904.417 | T10: =SUM(T11:T59) -> 28904.417 | U10: =SUM(U11:U59) -> 20170.534 | V10: =SUM(V11:V59) -> 16002.827 | W10: =SUM(W11:W59) -> 11878.102 | X10: =SUM(X11:X59) -> 8800.1196 | Y10: =SUM(Y11:Y59) -> 6506.3009 | Z10: =SUM(Z11:Z59) -> 4799.3567 | ... BO10: =SUM(BO11:BO59) -> 0
B11: =B10&" from Existing Customers" -> Orders from Existing Customers | C11: # | D11: 0 | H11: sum | I11: =IF(H11=Forecast!$H$195,T11,IF(H11=Forecast!$H$196,BO11,IF(H11=Forecast!$H$197,SUM(T11:BO11),IF(H11=Forecast!$H$198,AVERAGE(T11:BO11),0)))) -> 0 | S11: =T11 -> 0 | T11: 0 | U11: 0 | V11: 0 | W11: 0 | X11: 0 | Y11: 0 | Z11: 0 | AA11: 0 | AB11: 0 | AC11: 0 | AD11: 0 | AE11: 0 | AF11: 0 | AG11: 0 | AH11: 0 | AI11: 0 | AJ11: 0 | AK11: 0 | AL11: 0 | AM11: 0 | AN11: 0 | AO11: 0 | AP11: 0 | AQ11: 0 | AR11: 0 | AS11: 0 | AT11: 0 | AU11: 0 | AV11: 0 | AW11: 0 | AX11: 0 | AY11: 0 | AZ11: 0 | BA11: 0 | BB11: 0 | BC11: 0 | BD11: 0 | BE11: 0 | BF11: 0 | BG11: 0 | BH11: 0 | BI11: 0 | BJ11: 0 | BK11: 0 | BL11: 0 | BM11: 0 | BN11: 0 | BO11: 0
B12: =INDEX(T$7:BO$7,,D12) -> 45596 | C12: # | D12: 1 | H12: sum | I12: =IF(H12=Forecast!$H$195,T12,IF(H12=Forecast!$H$196,BO12,IF(H12=Forecast!$H$197,SUM(T12:BO12),IF(H12=Forecast!$H$198,AVERAGE(T12:BO12),0)))) -> 0 | S12: =T12 -> 0 | T12: 0 | U12: 0 | V12: 0 | W12: 0 | X12: 0 | Y12: 0 | Z12: 0 | AA12: 0 | AB12: 0 | AC12: 0 | AD12: 0 | AE12: 0 | AF12: 0 | AG12: 0 | AH12: 0 | AI12: 0 | AJ12: 0 | AK12: 0 | AL12: 0 | AM12: 0 | AN12: 0 | AO12: 0 | AP12: 0 | AQ12: 0 | AR12: 0 | AS12: 0 | AT12: 0 | AU12: 0 | AV12: 0 | AW12: 0 | AX12: 0 | AY12: 0 | AZ12: 0 | BA12: 0 | BB12: 0 | BC12: 0 | BD12: 0 | BE12: 0 | BF12: 0 | BG12: 0 | BH12: 0 | BI12: 0 | BJ12: 0 | BK12: 0 | BL12: 0 | BM12: 0 | BN12: 0 | BO12: 0
B13: =INDEX(T$7:BO$7,,D13) -> 45626 | C13: # | D13: =D12+1 -> 2 | H13: sum | I13: =IF(H13=Forecast!$H$195,T13,IF(H13=Forecast!$H$196,BO13,IF(H13=Forecast!$H$197,SUM(T13:BO13),IF(H13=Forecast!$H$198,AVERAGE(T13:BO13),0)))) -> 0 | S13: =T13 -> 0 | T13: 0 | U13: 0 | V13: 0 | W13: 0 | X13: 0 | Y13: 0 | Z13: 0 | AA13: 0 | AB13: 0 | AC13: 0 | AD13: 0 | AE13: 0 | AF13: 0 | AG13: 0 | AH13: 0 | AI13: 0 | AJ13: 0 | AK13: 0 | AL13: 0 | AM13: 0 | AN13: 0 | AO13: 0 | AP13: 0 | AQ13: 0 | AR13: 0 | AS13: 0 | AT13: 0 | AU13: 0 | AV13: 0 | AW13: 0 | AX13: 0 | AY13: 0 | AZ13: 0 | BA13: 0 | BB13: 0 | BC13: 0 | BD13: 0 | BE13: 0 | BF13: 0 | BG13: 0 | BH13: 0 | BI13: 0 | BJ13: 0 | BK13: 0 | BL13: 0 | BM13: 0 | BN13: 0 | BO13: 0
B14: =INDEX(T$7:BO$7,,D14) -> 45656 | C14: # | D14: =D13+1 -> 3 | H14: sum | I14: =IF(H14=Forecast!$H$195,T14,IF(H14=Forecast!$H$196,BO14,IF(H14=Forecast!$H$197,SUM(T14:BO14),IF(H14=Forecast!$H$198,AVERAGE(T14:BO14),0)))) -> 0 | S14: =T14 -> 0 | T14: 0 | U14: 0 | V14: 0 | W14: 0 | X14: 0 | Y14: 0 | Z14: 0 | AA14: 0 | AB14: 0 | AC14: 0 | AD14: 0 | AE14: 0 | AF14: 0 | AG14: 0 | AH14: 0 | AI14: 0 | AJ14: 0 | AK14: 0 | AL14: 0 | AM14: 0 | AN14: 0 | AO14: 0 | AP14: 0 | AQ14: 0 | AR14: 0 | AS14: 0 | AT14: 0 | AU14: 0 | AV14: 0 | AW14: 0 | AX14: 0 | AY14: 0 | AZ14: 0 | BA14: 0 | BB14: 0 | BC14: 0 | BD14: 0 | BE14: 0 | BF14: 0 | BG14: 0 | BH14: 0 | BI14: 0 | BJ14: 0 | BK14: 0 | BL14: 0 | BM14: 0 | BN14: 0 | BO14: 0
B15: =INDEX(T$7:BO$7,,D15) -> 45687 | C15: # | D15: =D14+1 -> 4 | H15: sum | I15: =IF(H15=Forecast!$H$195,T15,IF(H15=Forecast!$H$196,BO15,IF(H15=Forecast!$H$197,SUM(T15:BO15),IF(H15=Forecast!$H$198,AVERAGE(T15:BO15),0)))) -> 0 | S15: =T15 -> 0 | T15: 0 | U15: 0 | V15: 0 | W15: 0 | X15: 0 | Y15: 0 | Z15: 0 | AA15: 0 | AB15: 0 | AC15: 0 | AD15: 0 | AE15: 0 | AF15: 0 | AG15: 0 | AH15: 0 | AI15: 0 | AJ15: 0 | AK15: 0 | AL15: 0 | AM15: 0 | AN15: 0 | AO15: 0 | AP15: 0 | AQ15: 0 | AR15: 0 | AS15: 0 | AT15: 0 | AU15: 0 | AV15: 0 | AW15: 0 | AX15: 0 | AY15: 0 | AZ15: 0 | BA15: 0 | BB15: 0 | BC15: 0 | BD15: 0 | BE15: 0 | BF15: 0 | BG15: 0 | BH15: 0 | BI15: 0 | BJ15: 0 | BK15: 0 | BL15: 0 | BM15: 0 | BN15: 0 | BO15: 0
B16: =INDEX(T$7:BO$7,,D16) -> 45716 | C16: # | D16: =D15+1 -> 5 | H16: sum | I16: =IF(H16=Forecast!$H$195,T16,IF(H16=Forecast!$H$196,BO16,IF(H16=Forecast!$H$197,SUM(T16:BO16),IF(H16=Forecast!$H$198,AVERAGE(T16:BO16),0)))) -> 0 | S16: =T16 -> 0 | T16: 0 | U16: 0 | V16: 0 | W16: 0 | X16: 0 | Y16: 0 | Z16: 0 | AA16: 0 | AB16: 0 | AC16: 0 | AD16: 0 | AE16: 0 | AF16: 0 | AG16: 0 | AH16: 0 | AI16: 0 | AJ16: 0 | AK16: 0 | AL16: 0 | AM16: 0 | AN16: 0 | AO16: 0 | AP16: 0 | AQ16: 0 | AR16: 0 | AS16: 0 | AT16: 0 | AU16: 0 | AV16: 0 | AW16: 0 | AX16: 0 | AY16: 0 | AZ16: 0 | BA16: 0 | BB16: 0 | BC16: 0 | BD16: 0 | BE16: 0 | BF16: 0 | BG16: 0 | BH16: 0 | BI16: 0 | BJ16: 0 | BK16: 0 | BL16: 0 | BM16: 0 | BN16: 0 | BO16: 0
B17: =INDEX(T$7:BO$7,,D17) -> 45744 | C17: # | D17: =D16+1 -> 6 | H17: sum | I17: =IF(H17=Forecast!$H$195,T17,IF(H17=Forecast!$H$196,BO17,IF(H17=Forecast!$H$197,SUM(T17:BO17),IF(H17=Forecast!$H$198,AVERAGE(T17:BO17),0)))) -> 0 | S17: =T17 -> 0 | T17: 0 | U17: 0 | V17: 0 | W17: 0 | X17: 0 | Y17: 0 | Z17: 0 | AA17: 0 | AB17: 0 | AC17: 0 | AD17: 0 | AE17: 0 | AF17: 0 | AG17: 0 | AH17: 0 | AI17: 0 | AJ17: 0 | AK17: 0 | AL17: 0 | AM17: 0 | AN17: 0 | AO17: 0 | AP17: 0 | AQ17: 0 | AR17: 0 | AS17: 0 | AT17: 0 | AU17: 0 | AV17: 0 | AW17: 0 | AX17: 0 | AY17: 0 | AZ17: 0 | BA17: 0 | BB17: 0 | BC17: 0 | BD17: 0 | BE17: 0 | BF17: 0 | BG17: 0 | BH17: 0 | BI17: 0 | BJ17: 0 | BK17: 0 | BL17: 0 | BM17: 0 | BN17: 0 | BO17: 0
B18: =INDEX(T$7:BO$7,,D18) -> 45775 | C18: # | D18: =D17+1 -> 7 | H18: sum | I18: =IF(H18=Forecast!$H$195,T18,IF(H18=Forecast!$H$196,BO18,IF(H18=Forecast!$H$197,SUM(T18:BO18),IF(H18=Forecast!$H$198,AVERAGE(T18:BO18),0)))) -> 0 | S18: =T18 -> 0 | T18: 0 | U18: 0 | V18: 0 | W18: 0 | X18: 0 | Y18: 0 | Z18: 0 | AA18: 0 | AB18: 0 | AC18: 0 | AD18: 0 | AE18: 0 | AF18: 0 | AG18: 0 | AH18: 0 | AI18: 0 | AJ18: 0 | AK18: 0 | AL18: 0 | AM18: 0 | AN18: 0 | AO18: 0 | AP18: 0 | AQ18: 0 | AR18: 0 | AS18: 0 | AT18: 0 | AU18: 0 | AV18: 0 | AW18: 0 | AX18: 0 | AY18: 0 | AZ18: 0 | BA18: 0 | BB18: 0 | BC18: 0 | BD18: 0 | BE18: 0 | BF18: 0 | BG18: 0 | BH18: 0 | BI18: 0 | BJ18: 0 | BK18: 0 | BL18: 0 | BM18: 0 | BN18: 0 | BO18: 0
B19: =INDEX(T$7:BO$7,,D19) -> 45805 | C19: # | D19: =D18+1 -> 8 | H19: sum | I19: =IF(H19=Forecast!$H$195,T19,IF(H19=Forecast!$H$196,BO19,IF(H19=Forecast!$H$197,SUM(T19:BO19),IF(H19=Forecast!$H$198,AVERAGE(T19:BO19),0)))) -> 0 | S19: =T19 -> 0 | T19: 0 | U19: 0 | V19: 0 | W19: 0 | X19: 0 | Y19: 0 | Z19: 0 | AA19: 0 | AB19: 0 | AC19: 0 | AD19: 0 | AE19: 0 | AF19: 0 | AG19: 0 | AH19: 0 | AI19: 0 | AJ19: 0 | AK19: 0 | AL19: 0 | AM19: 0 | AN19: 0 | AO19: 0 | AP19: 0 | AQ19: 0 | AR19: 0 | AS19: 0 | AT19: 0 | AU19: 0 | AV19: 0 | AW19: 0 | AX19: 0 | AY19: 0 | AZ19: 0 | BA19: 0 | BB19: 0 | BC19: 0 | BD19: 0 | BE19: 0 | BF19: 0 | BG19: 0 | BH19: 0 | BI19: 0 | BJ19: 0 | BK19: 0 | BL19: 0 | BM19: 0 | BN19: 0 | BO19: 0
B20: =INDEX(T$7:BO$7,,D20) -> 45836 | C20: # | D20: =D19+1 -> 9 | H20: sum | I20: =IF(H20=Forecast!$H$195,T20,IF(H20=Forecast!$H$196,BO20,IF(H20=Forecast!$H$197,SUM(T20:BO20),IF(H20=Forecast!$H$198,AVERAGE(T20:BO20),0)))) -> 0 | S20: =T20 -> 0 | T20: 0 | U20: 0 | V20: 0 | W20: 0 | X20: 0 | Y20: 0 | Z20: 0 | AA20: 0 | AB20: 0 | AC20: 0 | AD20: 0 | AE20: 0 | AF20: 0 | AG20: 0 | AH20: 0 | AI20: 0 | AJ20: 0 | AK20: 0 | AL20: 0 | AM20: 0 | AN20: 0 | AO20: 0 | AP20: 0 | AQ20: 0 | AR20: 0 | AS20: 0 | AT20: 0 | AU20: 0 | AV20: 0 | AW20: 0 | AX20: 0 | AY20: 0 | AZ20: 0 | BA20: 0 | BB20: 0 | BC20: 0 | BD20: 0 | BE20: 0 | BF20: 0 | BG20: 0 | BH20: 0 | BI20: 0 | BJ20: 0 | BK20: 0 | BL20: 0 | BM20: 0 | BN20: 0 | BO20: 0
B21: =INDEX(T$7:BO$7,,D21) -> 45866 | C21: # | D21: =D20+1 -> 10 | H21: sum | I21: =IF(H21=Forecast!$H$195,T21,IF(H21=Forecast!$H$196,BO21,IF(H21=Forecast!$H$197,SUM(T21:BO21),IF(H21=Forecast!$H$198,AVERAGE(T21:BO21),0)))) -> 0 | S21: =T21 -> 0 | T21: 0 | U21: 0 | V21: 0 | W21: 0 | X21: 0 | Y21: 0 | Z21: 0 | AA21: 0 | AB21: 0 | AC21: 0 | AD21: 0 | AE21: 0 | AF21: 0 | AG21: 0 | AH21: 0 | AI21: 0 | AJ21: 0 | AK21: 0 | AL21: 0 | AM21: 0 | AN21: 0 | AO21: 0 | AP21: 0 | AQ21: 0 | AR21: 0 | AS21: 0 | AT21: 0 | AU21: 0 | AV21: 0 | AW21: 0 | AX21: 0 | AY21: 0 | AZ21: 0 | BA21: 0 | BB21: 0 | BC21: 0 | BD21: 0 | BE21: 0 | BF21: 0 | BG21: 0 | BH21: 0 | BI21: 0 | BJ21: 0 | BK21: 0 | BL21: 0 | BM21: 0 | BN21: 0 | BO21: 0
B22: =INDEX(T$7:BO$7,,D22) -> 45897 | C22: # | D22: =D21+1 -> 11 | H22: sum | I22: =IF(H22=Forecast!$H$195,T22,IF(H22=Forecast!$H$196,BO22,IF(H22=Forecast!$H$197,SUM(T22:BO22),IF(H22=Forecast!$H$198,AVERAGE(T22:BO22),0)))) -> 0 | S22: =T22 -> 0 | T22: 0 | U22: 0 | V22: 0 | W22: 0 | X22: 0 | Y22: 0 | Z22: 0 | AA22: 0 | AB22: 0 | AC22: 0 | AD22: 0 | AE22: 0 | AF22: 0 | AG22: 0 | AH22: 0 | AI22: 0 | AJ22: 0 | AK22: 0 | AL22: 0 | AM22: 0 | AN22: 0 | AO22: 0 | AP22: 0 | AQ22: 0 | AR22: 0 | AS22: 0 | AT22: 0 | AU22: 0 | AV22: 0 | AW22: 0 | AX22: 0 | AY22: 0 | AZ22: 0 | BA22: 0 | BB22: 0 | BC22: 0 | BD22: 0 | BE22: 0 | BF22: 0 | BG22: 0 | BH22: 0 | BI22: 0 | BJ22: 0 | BK22: 0 | BL22: 0 | BM22: 0 | BN22: 0 | BO22: 0
B23: =INDEX(T$7:BO$7,,D23) -> 45928 | C23: # | D23: =D22+1 -> 12 | H23: sum | I23: =IF(H23=Forecast!$H$195,T23,IF(H23=Forecast!$H$196,BO23,IF(H23=Forecast!$H$197,SUM(T23:BO23),IF(H23=Forecast!$H$198,AVERAGE(T23:BO23),0)))) -> 0 | S23: =T23 -> 0 | T23: 0 | U23: 0 | V23: 0 | W23: 0 | X23: 0 | Y23: 0 | Z23: 0 | AA23: 0 | AB23: 0 | AC23: 0 | AD23: 0 | AE23: 0 | AF23: 0 | AG23: 0 | AH23: 0 | AI23: 0 | AJ23: 0 | AK23: 0 | AL23: 0 | AM23: 0 | AN23: 0 | AO23: 0 | AP23: 0 | AQ23: 0 | AR23: 0 | AS23: 0 | AT23: 0 | AU23: 0 | AV23: 0 | AW23: 0 | AX23: 0 | AY23: 0 | AZ23: 0 | BA23: 0 | BB23: 0 | BC23: 0 | BD23: 0 | BE23: 0 | BF23: 0 | BG23: 0 | BH23: 0 | BI23: 0 | BJ23: 0 | BK23: 0 | BL23: 0 | BM23: 0 | BN23: 0 | BO23: 0
B24: =INDEX(T$7:BO$7,,D24) -> 45958 | C24: # | D24: =D23+1 -> 13 | H24: sum | I24: =IF(H24=Forecast!$H$195,T24,IF(H24=Forecast!$H$196,BO24,IF(H24=Forecast!$H$197,SUM(T24:BO24),IF(H24=Forecast!$H$198,AVERAGE(T24:BO24),0)))) -> 0 | S24: =T24 -> 0 | T24: 0 | U24: 0 | V24: 0 | W24: 0 | X24: 0 | Y24: 0 | Z24: 0 | AA24: 0 | AB24: 0 | AC24: 0 | AD24: 0 | AE24: 0 | AF24: 0 | AG24: 0 | AH24: 0 | AI24: 0 | AJ24: 0 | AK24: 0 | AL24: 0 | AM24: 0 | AN24: 0 | AO24: 0 | AP24: 0 | AQ24: 0 | AR24: 0 | AS24: 0 | AT24: 0 | AU24: 0 | AV24: 0 | AW24: 0 | AX24: 0 | AY24: 0 | AZ24: 0 | BA24: 0 | BB24: 0 | BC24: 0 | BD24: 0 | BE24: 0 | BF24: 0 | BG24: 0 | BH24: 0 | BI24: 0 | BJ24: 0 | BK24: 0 | BL24: 0 | BM24: 0 | BN24: 0 | BO24: 0
... B34: =INDEX(T$7:BO$7,,D34) -> 46262 | C34: # | D34: =D33+1 -> 23 | H34: sum | I34: =IF(H34=Forecast!$H$195,T34,IF(H34=Forecast!$H$196,BO34,IF(H34=Forecast!$H$197,SUM(T34:BO34),IF(H34=Forecast!$H$198,AVERAGE(T34:BO34),0)))) -> 0 | S34: =T34 -> 0 | T34: 0 | U34: 0 | V34: 0 | W34: 0 | X34: 0 | Y34: 0 | Z34: 0 | AA34: 0 | AB34: 0 | AC34: 0 | AD34: 0 | AE34: 0 | AF34: 0 | AG34: 0 | AH34: 0 | AI34: 0 | AJ34: 0 | AK34: 0 | AL34: 0 | AM34: 0 | AN34: 0 | AO34: 0 | AP34: 0 | AQ34: 0 | AR34: 0 | AS34: 0 | AT34: 0 | AU34: 0 | AV34: 0 | AW34: 0 | AX34: 0 | AY34: 0 | AZ34: 0 | BA34: 0 | BB34: 0 | BC34: 0 | BD34: 0 | BE34: 0 | BF34: 0 | BG34: 0 | BH34: 0 | BI34: 0 | BJ34: 0 | BK34: 0 | BL34: 0 | BM34: 0 | BN34: 0 | BO34: 0
B35: =INDEX(T$7:BO$7,,D35) -> 46293 | C35: # | D35: =D34+1 -> 24 | H35: sum | I35: =IF(H35=Forecast!$H$195,T35,IF(H35=Forecast!$H$196,BO35,IF(H35=Forecast!$H$197,SUM(T35:BO35),IF(H35=Forecast!$H$198,AVERAGE(T35:BO35),0)))) -> 2908.8592 | S35: =T35 -> 583.97805 | T35: =T36*0.95 -> 583.97805 | U35: =T35*0.8 -> 467.18244 | V35: =U35*0.8 -> 373.74595 | W35: =V35*0.8 -> 298.99676 | X35: =W35*0.8 -> 239.19741 | Y35: =X35*0.8 -> 191.35793 | Z35: =Y35*0.8 -> 153.08634 | AA35: =Z35*0.8 -> 122.46907 | AB35: =AA35*0.8 -> 97.975259 | ... AR35: =AQ35*0.8 -> 2.7577584 | BC35: 0 | BD35: 0 | BE35: 0 | BF35: 0 | BG35: 0 | BH35: 0 | BI35: 0 | BJ35: 0 | BK35: 0 | BL35: 0 | BM35: 0 | BN35: 0 | BO35: 0
B36: =INDEX(T$7:BO$7,,D36) -> 46323 | C36: # | D36: =D35+1 -> 25 | H36: sum | I36: =IF(H36=Forecast!$H$195,T36,IF(H36=Forecast!$H$196,BO36,IF(H36=Forecast!$H$197,SUM(T36:BO36),IF(H36=Forecast!$H$198,AVERAGE(T36:BO36),0)))) -> 3059.0542 | S36: =T36 -> 614.71374 | T36: =T37*0.95 -> 614.71374 | U36: =T36*0.8 -> 491.77099 | V36: =U36*0.8 -> 393.41679 | W36: =V36*0.8 -> 314.73343 | X36: =W36*0.8 -> 251.78675 | Y36: =X36*0.8 -> 201.4294 | Z36: =Y36*0.8 -> 161.14352 | AA36: =Z36*0.8 -> 128.91481 | AB36: =AA36*0.8 -> 103.13185 | ... AQ36: =AP36*0.8 -> 3.6286294 | BC36: 0 | BD36: 0 | BE36: 0 | BF36: 0 | BG36: 0 | BH36: 0 | BI36: 0 | BJ36: 0 | BK36: 0 | BL36: 0 | BM36: 0 | BN36: 0 | BO36: 0
B37: =INDEX(T$7:BO$7,,D37) -> 46354 | C37: # | D37: =D36+1 -> 26 | H37: sum | I37: =IF(H37=Forecast!$H$195,T37,IF(H37=Forecast!$H$196,BO37,IF(H37=Forecast!$H$197,SUM(T37:BO37),IF(H37=Forecast!$H$198,AVERAGE(T37:BO37),0)))) -> 3216.2374 | S37: =T37 -> 647.06709 | T37: =T38*0.95 -> 647.06709 | U37: =T37*0.8 -> 517.65367 | V37: =U37*0.8 -> 414.12294 | W37: =V37*0.8 -> 331.29835 | X37: =W37*0.8 -> 265.03868 | Y37: =X37*0.8 -> 212.03094 | Z37: =Y37*0.8 -> 169.62476 | AA37: =Z37*0.8 -> 135.6998 | AB37: =AA37*0.8 -> 108.55984 | ... AP37: =AO37*0.8 -> 4.7745124 | BC37: 0 | BD37: 0 | BE37: 0 | BF37: 0 | BG37: 0 | BH37: 0 | BI37: 0 | BJ37: 0 | BK37: 0 | BL37: 0 | BM37: 0 | BN37: 0 | BO37: 0
B38: =INDEX(T$7:BO$7,,D38) -> 46384 | C38: # | D38: =D37+1 -> 27 | H38: sum | I38: =IF(H38=Forecast!$H$195,T38,IF(H38=Forecast!$H$196,BO38,IF(H38=Forecast!$H$197,SUM(T38:BO38),IF(H38=Forecast!$H$198,AVERAGE(T38:BO38),0)))) -> 3380.4873 | S38: =T38 -> 681.12325 | T38: =T39*0.95 -> 681.12325 | U38: =T38*0.8 -> 544.8986 | V38: =U38*0.8 -> 435.91888 | W38: =V38*0.8 -> 348.73511 | X38: =W38*0.8 -> 278.98808 | Y38: =X38*0.8 -> 223.19047 | Z38: =Y38*0.8 -> 178.55237 | AA38: =Z38*0.8 -> 142.8419 | AB38: =AA38*0.8 -> 114.27352 | ... AO38: =AN38*0.8 -> 6.2822532 | BC38: 0 | BD38: 0 | BE38: 0 | BF38: 0 | BG38: 0 | BH38: 0 | BI38: 0 | BJ38: 0 | BK38: 0 | BL38: 0 | BM38: 0 | BN38: 0 | BO38: 0
B39: =INDEX(T$7:BO$7,,D39) -> 46415 | C39: # | D39: =D38+1 -> 28 | H39: sum | I39: =IF(H39=Forecast!$H$195,T39,IF(H39=Forecast!$H$196,BO39,IF(H39=Forecast!$H$197,SUM(T39:BO39),IF(H39=Forecast!$H$198,AVERAGE(T39:BO39),0)))) -> 3551.7947 | S39: =T39 -> 716.97184 | T39: =T40*0.95 -> 716.97184 | U39: =T39*0.8 -> 573.57748 | V39: =U39*0.8 -> 458.86198 | W39: =V39*0.8 -> 367.08958 | X39: =W39*0.8 -> 293.67167 | Y39: =X39*0.8 -> 234.93733 | Z39: =Y39*0.8 -> 187.94987 | AA39: =Z39*0.8 -> 150.35989 | AB39: =AA39*0.8 -> 120.28792 | ... AN39: =AM39*0.8 -> 8.2661226 | BC39: 0 | BD39: 0 | BE39: 0 | BF39: 0 | BG39: 0 | BH39: 0 | BI39: 0 | BJ39: 0 | BK39: 0 | BL39: 0 | BM39: 0 | BN39: 0 | BO39: 0
B40: =INDEX(T$7:BO$7,,D40) -> 46446 | C40: # | D40: =D39+1 -> 29 | H40: sum | I40: =IF(H40=Forecast!$H$195,T40,IF(H40=Forecast!$H$196,BO40,IF(H40=Forecast!$H$197,SUM(T40:BO40),IF(H40=Forecast!$H$198,AVERAGE(T40:BO40),0)))) -> 3719.1536 | S40: =T40 -> 754.70721 | T40: =T41*0.95 -> 754.70721 | U40: =T40*0.8 -> 603.76576 | V40: =U40*0.8 -> 483.01261 | W40: =V40*0.8 -> 386.41009 | X40: =W40*0.8 -> 309.12807 | Y40: =X40*0.8 -> 247.30246 | Z40: =Y40*0.8 -> 197.84197 | AA40: =Z40*0.8 -> 158.27357 | AB40: =AA40*0.8 -> 126.61886 | ... AL40: =AK40*0.8 -> 13.595596 | BC40: 0 | BD40: 0 | BE40: 0 | BF40: 0 | BG40: 0 | BH40: 0 | BI40: 0 | BJ40: 0 | BK40: 0 | BL40: 0 | BM40: 0 | BN40: 0 | BO40: 0
B41: =INDEX(T$7:BO$7,,D41) -> 46474 | C41: # | D41: =D40+1 -> 30 | H41: sum | I41: =IF(H41=Forecast!$H$195,T41,IF(H41=Forecast!$H$196,BO41,IF(H41=Forecast!$H$197,SUM(T41:BO41),IF(H41=Forecast!$H$198,AVERAGE(T41:BO41),0)))) -> 3914.8986 | S41: =T41 -> 794.42864 | T41: =T42*0.95 -> 794.42864 | U41: =T41*0.8 -> 635.54291 | V41: =U41*0.8 -> 508.43433 | W41: =V41*0.8 -> 406.74746 | X41: =W41*0.8 -> 325.39797 | Y41: =X41*0.8 -> 260.31838 | Z41: =Y41*0.8 -> 208.2547 | AA41: =Z41*0.8 -> 166.60376 | AB41: =AA41*0.8 -> 133.28301 | ... AL41: =AK41*0.8 -> 14.311154 | BC41: 0 | BD41: 0 | BE41: 0 | BF41: 0 | BG41: 0 | BH41: 0 | BI41: 0 | BJ41: 0 | BK41: 0 | BL41: 0 | BM41: 0 | BN41: 0 | BO41: 0
B42: =INDEX(T$7:BO$7,,D42) -> 46505 | C42: # | D42: =D41+1 -> 31 | H42: sum | I42: =IF(H42=Forecast!$H$195,T42,IF(H42=Forecast!$H$196,BO42,IF(H42=Forecast!$H$197,SUM(T42:BO42),IF(H42=Forecast!$H$198,AVERAGE(T42:BO42),0)))) -> 4105.8815 | S42: =T42 -> 836.24067 | T42: =T43*0.95 -> 836.24067 | U42: =T42*0.8 -> 668.99254 | V42: =U42*0.8 -> 535.19403 | W42: =V42*0.8 -> 428.15522 | X42: =W42*0.8 -> 342.52418 | Y42: =X42*0.8 -> 274.01934 | Z42: =Y42*0.8 -> 219.21547 | AA42: =Z42*0.8 -> 175.37238 | AB42: =AA42*0.8 -> 140.2979 | ... AK42: =AJ42*0.8 -> 18.830466 | BC42: 0 | BD42: 0 | BE42: 0 | BF42: 0 | BG42: 0 | BH42: 0 | BI42: 0 | BJ42: 0 | BK42: 0 | BL42: 0 | BM42: 0 | BN42: 0 | BO42: 0
B43: =INDEX(T$7:BO$7,,D43) -> 46535 | C43: # | D43: =D42+1 -> 32 | H43: sum | I43: =IF(H43=Forecast!$H$195,T43,IF(H43=Forecast!$H$196,BO43,IF(H43=Forecast!$H$197,SUM(T43:BO43),IF(H43=Forecast!$H$198,AVERAGE(T43:BO43),0)))) -> 4302.159 | S43: =T43 -> 880.25334 | T43: =T44*0.95 -> 880.25334 | U43: =T43*0.8 -> 704.20267 | V43: =U43*0.8 -> 563.36214 | W43: =V43*0.8 -> 450.68971 | X43: =W43*0.8 -> 360.55177 | Y43: =X43*0.8 -> 288.44141 | Z43: =Y43*0.8 -> 230.75313 | AA43: =Z43*0.8 -> 184.6025 | AB43: =AA43*0.8 -> 147.682 | ... AJ43: =AI43*0.8 -> 24.776929 | BC43: 0 | BD43: 0 | BE43: 0 | BF43: 0 | BG43: 0 | BH43: 0 | BI43: 0 | BJ43: 0 | BK43: 0 | BL43: 0 | BM43: 0 | BN43: 0 | BO43: 0
B44: =INDEX(T$7:BO$7,,D44) -> 46566 | C44: # | D44: =D43+1 -> 33 | H44: sum | I44: =IF(H44=Forecast!$H$195,T44,IF(H44=Forecast!$H$196,BO44,IF(H44=Forecast!$H$197,SUM(T44:BO44),IF(H44=Forecast!$H$198,AVERAGE(T44:BO44),0)))) -> 4502.5074 | S44: =T44 -> 926.58246 | T44: =T45*0.95 -> 926.58246 | U44: =T44*0.8 -> 741.26597 | V44: =U44*0.8 -> 593.01277 | W44: =V44*0.8 -> 474.41022 | X44: =W44*0.8 -> 379.52818 | Y44: =X44*0.8 -> 303.62254 | Z44: =Y44*0.8 -> 242.89803 | AA44: =Z44*0.8 -> 194.31843 | AB44: =AA44*0.8 -> 155.45474 | ... AI44: =AH44*0.8 -> 32.601222 | BC44: 0 | BD44: 0 | BE44: 0 | BF44: 0 | BG44: 0 | BH44: 0 | BI44: 0 | BJ44: 0 | BK44: 0 | BL44: 0 | BM44: 0 | BN44: 0 | BO44: 0
B45: =INDEX(T$7:BO$7,,D45) -> 46596 | C45: # | D45: =D44+1 -> 34 | H45: sum | I45: =IF(H45=Forecast!$H$195,T45,IF(H45=Forecast!$H$196,BO45,IF(H45=Forecast!$H$197,SUM(T45:BO45),IF(H45=Forecast!$H$198,AVERAGE(T45:BO45),0)))) -> 4705.1644 | S45: =T45 -> 975.34996 | T45: =T46*0.95 -> 975.34996 | U45: =T45*0.8 -> 780.27997 | V45: =U45*0.8 -> 624.22397 | W45: =V45*0.8 -> 499.37918 | X45: =W45*0.8 -> 399.50334 | Y45: =X45*0.8 -> 319.60267 | Z45: =Y45*0.8 -> 255.68214 | AA45: =Z45*0.8 -> 204.54571 | AB45: =AA45*0.8 -> 163.63657 | ... AH45: =AG45*0.8 -> 42.896345 | BC45: 0 | BD45: 0 | BE45: 0 | BF45: 0 | BG45: 0 | BH45: 0 | BI45: 0 | BJ45: 0 | BK45: 0 | BL45: 0 | BM45: 0 | BN45: 0 | BO45: 0
B46: =INDEX(T$7:BO$7,,D46) -> 46627 | C46: # | D46: =D45+1 -> 35 | H46: sum | I46: =IF(H46=Forecast!$H$195,T46,IF(H46=Forecast!$H$196,BO46,IF(H46=Forecast!$H$197,SUM(T46:BO46),IF(H46=Forecast!$H$198,AVERAGE(T46:BO46),0)))) -> 4907.6506 | S46: =T46 -> 1026.6842 | T46: =T47*0.95 -> 1026.6842 | U46: =T46*0.8 -> 821.34733 | V46: =U46*0.8 -> 657.07787 | W46: =V46*0.8 -> 525.66229 | X46: =W46*0.8 -> 420.52983 | Y46: =X46*0.8 -> 336.42387 | Z46: =Y46*0.8 -> 269.13909 | AA46: =Z46*0.8 -> 215.31128 | AB46: =AA46*0.8 -> 172.24902 | ... AG46: =AF46*0.8 -> 56.442559 | BC46: 0 | BD46: 0 | BE46: 0 | BF46: 0 | BG46: 0 | BH46: 0 | BI46: 0 | BJ46: 0 | BK46: 0 | BL46: 0 | BM46: 0 | BN46: 0 | BO46: 0
B47: =INDEX(T$7:BO$7,,D47) -> 46658 | C47: # | D47: =D46+1 -> 36 | H47: sum | I47: =IF(H47=Forecast!$H$195,T47,IF(H47=Forecast!$H$196,BO47,IF(H47=Forecast!$H$197,SUM(T47:BO47),IF(H47=Forecast!$H$198,AVERAGE(T47:BO47),0)))) -> 5106.5348 | S47: =T47 -> 1080.7202 | T47: =T48*0.95 -> 1080.7202 | U47: =T47*0.8 -> 864.57614 | V47: =U47*0.8 -> 691.66091 | W47: =V47*0.8 -> 553.32873 | X47: =W47*0.8 -> 442.66298 | Y47: =X47*0.8 -> 354.13039 | Z47: =Y47*0.8 -> 283.30431 | AA47: =Z47*0.8 -> 226.64345 | AB47: =AA47*0.8 -> 181.31476 | ... AF47: =AE47*0.8 -> 74.266525 | BC47: 0 | BD47: 0 | BE47: 0 | BF47: 0 | BG47: 0 | BH47: 0 | BI47: 0 | BJ47: 0 | BK47: 0 | BL47: 0 | BM47: 0 | BN47: 0 | BO47: 0
B48: =INDEX(T$7:BO$7,,D48) -> 46688 | C48: # | D48: =D47+1 -> 37 | H48: sum | I48: =IF(H48=Forecast!$H$195,T48,IF(H48=Forecast!$H$196,BO48,IF(H48=Forecast!$H$197,SUM(T48:BO48),IF(H48=Forecast!$H$198,AVERAGE(T48:BO48),0)))) -> 5297.1245 | S48: =T48 -> 1137.6002 | T48: =T49*0.95 -> 1137.6002 | U48: =T48*0.8 -> 910.08015 | V48: =U48*0.8 -> 728.06412 | W48: =V48*0.8 -> 582.45129 | X48: =W48*0.8 -> 465.96104 | Y48: =X48*0.8 -> 372.76883 | Z48: =Y48*0.8 -> 298.21506 | AA48: =Z48*0.8 -> 238.57205 | AB48: =AA48*0.8 -> 190.85764 | ... AE48: =AD48*0.8 -> 97.719112 | BC48: 0 | BD48: 0 | BE48: 0 | BF48: 0 | BG48: 0 | BH48: 0 | BI48: 0 | BJ48: 0 | BK48: 0 | BL48: 0 | BM48: 0 | BN48: 0 | BO48: 0
B49: =INDEX(T$7:BO$7,,D49) -> 46719 | C49: # | D49: =D48+1 -> 38 | H49: sum | I49: =IF(H49=Forecast!$H$195,T49,IF(H49=Forecast!$H$196,BO49,IF(H49=Forecast!$H$197,SUM(T49:BO49),IF(H49=Forecast!$H$198,AVERAGE(T49:BO49),0)))) -> 5473.0583 | S49: =T49 -> 1197.4739 | T49: =T50*0.95 -> 1197.4739 | U49: =T49*0.8 -> 957.9791 | V49: =U49*0.8 -> 766.38328 | W49: =V49*0.8 -> 613.10663 | X49: =W49*0.8 -> 490.4853 | Y49: =X49*0.8 -> 392.38824 | Z49: =Y49*0.8 -> 313.91059 | AA49: =Z49*0.8 -> 251.12847 | AB49: =AA49*0.8 -> 200.90278 | ... AD49: =AC49*0.8 -> 128.57778 | BC49: 0 | BD49: 0 | BE49: 0 | BF49: 0 | BG49: 0 | BH49: 0 | BI49: 0 | BJ49: 0 | BK49: 0 | BL49: 0 | BM49: 0 | BN49: 0 | BO49: 0
B50: =INDEX(T$7:BO$7,,D50) -> 46749 | C50: # | D50: =D49+1 -> 39 | H50: sum | I50: =IF(H50=Forecast!$H$195,T50,IF(H50=Forecast!$H$196,BO50,IF(H50=Forecast!$H$197,SUM(T50:BO50),IF(H50=Forecast!$H$198,AVERAGE(T50:BO50),0)))) -> 5625.7689 | S50: =T50 -> 1260.4988 | T50: =T51*0.95 -> 1260.4988 | U50: =T50*0.8 -> 1008.3991 | V50: =U50*0.8 -> 806.71924 | W50: =V50*0.8 -> 645.3754 | X50: =W50*0.8 -> 516.30032 | Y50: =X50*0.8 -> 413.04025 | Z50: =Y50*0.8 -> 330.4322 | AA50: =Z50*0.8 -> 264.34576 | AB50: =AA50*0.8 -> 211.47661 | AC50: =AB50*0.8 -> 169.18129 | BC50: 0 | BD50: 0 | BE50: 0 | BF50: 0 | BG50: 0 | BH50: 0 | BI50: 0 | BJ50: 0 | BK50: 0 | BL50: 0 | BM50: 0 | BN50: 0 | BO50: 0
B51: =INDEX(T$7:BO$7,,D51) -> 46780 | C51: # | D51: =D50+1 -> 40 | H51: sum | I51: =IF(H51=Forecast!$H$195,T51,IF(H51=Forecast!$H$196,BO51,IF(H51=Forecast!$H$197,SUM(T51:BO51),IF(H51=Forecast!$H$198,AVERAGE(T51:BO51),0)))) -> 5743.7765 | S51: =T51 -> 1326.8409 | T51: =T52*0.95 -> 1326.8409 | U51: =T51*0.8 -> 1061.4727 | V51: =U51*0.8 -> 849.17815 | W51: =V51*0.8 -> 679.34252 | X51: =W51*0.8 -> 543.47402 | Y51: =X51*0.8 -> 434.77921 | Z51: =Y51*0.8 -> 347.82337 | AA51: =Z51*0.8 -> 278.2587 | AB51: =AA51*0.8 -> 222.60696 | BC51: 0 | BD51: 0 | BE51: 0 | BF51: 0 | BG51: 0 | BH51: 0 | BI51: 0 | BJ51: 0 | BK51: 0 | BL51: 0 | BM51: 0 | BN51: 0 | BO51: 0
B52: =INDEX(T$7:BO$7,,D52) -> 46811 | C52: # | D52: =D51+1 -> 41 | H52: sum | I52: =IF(H52=Forecast!$H$195,T52,IF(H52=Forecast!$H$196,BO52,IF(H52=Forecast!$H$197,SUM(T52:BO52),IF(H52=Forecast!$H$198,AVERAGE(T52:BO52),0)))) -> 5811.7574 | S52: =T52 -> 1396.6746 | T52: =T53*0.95 -> 1396.6746 | U52: =T52*0.8 -> 1117.3397 | V52: =U52*0.8 -> 893.87174 | W52: =V52*0.8 -> 715.09739 | X52: =W52*0.8 -> 572.07791 | Y52: =X52*0.8 -> 457.66233 | Z52: =Y52*0.8 -> 366.12986 | AA52: =Z52*0.8 -> 292.90389 | BC52: 0 | BD52: 0 | BE52: 0 | BF52: 0 | BG52: 0 | BH52: 0 | BI52: 0 | BJ52: 0 | BK52: 0 | BL52: 0 | BM52: 0 | BN52: 0 | BO52: 0
B53: =INDEX(T$7:BO$7,,D53) -> 46840 | C53: # | D53: =D52+1 -> 42 | H53: sum | I53: =IF(H53=Forecast!$H$195,T53,IF(H53=Forecast!$H$196,BO53,IF(H53=Forecast!$H$197,SUM(T53:BO53),IF(H53=Forecast!$H$198,AVERAGE(T53:BO53),0)))) -> 5809.3195 | S53: =T53 -> 1470.1838 | T53: =T54*0.95 -> 1470.1838 | U53: =T53*0.8 -> 1176.147 | V53: =U53*0.8 -> 940.91762 | W53: =V53*0.8 -> 752.7341 | X53: =W53*0.8 -> 602.18728 | Y53: =X53*0.8 -> 481.74982 | Z53: =Y53*0.8 -> 385.39986 | BC53: 0 | BD53: 0 | BE53: 0 | BF53: 0 | BG53: 0 | BH53: 0 | BI53: 0 | BJ53: 0 | BK53: 0 | BL53: 0 | BM53: 0 | BN53: 0 | BO53: 0
B54: =INDEX(T$7:BO$7,,D54) -> 46871 | C54: # | D54: =D53+1 -> 43 | H54: sum | I54: =IF(H54=Forecast!$H$195,T54,IF(H54=Forecast!$H$196,BO54,IF(H54=Forecast!$H$197,SUM(T54:BO54),IF(H54=Forecast!$H$198,AVERAGE(T54:BO54),0)))) -> 5709.3891 | S54: =T54 -> 1547.5619 | T54: =T55*0.95 -> 1547.5619 | U54: =T54*0.8 -> 1238.0495 | V54: =U54*0.8 -> 990.4396 | W54: =V54*0.8 -> 792.35168 | X54: =W54*0.8 -> 633.88134 | Y54: =X54*0.8 -> 507.10508 | BC54: 0 | BD54: 0 | BE54: 0 | BF54: 0 | BG54: 0 | BH54: 0 | BI54: 0 | BJ54: 0 | BK54: 0 | BL54: 0 | BM54: 0 | BN54: 0 | BO54: 0
B55: =INDEX(T$7:BO$7,,D55) -> 46901 | C55: # | D55: =D54+1 -> 44 | H55: sum | I55: =IF(H55=Forecast!$H$195,T55,IF(H55=Forecast!$H$196,BO55,IF(H55=Forecast!$H$197,SUM(T55:BO55),IF(H55=Forecast!$H$198,AVERAGE(T55:BO55),0)))) -> 5476.0884 | S55: =T55 -> 1629.0125 | T55: =T56*0.95 -> 1629.0125 | U55: =T55*0.8 -> 1303.21 | V55: =U55*0.8 -> 1042.568 | W55: =V55*0.8 -> 834.0544 | X55: =W55*0.8 -> 667.24352 | BC55: 0 | BD55: 0 | BE55: 0 | BF55: 0 | BG55: 0 | BH55: 0 | BI55: 0 | BJ55: 0 | BK55: 0 | BL55: 0 | BM55: 0 | BN55: 0 | BO55: 0
B56: =INDEX(T$7:BO$7,,D56) -> 46932 | C56: # | D56: =D55+1 -> 45 | H56: sum | I56: =IF(H56=Forecast!$H$195,T56,IF(H56=Forecast!$H$196,BO56,IF(H56=Forecast!$H$197,SUM(T56:BO56),IF(H56=Forecast!$H$198,AVERAGE(T56:BO56),0)))) -> 5061.942 | S56: =T56 -> 1714.75 | T56: =T57*0.95 -> 1714.75 | U56: =T56*0.8 -> 1371.8 | V56: =U56*0.8 -> 1097.44 | W56: =V56*0.8 -> 877.952 | BC56: 0 | BD56: 0 | BE56: 0 | BF56: 0 | BG56: 0 | BH56: 0 | BI56: 0 | BJ56: 0 | BK56: 0 | BL56: 0 | BM56: 0 | BN56: 0 | BO56: 0
B57: =INDEX(T$7:BO$7,,D57) -> 46962 | C57: # | D57: =D56+1 -> 46 | H57: sum | I57: =IF(H57=Forecast!$H$195,T57,IF(H57=Forecast!$H$196,BO57,IF(H57=Forecast!$H$197,SUM(T57:BO57),IF(H57=Forecast!$H$198,AVERAGE(T57:BO57),0)))) -> 4404.2 | S57: =T57 -> 1805 | T57: =T58*0.95 -> 1805 | U57: =T57*0.8 -> 1444 | V57: =U57*0.8 -> 1155.2 | BC57: 0 | BD57: 0 | BE57: 0 | BF57: 0 | BG57: 0 | BH57: 0 | BI57: 0 | BJ57: 0 | BK57: 0 | BL57: 0 | BM57: 0 | BN57: 0 | BO57: 0
B58: =INDEX(T$7:BO$7,,D58) -> 46993 | C58: # | D58: =D57+1 -> 47 | H58: sum | I58: =IF(H58=Forecast!$H$195,T58,IF(H58=Forecast!$H$196,BO58,IF(H58=Forecast!$H$197,SUM(T58:BO58),IF(H58=Forecast!$H$198,AVERAGE(T58:BO58),0)))) -> 2067 | S58: =T58 -> 1900 | T58: =T59*0.95 -> 1900 | U58: 167 | BC58: 0 | BD58: 0 | BE58: 0 | BF58: 0 | BG58: 0 | BH58: 0 | BI58: 0 | BJ58: 0 | BK58: 0 | BL58: 0 | BM58: 0 | BN58: 0 | BO58: 0
B59: =INDEX(T$7:BO$7,,D59) -> 47024 | C59: # | D59: =D58+1 -> 48 | H59: sum | I59: =IF(H59=Forecast!$H$195,T59,IF(H59=Forecast!$H$196,BO59,IF(H59=Forecast!$H$197,SUM(T59:BO59),IF(H59=Forecast!$H$198,AVERAGE(T59:BO59),0)))) -> 2000 | S59: =T59 -> 2000 | T59: 2000 | BC59: 0 | BD59: 0 | BE59: 0 | BF59: 0 | BG59: 0 | BH59: 0 | BI59: 0 | BJ59: 0 | BK59: 0 | BL59: 0 | BM59: 0 | BN59: 0 | BO59: 0
B61: Analysis
B62: Retention, average | C62: # | D62: assumed % change | F62: 0 | H62: sum | I62: =IF(H62=Forecast!$H$195,T62,IF(H62=Forecast!$H$196,BO62,IF(H62=Forecast!$H$197,SUM(T62:BO62),IF(H62=Forecast!$H$198,AVERAGE(T62:BO62),0)))) -> 5307.4698 | K62: =D12 -> 1 | L62: =D59 -> 48 | T62: =IFERROR(IF(T6>$L62,0, SUMPRODUCT(T11:T59,--($D11:$D59>=$K62),--($D11:$D59<=$L62),S11:S59)/SUMPRODUCT(--($D11:$D59>=$K62),--($D11:$D59<=$L62),S11:S59)),0)*(1+$F62) -> 1310.1432 | U62: =IFERROR(IF(U6>$L62,0, SUMPRODUCT(U11:U59,--($D11:$D59>=$K62),--($D11:$D59<=$L62),T11:T59)/SUMPRODUCT(--($D11:$D59>=$K62),--($D11:$D59<=$L62),T11:T59)),0)*(1+$F62) -> 848.46683 | V62: =IFERROR(IF(V6>$L62,0, SUMPRODUCT(V11:V59,--($D11:$D59>=$K62),--($D11:$D59<=$L62),U11:U59)/SUMPRODUCT(--($D11:$D59>=$K62),--($D11:$D59<=$L62),U11:U59)),0)*(1+$F62) -> 768.07929 | W62: =IFERROR(IF(W6>$L62,0, SUMPRODUCT(W11:W59,--($D11:$D59>=$K62),--($D11:$D59<=$L62),V11:V59)/SUMPRODUCT(--($D11:$D59>=$K62),--($D11:$D59<=$L62),V11:V59)),0)*(1+$F62) -> 552.88073 | X62: =IFERROR(IF(X6>$L62,0, SUMPRODUCT(X11:X59,--($D11:$D59>=$K62),--($D11:$D59<=$L62),W11:W59)/SUMPRODUCT(--($D11:$D59>=$K62),--($D11:$D59<=$L62),W11:W59)),0)*(1+$F62) -> 424.80351 | Y62: =IFERROR(IF(Y6>$L62,0, SUMPRODUCT(Y11:Y59,--($D11:$D59>=$K62),--($D11:$D59<=$L62),X11:X59)/SUMPRODUCT(--($D11:$D59>=$K62),--($D11:$D59<=$L62),X11:X59)),0)*(1+$F62) -> 326.49315 | Z62: =IFERROR(IF(Z6>$L62,0, SUMPRODUCT(Z11:Z59,--($D11:$D59>=$K62),--($D11:$D59<=$L62),Y11:Y59)/SUMPRODUCT(--($D11:$D59>=$K62),--($D11:$D59<=$L62),Y11:Y59)),0)*(1+$F62) -> 251.00437 | AA62: =IFERROR(IF(AA6>$L62,0, SUMPRODUCT(AA11:AA59,--($D11:$D59>=$K62),--($D11:$D59<=$L62),Z11:Z59)/SUMPRODUCT(--($D11:$D59>=$K62),--($D11:$D59<=$L62),Z11:Z59)),0)*(1+$F62) -> 193.01836 | ... BO62: =IFERROR(IF(BO6>$L62,0, SUMPRODUCT(BO11:BO59,--($D11:$D59>=$K62),--($D11:$D59<=$L62),BN11:BN59)/SUMPRODUCT(--($D11:$D59>=$K62),--($D11:$D59<=$L62),BN11:BN59)),0)*(1+$F62) -> 0
B63: Retention, as a % of initial cohort size | C63: % | H63: average | I63: =IF(H63=Forecast!$H$195,T63,IF(H63=Forecast!$H$196,BO63,IF(H63=Forecast!$H$197,SUM(T63:BO63),IF(H63=Forecast!$H$198,AVERAGE(T63:BO63),0)))) -> 0.084397104 | T63: =IFERROR(T62/$T62,0) -> 1 | U63: =IFERROR(U62/$T62,0) -> 0.64761384 | V63: =IFERROR(V62/$T62,0) -> 0.586256 | W63: =IFERROR(W62/$T62,0) -> 0.42200024 | X63: =IFERROR(X62/$T62,0) -> 0.32424205 | Y63: =IFERROR(Y62/$T62,0) -> 0.24920418 | Z63: =IFERROR(Z62/$T62,0) -> 0.19158545 | AA63: =IFERROR(AA62/$T62,0) -> 0.14732616 | ... BO63: =IFERROR(BO62/$T62,0) -> 0
B64: Retention, on a 1 # basis | C64: # | H64: sum | I64: =IF(H64=Forecast!$H$195,T64,IF(H64=Forecast!$H$196,BO64,IF(H64=Forecast!$H$197,SUM(T64:BO64),IF(H64=Forecast!$H$198,AVERAGE(T64:BO64),0)))) -> 4.051061 | S64: 1 | T64: =IFERROR(T62/$T62,0) -> 1 | U64: =IFERROR(U62/$T62,0) -> 0.64761384 | V64: =IFERROR(V62/$T62,0) -> 0.586256 | W64: =IFERROR(W62/$T62,0) -> 0.42200024 | X64: =IFERROR(X62/$T62,0) -> 0.32424205 | Y64: =IFERROR(Y62/$T62,0) -> 0.24920418 | Z64: =IFERROR(Z62/$T62,0) -> 0.19158545 | AA64: =IFERROR(AA62/$T62,0) -> 0.14732616 | ... BO64: =IFERROR(BO62/$T62,0) -> 0
B65: Retention, as a % change from previous period | C65: % | H65: average | I65: =IF(H65=Forecast!$H$195,T65,IF(H65=Forecast!$H$196,BO65,IF(H65=Forecast!$H$197,SUM(T65:BO65),IF(H65=Forecast!$H$198,AVERAGE(T65:BO65),0)))) -> -0.14186166 | T65: =IFERROR((T64-S64)/S64,0) -> 0 | U65: =IFERROR((U64-T64)/T64,0) -> -0.35238616 | V65: =IFERROR((V64-U64)/U64,0) -> -0.094744477 | W65: =IFERROR((W64-V64)/V64,0) -> -0.28017753 | X65: =IFERROR((X64-W64)/W64,0) -> -0.23165434 | Y65: =IFERROR((Y64-X64)/X64,0) -> -0.23142549 | Z65: =IFERROR((Z64-Y64)/Y64,0) -> -0.23121091 | AA65: =IFERROR((AA64-Z64)/Z64,0) -> -0.23101595 | ... BO65: =IFERROR((BO64-BN64)/BN64,0) -> 0

Sheet Impact assumptions
C2: Scenario controls | illustrative, not Mauli actuals
C4: Scenario: 1 Low / 2 Base / 3 High | D4: 2 | G4: All scenario values are illustrative planning assumptions.
C5: Benefit multiplier | sensitivity input | D5: 1 | G5: Change one selector; forecast and summary update together.
C6: Cost multiplier | sensitivity input | D6: 1 | G6: Blue = editable. Green = linked. Amber = input.
C7: Required inputs / bounds status | D7: =IF(AND(COUNT(D13:D31)=19,COUNT(D35,D40,D45,D50,D55,D60,D65,D70,D75,D80,D85,D90,D95,D100,D105,D110,D115,D120,D125,D130,D135,D140)=22),IF(AND(D13>=0,D14>-1,D15>=0,D15<=1,D16>=0,D17>=0,D18>=0,D18<=1,D19>=0,D20>=0,D20<=1,D21>=0,D21<=1,D22>=0,D23>=0,D23<=1,D24>=0,D25>=0,D26>=0,D27>=0,D28>=0,D28<=1,D29>=0,D29<=6,D29=INT(D29),D30>=0,D31>-1,D5>=0,D6>=0,D35>=1,D35=INT(D35),D40>=1,D45>=0,D45<=1,D70>=0,D70<=1,D115=INT(D115),D115>=0,D115<=1,D120>=0,D120<=1,D75>=0,D80>=0,D85>=0,D90>=0,D95>=0,D100>=0,D105>=0,D110>=0,D125>=0,D130>=0,D135>=0,D140>=0),"Ready","Invalid bounds"),"Incomplete") -> Ready
C8: Data mode: 1 Demo / 2 Client inputs | D8: 1
C9: Assumed first forecast month | D9: 46327 | G9: Sensitivity | 24-month incremental cash (£)
C10: Selected case | D10: =CHOOSE(D4,"Low","Base","High") -> Base | G10: Cost mulitplier | H10: benefit
G11: ='Impact summary'!D15 -> 13823.001 | H11: 0 | I11: 0.5 | J11: 1 | K11: 1.5 | L11: 2
C12: Baseline driver | D12: Active | E12: Demo | G12: 0.5 | H12: -17550 | I12: -3167.6739 | J12: 11591.263 | K12: 26733.779 | L12: 42266.901
C13: Eligible non-customer sessions / month | D13: =IF($D$8=1,IF(ISNUMBER(E13),E13,"Not supplied"),IF(ISNUMBER('Impact actual inputs'!D7),'Impact actual inputs'!D7,"Not supplied")) -> 10000 | E13: 10000 | G13: 0.75 | H13: -26325 | I13: -11942.674 | J13: 2816.2633 | K13: 17958.779 | L13: 33491.901
C14: Monthly session growth | D14: =IF($D$8=1,IF(ISNUMBER(E14),E14,"Not supplied"),IF(ISNUMBER('Impact actual inputs'!D8),'Impact actual inputs'!D8,"Not supplied")) -> 0.05 | E14: 0.05 | G14: 1 | H14: -35100 | I14: -20717.674 | J14: -5958.7367 | K14: 9183.7786 | L14: 24716.901
C15: New-buyer conversion | D15: =IF($D$8=1,IF(ISNUMBER(E15),E15,"Not supplied"),IF(ISNUMBER('Impact actual inputs'!D9),'Impact actual inputs'!D9,"Not supplied")) -> 0.02 | E15: 0.02 | G15: 1.25 | H15: -43875 | I15: -29492.674 | J15: -14733.737 | K15: 408.77864 | L15: 15941.901
C16: Opening active prior-buyer pool | D16: =IF($D$8=1,IF(ISNUMBER(E16),E16,"Not supplied"),IF(ISNUMBER('Impact actual inputs'!D10),'Impact actual inputs'!D10,"Not supplied")) -> 1000 | E16: 1000 | G16: 1.5 | H16: -52650 | I16: -38267.674 | J16: -23508.737 | K16: -8366.2214 | L16: 7166.9011
C17: Monthly repeat orders / active buyer | D17: =IF($D$8=1,IF(ISNUMBER(E17),E17,"Not supplied"),IF(ISNUMBER('Impact actual inputs'!D11),'Impact actual inputs'!D11,"Not supplied")) -> 0.04 | E17: 0.04
C18: Monthly active-pool attrition | D18: =IF($D$8=1,IF(ISNUMBER(E18),E18,"Not supplied"),IF(ISNUMBER('Impact actual inputs'!D12),'Impact actual inputs'!D12,"Not supplied")) -> 0.02 | E18: 0.02 | G18: Benefit multiplier across; cost multiplier down.
C19: D2C basket after discounts, before refunds | D19: =IF($D$8=1,IF(ISNUMBER(E19),E19,"Not supplied"),IF(ISNUMBER('Impact actual inputs'!D13),'Impact actual inputs'!D13,"Not supplied")) -> 80 | E19: 80 | G19: No benefit (0) eliminates every assumed commercial uplift.
C20: Merchandise refund fraction | D20: =IF($D$8=1,IF(ISNUMBER(E20),E20,"Not supplied"),IF(ISNUMBER('Impact actual inputs'!D14),'Impact actual inputs'!D14,"Not supplied")) -> 0.04 | E20: 0.04 | G20: Refresh in Excel with Automatic calculation, including Data Tables.
C21: Product cost / gross merchandise | D21: =IF($D$8=1,IF(ISNUMBER(E21),E21,"Not supplied"),IF(ISNUMBER('Impact actual inputs'!D15),'Impact actual inputs'!D15,"Not supplied")) -> 0.3 | E21: 0.3
C22: Fulfilment / order | D22: =IF($D$8=1,IF(ISNUMBER(E22),E22,"Not supplied"),IF(ISNUMBER('Impact actual inputs'!D16),'Impact actual inputs'!D16,"Not supplied")) -> 5 | E22: 5
C23: Payment + commission / gross merchandise | D23: =IF($D$8=1,IF(ISNUMBER(E23),E23,"Not supplied"),IF(ISNUMBER('Impact actual inputs'!D17),'Impact actual inputs'!D17,"Not supplied")) -> 0.03 | E23: 0.03
C24: Variable service / order | D24: =IF($D$8=1,IF(ISNUMBER(E24),E24,"Not supplied"),IF(ISNUMBER('Impact actual inputs'!D18),'Impact actual inputs'!D18,"Not supplied")) -> 1 | E24: 1
C25: Baseline monthly acquisition spend | D25: =IF($D$8=1,IF(ISNUMBER(E25),E25,"Not supplied"),IF(ISNUMBER('Impact actual inputs'!D19),'Impact actual inputs'!D19,"Not supplied")) -> 2000 | E25: 2000
C26: Baseline fixed monthly operating costs | D26: =IF($D$8=1,IF(ISNUMBER(E26),E26,"Not supplied"),IF(ISNUMBER('Impact actual inputs'!D20),'Impact actual inputs'!D20,"Not supplied")) -> 6000 | E26: 6000
C27: Baseline B2B monthly net sales | D27: =IF($D$8=1,IF(ISNUMBER(E27),E27,"Not supplied"),IF(ISNUMBER('Impact actual inputs'!D21),'Impact actual inputs'!D21,"Not supplied")) -> 5000 | E27: 5000
C28: B2B contribution margin | D28: =IF($D$8=1,IF(ISNUMBER(E28),E28,"Not supplied"),IF(ISNUMBER('Impact actual inputs'!D22),'Impact actual inputs'!D22,"Not supplied")) -> 0.45 | E28: 0.45
C29: B2B collection delay, whole months | D29: =IF($D$8=1,IF(ISNUMBER(E29),E29,"Not supplied"),IF(ISNUMBER('Impact actual inputs'!D23),'Impact actual inputs'!D23,"Not supplied")) -> 1 | E29: 1
C30: Cost funding buffer, months | D30: =IF($D$8=1,IF(ISNUMBER(E30),E30,"Not supplied"),IF(ISNUMBER('Impact actual inputs'!D24),'Impact actual inputs'!D24,"Not supplied")) -> 0.5 | E30: 0.5
C31: Annual discount rate | D31: =IF($D$8=1,IF(ISNUMBER(E31),E31,"Not supplied"),IF(ISNUMBER('Impact actual inputs'!D25),'Impact actual inputs'!D25,"Not supplied")) -> 0.12 | E31: 0.12
C35: Launch month | Active | D35: =IF(CHOOSE($D$4,ISNUMBER(D36),ISNUMBER(D37),ISNUMBER(D38)),CHOOSE($D$4,D36,D37,D38),"Not supplied") -> 3 | G35: First month in 1–24. Beyond 24 = no launch in horizon.
C36: Low | D36: 5
C37: Base | D37: 3
C38: High | D38: 2
C40: Ramp months to maximum adoption | Active | D40: =IF(CHOOSE($D$4,ISNUMBER(D41),ISNUMBER(D42),ISNUMBER(D43)),CHOOSE($D$4,D41,D42,D43),"Not supplied") -> 4 | G40: At least one month; linear ramp from launch.
C41: Low | D41: 6
C42: Base | D42: 4
C43: High | D43: 3
C45: Maximum eligible adoption | Active | D45: =IF(CHOOSE($D$4,ISNUMBER(D46),ISNUMBER(D47),ISNUMBER(D48)),CHOOSE($D$4,D46,D47,D48),"Not supplied") -> 0.6 | G45: Fraction reached at saturation, not all visitors.
C46: Low | D46: 0.35
C47: Base | D47: 0.6
C48: High | D48: 0.8
C50: Traffic relative lift at full adoption | Active | D50: =IF(CHOOSE($D$4,ISNUMBER(D51),ISNUMBER(D52),ISNUMBER(D53)),CHOOSE($D$4,D51,D52,D53),"Not supplied") -> 0.06 | G50: Incremental eligible sessions; no causal prediction.
C51: Low | D51: 0
C52: Base | D52: 0.06
C53: High | D53: 0.12
C55: Conversion relative lift at full adoption | Active | D55: =IF(CHOOSE($D$4,ISNUMBER(D56),ISNUMBER(D57),ISNUMBER(D58)),CHOOSE($D$4,D56,D57,D58),"Not supplied") -> 0.08 | G55: A 10% lift on 2% = 2.2%, not 12%.
C56: Low | D56: -0.03
C57: Base | D57: 0.08
C58: High | D58: 0.15
C60: Repeat frequency increase, percentage points | Active | D60: =IF(CHOOSE($D$4,ISNUMBER(D61),ISNUMBER(D62),ISNUMBER(D63)),CHOOSE($D$4,D61,D62,D63),"Not supplied") -> 0.005 | G60: Additive monthly order frequency increment.
C61: Low | D61: 0
C62: Base | D62: 0.005
C63: High | D63: 0.01
C65: Basket relative lift | Active | D65: =IF(CHOOSE($D$4,ISNUMBER(D66),ISNUMBER(D67),ISNUMBER(D68)),CHOOSE($D$4,D66,D67,D68),"Not supplied") -> 0.02 | G65: No compulsory bundle assumption.
C66: Low | D66: 0
C67: Base | D67: 0.02
C68: High | D68: 0.04
C70: Cannibalisation / non-incrementality | Active | D70: =IF(CHOOSE($D$4,ISNUMBER(D71),ISNUMBER(D72),ISNUMBER(D73)),CHOOSE($D$4,D71,D72,D73),"Not supplied") -> 0.2 | G70: Reduces all benefit channels including partner sales.
C71: Low | D71: 0.35
C72: Base | D72: 0.2
C73: High | D73: 0.1
C75: One-off design / research | Active | D75: =IF(CHOOSE($D$4,ISNUMBER(D76),ISNUMBER(D77),ISNUMBER(D78)),CHOOSE($D$4,D76,D77,D78),"Not supplied") -> 1600 | G75: Illustrative cash cost; include internal time at opportunity cost.
C76: Low | D76: 2000
C77: Base | D77: 1600
C78: High | D78: 1200
C80: One-off Shopify / tracking integration | Active | D80: =IF(CHOOSE($D$4,ISNUMBER(D81),ISNUMBER(D82),ISNUMBER(D83)),CHOOSE($D$4,D81,D82,D83),"Not supplied") -> 2000 | G80: Existing store enhancement only. Validate agency quote.
C81: Low | D81: 3000
C82: Base | D82: 2000
C83: High | D83: 1500
C85: One-off educational content | Active | D85: =IF(CHOOSE($D$4,ISNUMBER(D86),ISNUMBER(D87),ISNUMBER(D88)),CHOOSE($D$4,D86,D87,D88),"Not supplied") -> 1200 | G85: Production, rights and review.
C86: Low | D86: 1600
C87: Base | D87: 1200
C88: High | D88: 900
C90: One-off training / QA | Active | D90: =IF(CHOOSE($D$4,ISNUMBER(D91),ISNUMBER(D92),ISNUMBER(D93)),CHOOSE($D$4,D91,D92,D93),"Not supplied") -> 600 | G90: Accessibility, wellness content review and training.
C91: Low | D91: 900
C92: Base | D92: 600
C93: High | D93: 400
C95: Monthly tools / apps | Active | D95: =IF(CHOOSE($D$4,ISNUMBER(D96),ISNUMBER(D97),ISNUMBER(D98)),CHOOSE($D$4,D96,D97,D98),"Not supplied") -> 100 | G95: Starts at launch; no vendor price claim.
C96: Low | D96: 150
C97: Base | D97: 100
C98: High | D98: 80
C100: Monthly support / analyst labour | Active | D100: =IF(CHOOSE($D$4,ISNUMBER(D101),ISNUMBER(D102),ISNUMBER(D103)),CHOOSE($D$4,D101,D102,D103),"Not supplied") -> 350 | G100: Starts at launch; include opportunity cost.
C101: Low | D101: 500
C102: Base | D102: 350
C103: High | D103: 250
C105: Monthly ongoing content | Active | D105: =IF(CHOOSE($D$4,ISNUMBER(D106),ISNUMBER(D107),ISNUMBER(D108)),CHOOSE($D$4,D106,D107,D108),"Not supplied") -> 300 | G105: Starts at launch.
C106: Low | D106: 400
C107: Base | D107: 300
C108: High | D108: 250
C110: Monthly incremental paid marketing | Active | D110: =IF(CHOOSE($D$4,ISNUMBER(D111),ISNUMBER(D112),ISNUMBER(D113)),CHOOSE($D$4,D111,D112,D113),"Not supplied") -> 600 | G110: Starts at launch; do not also include this in CAC cost.
C111: Low | D111: 800
C112: Base | D112: 600
C113: High | D113: 500
C115: Voice enabled: 0 No / 1 Yes | Active | D115: =IF(CHOOSE($D$4,ISNUMBER(D116),ISNUMBER(D117),ISNUMBER(D118)),CHOOSE($D$4,D116,D117,D118),"Not supplied") -> 0 | G115: Optional; no API integration or vendor commitment.
C116: Low | D116: 0
C117: Base | D117: 0
C118: High | D118: 0
C120: Voice sessions / reached visitor | Active | D120: =IF(CHOOSE($D$4,ISNUMBER(D121),ISNUMBER(D122),ISNUMBER(D123)),CHOOSE($D$4,D121,D122,D123),"Not supplied") -> 0.1 | G120: Only relevant when enabled.
C121: Low | D121: 0.1
C122: Base | D122: 0.1
...

Sheet Impact summary
C2: Mauli | Incremental investment case
C4: Illustrative demo — replace inputs before client decisions.
C5: Case selected: | D5: ='Impact assumptions'!D10 -> Base | F5: =IF('Impact assumptions'!D8=1,"DEMO: fictional inputs","CLIENT INPUT MODE") -> DEMO: fictional inputs
C7: 24-month decision view | D7: Without | E7: With | F7: Incremental
C8: Net sales | D8: =IF('Impact assumptions'!D7="Ready",SUM('Impact forecast'!D21:AA21),"Not supplied") -> 1080110 | E8: =IF('Impact assumptions'!D7="Ready",SUM('Impact forecast'!D49:AA49),"Not supplied") -> 1167579.2 | F8: =IF(ISNUMBER(E8),E8-D8,"Not supplied") -> 87469.129
C9: Contribution before acquisition | D9: =IF('Impact assumptions'!D7="Ready",SUM('Impact forecast'!D27:AA27),"Not supplied") -> 609063.62 | E9: =IF('Impact assumptions'!D7="Ready",SUM('Impact forecast'!D55:AA55),"Not supplied") -> 659468.63 | F9: =IF(ISNUMBER(E9),E9-D9,"Not supplied") -> 50405.009
C10: Operating contribution before setup | D10: =IF('Impact assumptions'!D7="Ready",SUM('Impact forecast'!D30:AA30),"Not supplied") -> 417063.62 | E10: =IF('Impact assumptions'!D7="Ready",SUM('Impact forecast'!D61:AA61),"Not supplied") -> 437768.63 | F10: =IF(ISNUMBER(E10),E10-D10,"Not supplied") -> 20705.009
C11: One-off setup | D11: =0 -> 0 | E11: =IF('Impact assumptions'!D7="Ready",SUM('Impact forecast'!D67:AA67),"Not supplied") -> 5400 | F11: =IF(ISNUMBER(E11),E11-D11,"Not supplied") -> 5400
C12: Operating contribution after setup | D12: =IF('Impact assumptions'!D7="Ready",SUM('Impact forecast'!D30:AA30),"Not supplied") -> 417063.62 | E12: =IF(ISNUMBER(E10),E10-E11,"Not supplied") -> 432368.63 | F12: =IF(ISNUMBER(E12),E12-D12,"Not supplied") -> 15305.009
C15: Incremental operating cash, 24 months | D15: ='Impact forecast'!AA72 -> 13823.001 | F15: Pre-tax operating cash proxy; no terminal value.
C16: Peak incremental funding required | D16: =IF(ISNUMBER('Impact forecast'!AA72),MAX(0,-MIN('Impact forecast'!D72:AA72)),"Not supplied") -> 8394.8663 | F16: Largest cumulative cash deficit, starting at zero.
C17: NPV of incremental cash | D17: =IF(ISNUMBER('Impact forecast'!AA72),SUM('Impact forecast'!D73:AA73),"Not supplied") -> 10426.409
C18: First non-negative cumulative month | D18: =IF(ISNUMBER('Impact forecast'!AA72),IF(MIN('Impact forecast'!D75:AA75)=999,"Not reached",MIN('Impact forecast'!D75:AA75)),"Not supplied") -> 18 | F18: First crossing; later reversals remain visible in cash chart.
C19: Pilot investment, excluding working capital | D19: ='Impact forecast'!AA74 -> 35100
C20: Cash ROI = net incremental cash / investment | D20: =IF(ISNUMBER(D19),IF(D19=0,"n.a.",D15/D19),"Not supplied") -> 0.39381769 | F20: Not ROAS; denominator includes setup and all pilot running costs.
C21: No-benefit funding downside | D21: =IF(ISNUMBER('Impact forecast'!AA77),-MIN(0,'Impact forecast'!D77:AA77),"Not supplied") -> 35100 | F21: Same spend, all commercial benefits removed.
C22: Monthly break-even benefit at month 24 | D22: =IF(ISNUMBER('Impact forecast'!AA61),SUM('Impact forecast'!AA58:AA60),"Not supplied") -> 1350 | F22: Recurring incremental costs to cover before setup recovery.
C23: Month 24 contribution benefit | D23: ='Impact forecast'!AA65 -> 4106.6542
C27: Month | D27: Baseline net sales | E27: With net sales | F27: Cumulative cash
C28: =TEXT('Impact forecast'!D7,"mmm-yy") -> Nov-26 | D28: ='Impact forecast'!D21 -> 23432 | E28: ='Impact forecast'!D49 -> 23432 | F28: ='Impact forecast'!D72 -> -2700
C29: =TEXT('Impact forecast'!E7,"mmm-yy") -> Dec-26 | D29: ='Impact forecast'!E21 -> 24740.672 | E29: ='Impact forecast'!E49 -> 24740.672 | F29: ='Impact forecast'!E72 -> -2700
C30: =TEXT('Impact forecast'!F7,"mmm-yy") -> Jan-27 | D30: ='Impact forecast'!F21 -> 26107.036 | E30: ='Impact forecast'!F49 -> 26590.787 | F30: ='Impact forecast'!F72 -> -6646.6323
C31: =TEXT('Impact forecast'!G7,"mmm-yy") -> Feb-27 | D31: ='Impact forecast'!G21 -> 27534.132 | E31: ='Impact forecast'!G49 -> 28570.413 | F31: ='Impact forecast'!G72 -> -7590.6311
C32: =TEXT('Impact forecast'!H7,"mmm-yy") -> Mar-27 | D32: ='Impact forecast'!H21 -> 29025.148 | E32: ='Impact forecast'!H49 -> 30688.691 | F32: ='Impact forecast'!H72 -> -8188.9616
C33: =TEXT('Impact forecast'!I7,"mmm-yy") -> Apr-27 | D33: ='Impact forecast'!I21 -> 30583.428 | E33: ='Impact forecast'!I49 -> 32955.396 | F33: ='Impact forecast'!I72 -> -8394.8663
C34: =TEXT('Impact forecast'!J7,"mmm-yy") -> May-27 | D34: ='Impact forecast'!J21 -> 32212.482 | E34: ='Impact forecast'!J49 -> 34761.639 | F34: ='Impact forecast'!J72 -> -8320.011
C35: =TEXT('Impact forecast'!K7,"mmm-yy") -> Jun-27 | D35: ='Impact forecast'!K21 -> 33915.991 | E35: ='Impact forecast'!K49 -> 36649.689 | F35: ='Impact forecast'!K72 -> -8138.214
C36: =TEXT('Impact forecast'!L7,"mmm-yy") -> Jul-27 | D36: ='Impact forecast'!L21 -> 35697.817 | E36: ='Impact forecast'!L49 -> 38623.807 | F36: ='Impact forecast'!L72 -> -7844.9933
C37: =TEXT('Impact forecast'!M7,"mmm-yy") -> Aug-27 | D37: ='Impact forecast'!M21 -> 37562.015 | E37: ='Impact forecast'!M49 -> 40688.461 | F37: ='Impact forecast'!M72 -> -7435.6257
C38: =TEXT('Impact forecast'!N7,"mmm-yy") -> Sep-27 | D38: ='Impact forecast'!N21 -> 39512.836 | E38: ='Impact forecast'!N49 -> 42848.343 | F38: ='Impact forecast'!N72 -> -6905.1347
C39: =TEXT('Impact forecast'!O7,"mmm-yy") -> Oct-27 | D39: ='Impact forecast'!O21 -> 41554.743 | E39: ='Impact forecast'!O49 -> 45108.373 | F39: ='Impact forecast'!O72 -> -6248.2784
C40: =TEXT('Impact forecast'!P7,"mmm-yy") -> Nov-27 | D40: ='Impact forecast'!P21 -> 43692.421 | E40: ='Impact forecast'!P49 -> 47473.717 | F40: ='Impact forecast'!P72 -> -5459.5366
C41: =TEXT('Impact forecast'!Q7,"mmm-yy") -> Dec-27 | D41: ='Impact forecast'!Q21 -> 45930.784 | E41: ='Impact forecast'!Q49 -> 49949.794 | F41: ='Impact forecast'!Q72 -> -4533.0971
C42: =TEXT('Impact forecast'!R7,"mmm-yy") -> Jan-28 | D42: ='Impact forecast'!R21 -> 48274.991 | E42: ='Impact forecast'!R49 -> 52542.291 | F42: ='Impact forecast'!R72 -> -3462.8415
C43: =TEXT('Impact forecast'!S7,"mmm-yy") -> Feb-28 | D43: ='Impact forecast'!S21 -> 50730.454 | E43: ='Impact forecast'!S49 -> 55257.176 | F43: ='Impact forecast'!S72 -> -2242.3299
C44: =TEXT('Impact forecast'!T7,"mmm-yy") -> Mar-28 | D44: ='Impact forecast'!T21 -> 53302.856 | E44: ='Impact forecast'!T49 -> 58100.714 | F44: ='Impact forecast'!T72 -> -864.78563
C45: =TEXT('Impact forecast'!U7,"mmm-yy") -> Apr-28 | D45: ='Impact forecast'!U21 -> 55998.16 | E45: ='Impact forecast'!U49 -> 61079.48 | F45: ='Impact forecast'!U72 -> 676.92155
C46: =TEXT('Impact forecast'!V7,"mmm-yy") -> May-28 | D46: ='Impact forecast'!V21 -> 58822.627 | E46: ='Impact forecast'!V49 -> 64200.373 | F46: ='Impact forecast'!V72 -> 2390.2929
C47: =TEXT('Impact forecast'!W7,"mmm-yy") -> Jun-28 | D47: ='Impact forecast'!W21 -> 61782.826 | E47: ='Impact forecast'!W49 -> 67470.637 | F47: ='Impact forecast'!W72 -> 4283.2189
C48: =TEXT('Impact forecast'!X7,"mmm-yy") -> Jul-28 | D48: ='Impact forecast'!X21 -> 64885.653 | E48: ='Impact forecast'!X49 -> 70897.873 | F48: ='Impact forecast'!X72 -> 6363.9983
C49: =TEXT('Impact forecast'!Y7,"mmm-yy") -> Aug-28 | D49: ='Impact forecast'!Y21 -> 68138.348 | E49: ='Impact forecast'!Y49 -> 74490.06 | F49: ='Impact forecast'!Y72 -> 8641.3584
C50: =TEXT('Impact forecast'!Z7,"mmm-yy") -> Sep-28 | D50: ='Impact forecast'!Z21 -> 71548.51 | E50: ='Impact forecast'!Z49 -> 78255.575 | F50: ='Impact forecast'!Z72 -> 11124.476
C51: =TEXT('Impact forecast'!AA7,"mmm-yy") -> Oct-28 | D51: ='Impact forecast'!AA21 -> 75124.114 | E51: ='Impact forecast'!AA49 -> 82203.21 | F51: ='Impact forecast'!AA72 -> 13823.001
C54: Decision: replace demo assumptions, validate costs and design a controlled pilot before asserting impact.
C55: Actual results, client budget and approvals remain unknown. Model does not forecast a causal outcome.

Sheet Impact forecast
C2: 24-month forecast | baseline and intervention
C5: Case selected: | D5: ='Impact assumptions'!D10 -> Base
C7: Forecast month | D7: =EDATE('Impact assumptions'!$D$9,0) -> 46327 | E7: =EDATE('Impact assumptions'!$D$9,1) -> 46357 | F7: =EDATE('Impact assumptions'!$D$9,2) -> 46388 | G7: =EDATE('Impact assumptions'!$D$9,3) -> 46419 | H7: =EDATE('Impact assumptions'!$D$9,4) -> 46447 | I7: =EDATE('Impact assumptions'!$D$9,5) -> 46478 | J7: =EDATE('Impact assumptions'!$D$9,6) -> 46508 | K7: =EDATE('Impact assumptions'!$D$9,7) -> 46539 | L7: =EDATE('Impact assumptions'!$D$9,8) -> 46569 | M7: =EDATE('Impact assumptions'!$D$9,9) -> 46600 | N7: =EDATE('Impact assumptions'!$D$9,10) -> 46631 | O7: =EDATE('Impact assumptions'!$D$9,11) -> 46661 | P7: =EDATE('Impact assumptions'!$D$9,12) -> 46692 | Q7: =EDATE('Impact assumptions'!$D$9,13) -> 46722 | R7: =EDATE('Impact assumptions'!$D$9,14) -> 46753 | S7: =EDATE('Impact assumptions'!$D$9,15) -> 46784 | T7: =EDATE('Impact assumptions'!$D$9,16) -> 46813 | U7: =EDATE('Impact assumptions'!$D$9,17) -> 46844 | V7: =EDATE('Impact assumptions'!$D$9,18) -> 46874 | W7: =EDATE('Impact assumptions'!$D$9,19) -> 46905 | X7: =EDATE('Impact assumptions'!$D$9,20) -> 46935 | Y7: =EDATE('Impact assumptions'!$D$9,21) -> 46966 | Z7: =EDATE('Impact assumptions'!$D$9,22) -> 46997 | AA7: =EDATE('Impact assumptions'!$D$9,23) -> 47027
C8: Period index | D8: 1 | E8: 2 | F8: 3 | G8: 4 | H8: 5 | I8: 6 | J8: 7 | K8: 8 | L8: 9 | M8: 10 | N8: 11 | O8: 12 | P8: 13 | Q8: 14 | R8: 15 | S8: 16 | T8: 17 | U8: 18 | V8: 19 | W8: 20 | X8: 21 | Y8: 22 | Z8: 23 | AA8: 24
C10: WITHOUT recommendations | continuing business
C11: Eligible acquisition sessions | D11: =IF('Impact assumptions'!$D$7<>"Ready","Not supplied",'Impact assumptions'!$D$13*(1+'Impact assumptions'!$D$14)^(D8-1)) -> 10000 | E11: =IF('Impact assumptions'!$D$7<>"Ready","Not supplied",'Impact assumptions'!$D$13*(1+'Impact assumptions'!$D$14)^(E8-1)) -> 10500 | F11: =IF('Impact assumptions'!$D$7<>"Ready","Not supplied",'Impact assumptions'!$D$13*(1+'Impact assumptions'!$D$14)^(F8-1)) -> 11025 | G11: =IF('Impact assumptions'!$D$7<>"Ready","Not supplied",'Impact assumptions'!$D$13*(1+'Impact assumptions'!$D$14)^(G8-1)) -> 11576.25 | H11: =IF('Impact assumptions'!$D$7<>"Ready","Not supplied",'Impact assumptions'!$D$13*(1+'Impact assumptions'!$D$14)^(H8-1)) -> 12155.062 | I11: =IF('Impact assumptions'!$D$7<>"Ready","Not supplied",'Impact assumptions'!$D$13*(1+'Impact assumptions'!$D$14)^(I8-1)) -> 12762.816 | J11: =IF('Impact assumptions'!$D$7<>"Ready","Not supplied",'Impact assumptions'!$D$13*(1+'Impact assumptions'!$D$14)^(J8-1)) -> 13400.956 | K11: =IF('Impact assumptions'!$D$7<>"Ready","Not supplied",'Impact assumptions'!$D$13*(1+'Impact assumptions'!$D$14)^(K8-1)) -> 14071.004 | ... AA11: =IF('Impact assumptions'!$D$7<>"Ready","Not supplied",'Impact assumptions'!$D$13*(1+'Impact assumptions'!$D$14)^(AA8-1)) -> 30715.238
C12: New buyers / first orders | D12: =IF('Impact assumptions'!$D$7<>"Ready","Not supplied",D11*'Impact assumptions'!$D$15) -> 200 | E12: =IF('Impact assumptions'!$D$7<>"Ready","Not supplied",E11*'Impact assumptions'!$D$15) -> 210 | F12: =IF('Impact assumptions'!$D$7<>"Ready","Not supplied",F11*'Impact assumptions'!$D$15) -> 220.5 | G12: =IF('Impact assumptions'!$D$7<>"Ready","Not supplied",G11*'Impact assumptions'!$D$15) -> 231.525 | H12: =IF('Impact assumptions'!$D$7<>"Ready","Not supplied",H11*'Impact assumptions'!$D$15) -> 243.10125 | I12: =IF('Impact assumptions'!$D$7<>"Ready","Not supplied",I11*'Impact assumptions'!$D$15) -> 255.25631 | J12: =IF('Impact assumptions'!$D$7<>"Ready","Not supplied",J11*'Impact assumptions'!$D$15) -> 268.01913 | K12: =IF('Impact assumptions'!$D$7<>"Ready","Not supplied",K11*'Impact assumptions'!$D$15) -> 281.42008 | ... AA12: =IF('Impact assumptions'!$D$7<>"Ready","Not supplied",AA11*'Impact assumptions'!$D$15) -> 614.30475
C13: Opening active buyer pool | D13: =IF('Impact assumptions'!$D$7<>"Ready","Not supplied",'Impact assumptions'!$D$16) -> 1000 | E13: =IF('Impact assumptions'!$D$7<>"Ready","Not supplied",D16) -> 1176 | F13: =IF('Impact assumptions'!$D$7<>"Ready","Not supplied",E16) -> 1358.28 | G13: =IF('Impact assumptions'!$D$7<>"Ready","Not supplied",F16) -> 1547.2044 | H13: =IF('Impact assumptions'!$D$7<>"Ready","Not supplied",G16) -> 1743.1548 | I13: =IF('Impact assumptions'!$D$7<>"Ready","Not supplied",H16) -> 1946.5309 | J13: =IF('Impact assumptions'!$D$7<>"Ready","Not supplied",I16) -> 2157.7515 | K13: =IF('Impact assumptions'!$D$7<>"Ready","Not supplied",J16) -> 2377.2552 | L13: =IF('Impact assumptions'!$D$7<>"Ready","Not supplied",K16) -> 2605.5018 | ... AA13: =IF('Impact assumptions'!$D$7<>"Ready","Not supplied",Z16) -> 7469.2414
C14: Repeat orders | D14: =IF('Impact assumptions'!$D$7<>"Ready","Not supplied",D13*'Impact assumptions'!$D$17) -> 40 | E14: =IF('Impact assumptions'!$D$7<>"Ready","Not supplied",E13*'Impact assumptions'!$D$17) -> 47.04 | F14: =IF('Impact assumptions'!$D$7<>"Ready","Not supplied",F13*'Impact assumptions'!$D$17) -> 54.3312 | G14: =IF('Impact assumptions'!$D$7<>"Ready","Not supplied",G13*'Impact assumptions'!$D$17) -> 61.888176 | H14: =IF('Impact assumptions'!$D$7<>"Ready","Not supplied",H13*'Impact assumptions'!$D$17) -> 69.726192 | I14: =IF('Impact assumptions'!$D$7<>"Ready","Not supplied",I13*'Impact assumptions'!$D$17) -> 77.861238 | J14: =IF('Impact assumptions'!$D$7<>"Ready","Not supplied",J13*'Impact assumptions'!$D$17) -> 86.31006 | K14: =IF('Impact assumptions'!$D$7<>"Ready","Not supplied",K13*'Impact assumptions'!$D$17) -> 95.090209 | ... AA14: =IF('Impact assumptions'!$D$7<>"Ready","Not supplied",AA13*'Impact assumptions'!$D$17) -> 298.76966
C15: Total D2C orders | D15: =IF('Impact assumptions'!$D$7<>"Ready","Not supplied",SUM(D12,D14)) -> 240 | E15: =IF('Impact assumptions'!$D$7<>"Ready","Not supplied",SUM(E12,E14)) -> 257.04 | F15: =IF('Impact assumptions'!$D$7<>"Ready","Not supplied",SUM(F12,F14)) -> 274.8312 | G15: =IF('Impact assumptions'!$D$7<>"Ready","Not supplied",SUM(G12,G14)) -> 293.41318 | H15: =IF('Impact assumptions'!$D$7<>"Ready","Not supplied",SUM(H12,H14)) -> 312.82744 | I15: =IF('Impact assumptions'!$D$7<>"Ready","Not supplied",SUM(I12,I14)) -> 333.11755 | J15: =IF('Impact assumptions'!$D$7<>"Ready","Not supplied",SUM(J12,J14)) -> 354.32919 | K15: =IF('Impact assumptions'!$D$7<>"Ready","Not supplied",SUM(K12,K14)) -> 376.51029 | ... AA15: =IF('Impact assumptions'!$D$7<>"Ready","Not supplied",SUM(AA12,AA14)) -> 913.07441
C16: Closing active buyer pool | D16: =IF('Impact assumptions'!$D$7<>"Ready","Not supplied",SUM(D13,D12)*(1-'Impact assumptions'!$D$18)) -> 1176 | E16: =IF('Impact assumptions'!$D$7<>"Ready","Not supplied",SUM(E13,E12)*(1-'Impact assumptions'!$D$18)) -> 1358.28 | F16: =IF('Impact assumptions'!$D$7<>"Ready","Not supplied",SUM(F13,F12)*(1-'Impact assumptions'!$D$18)) -> 1547.2044 | G16: =IF('Impact assumptions'!$D$7<>"Ready","Not supplied",SUM(G13,G12)*(1-'Impact assumptions'!$D$18)) -> 1743.1548 | H16: =IF('Impact assumptions'!$D$7<>"Ready","Not supplied",SUM(H13,H12)*(1-'Impact assumptions'!$D$18)) -> 1946.5309 | I16: =IF('Impact assumptions'!$D$7<>"Ready","Not supplied",SUM(I13,I12)*(1-'Impact assumptions'!$D$18)) -> 2157.7515 | J16: =IF('Impact assumptions'!$D$7<>"Ready","Not supplied",SUM(J13,J12)*(1-'Impact assumptions'!$D$18)) -> 2377.2552 | K16: =IF('Impact assumptions'!$D$7<>"Ready","Not supplied",SUM(K13,K12)*(1-'Impact assumptions'!$D$18)) -> 2605.5018 | ... AA16: =IF('Impact assumptions'!$D$7<>"Ready","Not supplied",SUM(AA13,AA12)*(1-'Impact assumptions'!$D$18)) -> 7921.8752
C17: Gross D2C merchandise | D17: =IF('Impact assumptions'!$D$7<>"Ready","Not supplied",D15*'Impact assumptions'!$D$19) -> 19200 | E17: =IF('Impact assumptions'!$D$7<>"Ready","Not supplied",E15*'Impact assumptions'!$D$19) -> 20563.2 | F17: =IF('Impact assumptions'!$D$7<>"Ready","Not supplied",F15*'Impact assumptions'!$D$19) -> 21986.496 | G17: =IF('Impact assumptions'!$D$7<>"Ready","Not supplied",G15*'Impact assumptions'!$D$19) -> 23473.054 | H17: =IF('Impact assumptions'!$D$7<>"Ready","Not supplied",H15*'Impact assumptions'!$D$19) -> 25026.195 | I17: =IF('Impact assumptions'!$D$7<>"Ready","Not supplied",I15*'Impact assumptions'!$D$19) -> 26649.404 | J17: =IF('Impact assumptions'!$D$7<>"Ready","Not supplied",J15*'Impact assumptions'!$D$19) -> 28346.335 | K17: =IF('Impact assumptions'!$D$7<>"Ready","Not supplied",K15*'Impact assumptions'!$D$19) -> 30120.823 | ... AA17: =IF('Impact assumptions'!$D$7<>"Ready","Not supplied",AA15*'Impact assumptions'!$D$19) -> 73045.953
C18: Refunds | D18: =IF('Impact assumptions'!$D$7<>"Ready","Not supplied",D17*'Impact assumptions'!$D$20) -> 768 | E18: =IF('Impact assumptions'!$D$7<>"Ready","Not supplied",E17*'Impact assumptions'!$D$20) -> 822.528 | F18: =IF('Impact assumptions'!$D$7<>"Ready","Not supplied",F17*'Impact assumptions'!$D$20) -> 879.45984 | G18: =IF('Impact assumptions'!$D$7<>"Ready","Not supplied",G17*'Impact assumptions'!$D$20) -> 938.92216 | H18: =IF('Impact assumptions'!$D$7<>"Ready","Not supplied",H17*'Impact assumptions'!$D$20) -> 1001.0478 | I18: =IF('Impact assumptions'!$D$7<>"Ready","Not supplied",I17*'Impact assumptions'!$D$20) -> 1065.9762 | J18: =IF('Impact assumptions'!$D$7<>"Ready","Not supplied",J17*'Impact assumptions'!$D$20) -> 1133.8534 | K18: =IF('Impact assumptions'!$D$7<>"Ready","Not supplied",K17*'Impact assumptions'!$D$20) -> 1204.8329 | ... AA18: =IF('Impact assumptions'!$D$7<>"Ready","Not supplied",AA17*'Impact assumptions'!$D$20) -> 2921.8381
C19: D2C net sales | D19: =IF('Impact assumptions'!$D$7<>"Ready","Not supplied",D17-D18) -> 18432 | E19: =IF('Impact assumptions'!$D$7<>"Ready","Not supplied",E17-E18) -> 19740.672 | F19: =IF('Impact assumptions'!$D$7<>"Ready","Not supplied",F17-F18) -> 21107.036 | G19: =IF('Impact assumptions'!$D$7<>"Ready","Not supplied",G17-G18) -> 22534.132 | H19: =IF('Impact assumptions'!$D$7<>"Ready","Not supplied",H17-H18) -> 24025.148 | I19: =IF('Impact assumptions'!$D$7<>"Ready","Not supplied",I17-I18) -> 25583.428 | J19: =IF('Impact assumptions'!$D$7<>"Ready","Not supplied",J17-J18) -> 27212.482 | K19: =IF('Impact assumptions'!$D$7<>"Ready","Not supplied",K17-K18) -> 28915.991 | ... AA19: =IF('Impact assumptions'!$D$7<>"Ready","Not supplied",AA17-AA18) -> 70124.114
C20: B2B net sales | D20: =IF('Impact assumptions'!$D$7<>"Ready","Not supplied",'Impact assumptions'!$D$27) -> 5000 | E20: =IF('Impact assumptions'!$D$7<>"Ready","Not supplied",'Impact assumptions'!$D$27) -> 5000 | F20: =IF('Impact assumptions'!$D$7<>"Ready","Not supplied",'Impact assumptions'!$D$27) -> 5000 | G20: =IF('Impact assumptions'!$D$7<>"Ready","Not supplied",'Impact assumptions'!$D$27) -> 5000 | H20: =IF('Impact assumptions'!$D$7<>"Ready","Not supplied",'Impact assumptions'!$D$27) -> 5000 | I20: =IF('Impact assumptions'!$D$7<>"Ready","Not supplied",'Impact assumptions'!$D$27) -> 5000 | J20: =IF('Impact assumptions'!$D$7<>"Ready","Not supplied",'Impact assumptions'!$D$27) -> 5000 | K20: =IF('Impact assumptions'!$D$7<>"Ready","Not supplied",'Impact assumptions'!$D$27) -> 5000 | ... AA20: =IF('Impact assumptions'!$D$7<>"Ready","Not supplied",'Impact assumptions'!$D$27) -> 5000
C21: Total net sales | D21: =IF('Impact assumptions'!$D$7<>"Ready","Not supplied",SUM(D19:D20)) -> 23432 | E21: =IF('Impact assumptions'!$D$7<>"Ready","Not supplied",SUM(E19:E20)) -> 24740.672 | F21: =IF('Impact assumptions'!$D$7<>"Ready","Not supplied",SUM(F19:F20)) -> 26107.036 | G21: =IF('Impact assumptions'!$D$7<>"Ready","Not supplied",SUM(G19:G20)) -> 27534.132 | H21: =IF('Impact assumptions'!$D$7<>"Ready","Not supplied",SUM(H19:H20)) -> 29025.148 | I21: =IF('Impact assumptions'!$D$7<>"Ready","Not supplied",SUM(I19:I20)) -> 30583.428 | J21: =IF('Impact assumptions'!$D$7<>"Ready","Not supplied",SUM(J19:J20)) -> 32212.482 | K21: =IF('Impact assumptions'!$D$7<>"Ready","Not supplied",SUM(K19:K20)) -> 33915.991 | ... AA21: =IF('Impact assumptions'!$D$7<>"Ready","Not supplied",SUM(AA19:AA20)) -> 75124.114
C22: Product costs | D22: =IF('Impact assumptions'!$D$7<>"Ready","Not supplied",D17*'Impact assumptions'!$D$21) -> 5760 | E22: =IF('Impact assumptions'!$D$7<>"Ready","Not supplied",E17*'Impact assumptions'!$D$21) -> 6168.96 | F22: =IF('Impact assumptions'!$D$7<>"Ready","Not supplied",F17*'Impact assumptions'!$D$21) -> 6595.9488 | G22: =IF('Impact assumptions'!$D$7<>"Ready","Not supplied",G17*'Impact assumptions'!$D$21) -> 7041.9162 | H22: =IF('Impact assumptions'!$D$7<>"Ready","Not supplied",H17*'Impact assumptions'!$D$21) -> 7507.8586 | I22: =IF('Impact assumptions'!$D$7<>"Ready","Not supplied",I17*'Impact assumptions'!$D$21) -> 7994.8212 | J22: =IF('Impact assumptions'!$D$7<>"Ready","Not supplied",J17*'Impact assumptions'!$D$21) -> 8503.9005 | K22: =IF('Impact assumptions'!$D$7<>"Ready","Not supplied",K17*'Impact assumptions'!$D$21) -> 9036.247 | ... AA22: =IF('Impact assumptions'!$D$7<>"Ready","Not supplied",AA17*'Impact assumptions'!$D$21) -> 21913.786
C23: Fulfilment | D23: =IF('Impact assumptions'!$D$7<>"Ready","Not supplied",D15*'Impact assumptions'!$D$22) -> 1200 | E23: =IF('Impact assumptions'!$D$7<>"Ready","Not supplied",E15*'Impact assumptions'!$D$22) -> 1285.2 | F23: =IF('Impact assumptions'!$D$7<>"Ready","Not supplied",F15*'Impact assumptions'!$D$22) -> 1374.156 | G23: =IF('Impact assumptions'!$D$7<>"Ready","Not supplied",G15*'Impact assumptions'!$D$22) -> 1467.0659 | H23: =IF('Impact assumptions'!$D$7<>"Ready","Not supplied",H15*'Impact assumptions'!$D$22) -> 1564.1372 | I23: =IF('Impact assumptions'!$D$7<>"Ready","Not supplied",I15*'Impact assumptions'!$D$22) -> 1665.5878 | J23: =IF('Impact assumptions'!$D$7<>"Ready","Not supplied",J15*'Impact assumptions'!$D$22) -> 1771.6459 | K23: =IF('Impact assumptions'!$D$7<>"Ready","Not supplied",K15*'Impact assumptions'!$D$22) -> 1882.5515 | ... AA23: =IF('Impact assumptions'!$D$7<>"Ready","Not supplied",AA15*'Impact assumptions'!$D$22) -> 4565.372
C24: Payment / commission | D24: =IF('Impact assumptions'!$D$7<>"Ready","Not supplied",D17*'Impact assumptions'!$D$23) -> 576 | E24: =IF('Impact assumptions'!$D$7<>"Ready","Not supplied",E17*'Impact assumptions'!$D$23) -> 616.896 | F24: =IF('Impact assumptions'!$D$7<>"Ready","Not supplied",F17*'Impact assumptions'!$D$23) -> 659.59488 | G24: =IF('Impact assumptions'!$D$7<>"Ready","Not supplied",G17*'Impact assumptions'!$D$23) -> 704.19162 | H24: =IF('Impact assumptions'!$D$7<>"Ready","Not supplied",H17*'Impact assumptions'!$D$23) -> 750.78586 | I24: =IF('Impact assumptions'!$D$7<>"Ready","Not supplied",I17*'Impact assumptions'!$D$23) -> 799.48212 | J24: =IF('Impact assumptions'!$D$7<>"Ready","Not supplied",J17*'Impact assumptions'!$D$23) -> 850.39005 | K24: =IF('Impact assumptions'!$D$7<>"Ready","Not supplied",K17*'Impact assumptions'!$D$23) -> 903.6247 | ... AA24: =IF('Impact assumptions'!$D$7<>"Ready","Not supplied",AA17*'Impact assumptions'!$D$23) -> 2191.3786
C25: Variable service | D25: =IF('Impact assumptions'!$D$7<>"Ready","Not supplied",D15*'Impact assumptions'!$D$24) -> 240 | E25: =IF('Impact assumptions'!$D$7<>"Ready","Not supplied",E15*'Impact assumptions'!$D$24) -> 257.04 | F25: =IF('Impact assumptions'!$D$7<>"Ready","Not supplied",F15*'Impact assumptions'!$D$24) -> 274.8312 | G25: =IF('Impact assumptions'!$D$7<>"Ready","Not supplied",G15*'Impact assumptions'!$D$24) -> 293.41318 | H25: =IF('Impact assumptions'!$D$7<>"Ready","Not supplied",H15*'Impact assumptions'!$D$24) -> 312.82744 | I25: =IF('Impact assumptions'!$D$7<>"Ready","Not supplied",I15*'Impact assumptions'!$D$24) -> 333.11755 | J25: =IF('Impact assumptions'!$D$7<>"Ready","Not supplied",J15*'Impact assumptions'!$D$24) -> 354.32919 | K25: =IF('Impact assumptions'!$D$7<>"Ready","Not supplied",K15*'Impact assumptions'!$D$24) -> 376.51029 | ... AA25: =IF('Impact assumptions'!$D$7<>"Ready","Not supplied",AA15*'Impact assumptions'!$D$24) -> 913.07441
C26: B2B variable costs | D26: =IF('Impact assumptions'!$D$7<>"Ready","Not supplied",D20*(1-'Impact assumptions'!$D$28)) -> 2750 | E26: =IF('Impact assumptions'!$D$7<>"Ready","Not supplied",E20*(1-'Impact assumptions'!$D$28)) -> 2750 | F26: =IF('Impact assumptions'!$D$7<>"Ready","Not supplied",F20*(1-'Impact assumptions'!$D$28)) -> 2750 | G26: =IF('Impact assumptions'!$D$7<>"Ready","Not supplied",G20*(1-'Impact assumptions'!$D$28)) -> 2750 | H26: =IF('Impact assumptions'!$D$7<>"Ready","Not supplied",H20*(1-'Impact assumptions'!$D$28)) -> 2750 | I26: =IF('Impact assumptions'!$D$7<>"Ready","Not supplied",I20*(1-'Impact assumptions'!$D$28)) -> 2750 | J26: =IF('Impact assumptions'!$D$7<>"Ready","Not supplied",J20*(1-'Impact assumptions'!$D$28)) -> 2750 | K26: =IF('Impact assumptions'!$D$7<>"Ready","Not supplied",K20*(1-'Impact assumptions'!$D$28)) -> 2750 | ... AA26: =IF('Impact assumptions'!$D$7<>"Ready","Not supplied",AA20*(1-'Impact assumptions'!$D$28)) -> 2750
